Workbook

Sheet Designs
A1: Sno | B1: design_name | C1: design_code | D1: published | E1: active | F1: Selling price | G1: Light | H1: Cabinets | I1: 3 shelf backpanel | J1: Square | K1: Rectangle | L1: Shelf | N1: Final Price | O1: L Profile color | P1: Trim | Q1: Sqaure | R1: Rectangle | S1: Shelf | T1: Cost | U1: Selling price after discount | V1: Transport cost | W1: CP cost | X1: Margin
A2: 1 | B2: BR-1-1 | C2: BR-1-1 | D2: No | E2: Yes | F2: =VLOOKUP(C2, 'Pivot Table 2'!$A$1:$B$123, 2, FALSE) -> 5000 | G2: 0 | H2: 0 | I2: 0 | J2: 0 | N2: =F2+G2*4*1000+H2*10000+1*1500*I2+1*J2*1000+1*K2*1000+1*L2*1000 -> 5000 | T2: =VLOOKUP(C2, 'Pivot Table 2'!$A$1:$C$119, 3, FALSE) -> 2736 | U2: =(1-AA$6)*F2 -> 3000 | V2: =$AA$7 -> 500 | W2: =$AA$8 -> 4500 | X2: =U2-T2-V2-W2 -> -4736
A3: 2 | B3: BR-1-2 | C3: BR-1-2 | D3: No | E3: Yes | F3: =VLOOKUP(C3, 'Pivot Table 2'!$A$1:$B$123, 2, FALSE) -> 5000 | G3: 0 | H3: 0 | I3: 0 | J3: 0 | N3: =F3+G3*4*1000+H3*10000+1*1500*I3+1*J3*1000+1*K3*1000+1*L3*1000 -> 5000 | T3: =VLOOKUP(C3, 'Pivot Table 2'!$A$1:$C$119, 3, FALSE) -> 2736 | U3: =(1-AA$6)*F3 -> 3000 | V3: =$AA$7 -> 500 | W3: =$AA$8 -> 4500 | X3: =U3-T3-V3-W3 -> -4736
A4: 3 | B4: BR-2-1 | C4: BR-2-1 | D4: No | E4: Yes | F4: =VLOOKUP(C4, 'Pivot Table 2'!$A$1:$B$123, 2, FALSE) -> 5000 | G4: 0 | H4: 0 | I4: 0 | J4: 0 | N4: =F4+G4*4*1000+H4*10000+1*1500*I4+1*J4*1000+1*K4*1000+1*L4*1000 -> 5000 | T4: =VLOOKUP(C4, 'Pivot Table 2'!$A$1:$C$119, 3, FALSE) -> 2736 | U4: =(1-AA$6)*F4 -> 3000 | V4: =$AA$7 -> 500 | W4: =$AA$8 -> 4500 | X4: =U4-T4-V4-W4 -> -4736
A5: 4 | B5: BR-2-2 | C5: BR-2-2 | D5: No | E5: Yes | F5: =VLOOKUP(C5, 'Pivot Table 2'!$A$1:$B$123, 2, FALSE) -> 5000 | G5: 0 | H5: 0 | I5: 0 | J5: 0 | N5: =F5+G5*4*1000+H5*10000+1*1500*I5+1*J5*1000+1*K5*1000+1*L5*1000 -> 5000 | T5: =VLOOKUP(C5, 'Pivot Table 2'!$A$1:$C$119, 3, FALSE) -> 2736 | U5: =(1-AA$6)*F5 -> 3000 | V5: =$AA$7 -> 500 | W5: =$AA$8 -> 4500 | X5: =U5-T5-V5-W5 -> -4736
A6: 5 | B6: Noctis Haven (BR-3-1) | C6: BR-3-1 | D6: Yes | E6: Yes | F6: =VLOOKUP(C6, 'Pivot Table 2'!$A$1:$B$123, 2, FALSE) -> 26500 | G6: 0 | H6: 0 | I6: 0 | J6: 0 | K6: 0 | L6: 0 | M6: NA | N6: =F6+G6*4*1000+H6*10000+1*1500*I6+1*J6*1000+1*K6*1000+1*L6*1000 -> 26500 | O6: WHSWBIW08S223 | P6: No | Q6: 0 | R6: 0 | S6: 0 | T6: =VLOOKUP(C6, 'Pivot Table 2'!$A$1:$C$119, 3, FALSE) -> 13826.339 | U6: =(1-AA$6)*F6 -> 15900 | V6: =$AA$7 -> 500 | W6: =$AA$8 -> 4500 | X6: =U6-T6-V6-W6 -> -2926.339 | Y6: =25% -> 0.25 | Z6: Discount | AA6: =40% -> 0.4
A7: 6 | B7: Caelum Nest (BR-3-2) | C7: BR-3-2 | D7: Yes | E7: Yes | F7: =VLOOKUP(C7, 'Pivot Table 2'!$A$1:$B$123, 2, FALSE) -> 24000 | G7: 0 | H7: 0 | I7: 0 | J7: 0 | K7: 0 | L7: 0 | M7: NA | N7: =F7+G7*4*1000+H7*10000+1*1500*I7+1*J7*1000+1*K7*1000+1*L7*1000 -> 24000 | O7: WHSWBIW01S216 | P7: No | Q7: 0 | R7: 0 | S7: 0 | T7: =VLOOKUP(C7, 'Pivot Table 2'!$A$1:$C$119, 3, FALSE) -> 12503.966 | U7: =(1-AA$6)*F7 -> 14400 | V7: =$AA$7 -> 500 | W7: =$AA$8 -> 4500 | X7: =U7-T7-V7-W7 -> -3103.9661 | Y7: =25% -> 0.25 | Z7: Transport | AA7: =500 -> 500
A8: 7 | B8: Amber Silence (BR-4-1) | C8: BR-4-1 | D8: Yes | E8: Yes | F8: =VLOOKUP(C8, 'Pivot Table 2'!$A$1:$B$123, 2, FALSE) -> 34500 | G8: 0 | H8: 0 | I8: 0 | J8: 2 | K8: 1 | L8: 0 | M8: Light | N8: =F8+G8*4*1000+H8*10000+1*1500*I8+1*J8*1000+1*K8*1000+1*L8*1000 -> 37500 | O8: WHSWBIW01S216 | P8: No | Q8: WHSWSSBWBLWS171 | R8: WHSWSRBWBLWS181 | S8: 0 | T8: =VLOOKUP(C8, 'Pivot Table 2'!$A$1:$C$119, 3, FALSE) -> 17164.644 | U8: =(1-AA$6)*F8 -> 20700 | V8: =$AA$7 -> 500 | W8: =$AA$8 -> 4500 | X8: =U8-T8-V8-W8 -> -1464.6441 | Y8: =35% -> 0.35 | Z8: CP cost | AA8: =4500 -> 4500 | AB8: =AA8/(9.5*10) -> 47.368421
A9: 8 | B9: Elaris Woodline (BR-4-2) | C9: BR-4-2 | D9: Yes | E9: Yes | F9: =VLOOKUP(C9, 'Pivot Table 2'!$A$1:$B$123, 2, FALSE) -> 39500 | G9: 0 | H9: 0 | I9: 0 | J9: 2 | K9: 1 | L9: 0 | M9: Light | N9: =F9+G9*4*1000+H9*10000+1*1500*I9+1*J9*1000+1*K9*1000+1*L9*1000 -> 42500 | O9: WHSWBIW03S218 | P9: No | Q9: WHSWSSBWBLWS171 | R9: WHSWSRBWBLWS181 | S9: 0 | T9: =VLOOKUP(C9, 'Pivot Table 2'!$A$1:$C$119, 3, FALSE) -> 20893.458 | U9: =(1-AA$6)*F9 -> 23700 | V9: =$AA$7 -> 500 | W9: =$AA$8 -> 4500 | X9: =U9-T9-V9-W9 -> -2193.4576 | Y9: =35% -> 0.35
A10: 9 | B10: BR-5-1 | C10: BR-5-1 | D10: No | E10: Yes | F10: =VLOOKUP(C10, 'Pivot Table 2'!$A$1:$B$123, 2, FALSE) -> 35000 | G10: 0 | H10: 0 | I10: 0 | J10: 0 | N10: =F10+G10*4*1000+H10*10000+1*1500*I10+1*J10*1000+1*K10*1000+1*L10*1000 -> 35000 | T10: =VLOOKUP(C10, 'Pivot Table 2'!$A$1:$C$119, 3, FALSE) -> 17636.339 | U10: =(1-AA$6)*F10 -> 21000 | V10: =$AA$7 -> 500 | W10: =$AA$8 -> 4500 | X10: =U10-T10-V10-W10 -> -1636.339
A11: 10 | B11: BR-5-2 | C11: BR-5-2 | D11: No | E11: Yes | F11: =VLOOKUP(C11, 'Pivot Table 2'!$A$1:$B$123, 2, FALSE) -> 35000 | G11: 0 | H11: 0 | I11: 0 | J11: 0 | N11: =F11+G11*4*1000+H11*10000+1*1500*I11+1*J11*1000+1*K11*1000+1*L11*1000 -> 35000 | T11: =VLOOKUP(C11, 'Pivot Table 2'!$A$1:$C$119, 3, FALSE) -> 14653.288 | U11: =(1-AA$6)*F11 -> 21000 | V11: =$AA$7 -> 500 | W11: =$AA$8 -> 4500 | X11: =U11-T11-V11-W11 -> 1346.7119
A12: 11 | B12: Solstice Haven (BR-6-1) | C12: BR-6-1 | D12: Yes | E12: Yes | F12: =VLOOKUP(C12, 'Pivot Table 2'!$A$1:$B$123, 2, FALSE) -> 63000 | G12: 0 | H12: 0 | I12: 0 | J12: 4 | K12: 0 | L12: 0 | M12: Light | N12: =F12+G12*4*1000+H12*10000+1*1500*I12+1*J12*1000+1*K12*1000+1*L12*1000 -> 67000 | O12: WHSWBIW02S217 | P12: ?? | Q12: WHSWSSBWBLWS171 | R12: 0 | S12: 0 | T12: =VLOOKUP(C12, 'Pivot Table 2'!$A$1:$C$119, 3, FALSE) -> 29897.864 | U12: =(1-AA$6)*F12 -> 37800 | V12: =$AA$7 -> 500 | W12: =$AA$8 -> 4500 | X12: =U12-T12-V12-W12 -> 2902.1356 | Y12: =40% -> 0.4
A13: 12 | B13: Morvane Essence (BR-6-2) | C13: BR-6-2 | D13: Yes | E13: Yes | F13: =VLOOKUP(C13, 'Pivot Table 2'!$A$1:$B$123, 2, FALSE) -> 53000 | G13: 0 | H13: 0 | I13: 0 | J13: 4 | K13: 0 | L13: 0 | M13: Light | N13: =F13+G13*4*1000+H13*10000+1*1500*I13+1*J13*1000+1*K13*1000+1*L13*1000 -> 57000 | O13: WHSWBIW01S216 | P13: No | Q13: WHSWSSBWBLWS171 | R13: 0 | S13: 0 | T13: =VLOOKUP(C13, 'Pivot Table 2'!$A$1:$C$119, 3, FALSE) -> 25695.831 | U13: =(1-AA$6)*F13 -> 31800 | V13: =$AA$7 -> 500 | W13: =$AA$8 -> 4500 | X13: =U13-T13-V13-W13 -> 1104.1695 | Y13: =40% -> 0.4
A14: 13 | B14: BR-7-1 | C14: BR-7-1 | D14: No | E14: Yes | F14: =VLOOKUP(C14, 'Pivot Table 2'!$A$1:$B$123, 2, FALSE) -> 35000 | G14: 0 | H14: 0 | I14: 0 | J14: 0 | N14: =F14+G14*4*1000+H14*10000+1*1500*I14+1*J14*1000+1*K14*1000+1*L14*1000 -> 35000 | T14: =VLOOKUP(C14, 'Pivot Table 2'!$A$1:$C$119, 3, FALSE) -> 14925.831 | U14: =(1-AA$6)*F14 -> 21000 | V14: =$AA$7 -> 500 | W14: =$AA$8 -> 4500 | X14: =U14-T14-V14-W14 -> 1074.1695
A15: 14 | B15: BR-7-2 | C15: BR-7-2 | D15: No | E15: Yes | F15: =VLOOKUP(C15, 'Pivot Table 2'!$A$1:$B$123, 2, FALSE) -> 35000 | G15: 0 | H15: 0 | I15: 0 | J15: 0 | N15: =F15+G15*4*1000+H15*10000+1*1500*I15+1*J15*1000+1*K15*1000+1*L15*1000 -> 35000 | T15: =VLOOKUP(C15, 'Pivot Table 2'!$A$1:$C$119, 3, FALSE) -> 16144.814 | U15: =(1-AA$6)*F15 -> 21000 | V15: =$AA$7 -> 500 | W15: =$AA$8 -> 4500 | X15: =U15-T15-V15-W15 -> -144.81356
A16: 15 | B16: Mirevan Grove (BR-8-1) | C16: BR-8-1 | D16: Yes | E16: Yes | F16: =VLOOKUP(C16, 'Pivot Table 2'!$A$1:$B$123, 2, FALSE) -> 50000 | G16: 0 | H16: 0 | I16: 0 | J16: 4 | K16: 0 | L16: 0 | M16: Mid | N16: =F16+G16*4*1000+H16*10000+1*1500*I16+1*J16*1000+1*K16*1000+1*L16*1000 -> 54000 | O16: WHSWBIW03S218 | P16: No | Q16: WHSWSSBWBMWS172 | R16: 0 | S16: 0 | T16: =VLOOKUP(C16, 'Pivot Table 2'!$A$1:$C$119, 3, FALSE) -> 26712.169 | U16: =(1-AA$6)*F16 -> 30000 | V16: =$AA$7 -> 500 | W16: =$AA$8 -> 4500 | X16: =U16-T16-V16-W16 -> -1712.1695 | Y16: =35% -> 0.35
A17: 16 | B17: Alba Caliza (BR-8-2) | C17: BR-8-2 | D17: Yes | E17: Yes | F17: =VLOOKUP(C17, 'Pivot Table 2'!$A$1:$B$123, 2, FALSE) -> 50000 | G17: 0 | H17: 0 | I17: 0 | J17: 4 | K17: 0 | L17: 0 | M17: Mid | N17: =F17+G17*4*1000+H17*10000+1*1500*I17+1*J17*1000+1*K17*1000+1*L17*1000 -> 54000 | O17: WHSWBIW02S217 | P17: Yes | Q17: WHSWSSBWBMWS172 | R17: 0 | S17: 0 | T17: =VLOOKUP(C17, 'Pivot Table 2'!$A$1:$C$119, 3, FALSE) -> 26712.169 | U17: =(1-AA$6)*F17 -> 30000 | V17: =$AA$7 -> 500 | W17: =$AA$8 -> 4500 | X17: =U17-T17-V17-W17 -> -1712.1695 | Y17: =35% -> 0.35
A18: 17 | B18: Velvet Whisperline (BR-12-1) | C18: BR-12-1 | D18: Yes | E18: Yes | F18: =VLOOKUP(C18, 'Pivot Table 2'!$A$1:$B$123, 2, FALSE) -> 41000 | G18: 0 | H18: 0 | I18: 0 | J18: 0 | K18: 2 | L18: 1 | M18: Light | N18: =F18+G18*4*1000+H18*10000+1*1500*I18+1*J18*1000+1*K18*1000+1*L18*1000 -> 44000 | O18: WHSWBIW02S217 | P18: No | Q18: 0 | R18: WHSWSRBWBLWS181 | S18: WHSWS300SLWS191 | T18: =VLOOKUP(C18, 'Pivot Table 2'!$A$1:$C$119, 3, FALSE) -> 20289.898 | U18: =(1-AA$6)*F18 -> 24600 | V18: =$AA$7 -> 500 | W18: =$AA$8 -> 4500 | X18: =U18-T18-V18-W18 -> -689.89831 | Y18: =35% -> 0.35
A19: 18 | B19: BR-13-1 | C19: BR-13-1 | D19: No | E19: Yes | F19: =VLOOKUP(C19, 'Pivot Table 2'!$A$1:$B$123, 2, FALSE) -> 42500 | G19: 0 | H19: 0 | I19: 0 | J19: 0 | N19: =F19+G19*4*1000+H19*10000+1*1500*I19+1*J19*1000+1*K19*1000+1*L19*1000 -> 42500 | T19: =VLOOKUP(C19, 'Pivot Table 2'!$A$1:$C$119, 3, FALSE) -> 19504.475 | U19: =(1-AA$6)*F19 -> 25500 | V19: =$AA$7 -> 500 | W19: =$AA$8 -> 4500 | X19: =U19-T19-V19-W19 -> 995.52542
A20: 19 | B20: Elmara Nest (BR-15-1) | C20: BR-15-1 | D20: Yes | E20: Yes | F20: =VLOOKUP(C20, 'Pivot Table 2'!$A$1:$B$123, 2, FALSE) -> 45800 | G20: 0 | H20: 0 | I20: 0 | J20: 3 | K20: 0 | L20: 2 | M20: Light | N20: =F20+G20*4*1000+H20*10000+1*1500*I20+1*J20*1000+1*K20*1000+1*L20*1000 -> 50800 | O20: WHSWBIW02S217 | P20: Yes | Q20: WHSWSSBWBMWS172 | R20: 0 | S20: WHSWS300SLWS191 | T20: =VLOOKUP(C20, 'Pivot Table 2'!$A$1:$C$119, 3, FALSE) -> 25651.161 | U20: =(1-AA$6)*F20 -> 27480 | V20: =$AA$7 -> 500 | W20: =$AA$8 -> 4500 | X20: =U20-T20-V20-W20 -> -3171.1614 | Y20: =30% -> 0.3
A21: 20 | B21: Velisse Grove (BR-15-2) | C21: BR-15-2 | D21: Yes | E21: Yes | F21: =VLOOKUP(C21, 'Pivot Table 2'!$A$1:$B$123, 2, FALSE) -> 44800 | G21: 0 | H21: 0 | I21: 0 | J21: 3 | K21: 0 | L21: 2 | M21: Light | N21: =F21+G21*4*1000+H21*10000+1*1500*I21+1*J21*1000+1*K21*1000+1*L21*1000 -> 49800 | O21: WHSWBIW02S217 | P21: No | Q21: WHSWSSBWBMWS172 | R21: 0 | S21: WHSWS300SLWS191 | T21: =VLOOKUP(C21, 'Pivot Table 2'!$A$1:$C$119, 3, FALSE) -> 24976.161 | U21: =(1-AA$6)*F21 -> 26880 | V21: =$AA$7 -> 500 | W21: =$AA$8 -> 4500 | X21: =U21-T21-V21-W21 -> -3096.1614 | Y21: =30% -> 0.3
A22: 21 | B22: BR-9-1 | C22: BR-9-1 | D22: No | E22: Yes | F22: =VLOOKUP(C22, 'Pivot Table 2'!$A$1:$B$123, 2, FALSE) -> 95000 | G22: 0 | H22: 0 | I22: 0 | J22: 0 | N22: =F22+G22*4*1000+H22*10000+1*1500*I22+1*J22*1000+1*K22*1000+1*L22*1000 -> 95000 | T22: =VLOOKUP(C22, 'Pivot Table 2'!$A$1:$C$119, 3, FALSE) -> 52516.645 | U22: =(1-AA$6)*F22 -> 57000 | V22: =$AA$7 -> 500 | W22: =$AA$8 -> 4500 | X22: =U22-T22-V22-W22 -> -516.64542
A23: 22 | B23: BR-19-1 | C23: BR-19-1 | D23: No | E23: Yes | F23: =VLOOKUP(C23, 'Pivot Table 2'!$A$1:$B$123, 2, FALSE) -> 5000 | G23: 0 | H23: 0 | I23: 0 | J23: 0 | N23: =F23+G23*4*1000+H23*10000+1*1500*I23+1*J23*1000+1*K23*1000+1*L23*1000 -> 5000 | T23: =VLOOKUP(C23, 'Pivot Table 2'!$A$1:$C$119, 3, FALSE) -> 2736 | U23: =(1-AA$6)*F23 -> 3000 | V23: =$AA$7 -> 500 | W23: =$AA$8 -> 4500 | X23: =U23-T23-V23-W23 -> -4736
A24: 23 | B24: Celestine Veil (BR-10-1) | C24: BR-10-1 | D24: Yes | E24: Yes | F24: =VLOOKUP(C24, 'Pivot Table 2'!$A$1:$B$123, 2, FALSE) -> 5000 | G24: 0 | H24: 0 | I24: 0 | J24: 0 | K24: 0 | L24: 0 | M24: NA | N24: =F24+G24*4*1000+H24*10000+1*1500*I24+1*J24*1000+1*K24*1000+1*L24*1000 -> 5000 | O24: WHSWBIW02S217 | P24: No | Q24: 0 | R24: 0 | S24: 0 | T24: =VLOOKUP(C24, 'Pivot Table 2'!$A$1:$C$119, 3, FALSE) -> 2736 | U24: =(1-AA$6)*F24 -> 3000 | V24: =$AA$7 -> 500 | W24: =$AA$8 -> 4500 | X24: =U24-T24-V24-W24 -> -4736
A25: 24 | B25: Lignora Arch (BR-10-2) | C25: BR-10-2 | D25: Yes | E25: Yes | F25: =VLOOKUP(C25, 'Pivot Table 2'!$A$1:$B$123, 2, FALSE) -> 47500 | G25: 0 | H25: 0 | I25: 0 | J25: 0 | K25: 0 | L25: 0 | M25: NA | N25: =F25+G25*4*1000+H25*10000+1*1500*I25+1*J25*1000+1*K25*1000+1*L25*1000 -> 47500 | O25: WHSWBIW02S217 | P25: No | Q25: 0 | R25: 0 | S25: 0 | T25: =VLOOKUP(C25, 'Pivot Table 2'!$A$1:$C$119, 3, FALSE) -> 27529.548 | U25: =(1-AA$6)*F25 -> 28500 | V25: =$AA$7 -> 500 | W25: =$AA$8 -> 4500 | X25: =U25-T25-V25-W25 -> -4029.5485 | Y25: =30% -> 0.3
A26: 25 | B26: BR-31-1 | C26: BR-31-1 | D26: No | E26: Yes | F26: =VLOOKUP(C26, 'Pivot Table 2'!$A$1:$B$123, 2, FALSE) -> 140000 | G26: 0 | H26: 0 | I26: 0 | J26: 0 | N26: =F26+G26*4*1000+H26*10000+1*1500*I26+1*J26*1000+1*K26*1000+1*L26*1000 -> 140000 | T26: =VLOOKUP(C26, 'Pivot Table 2'!$A$1:$C$119, 3, FALSE) -> 77406.968 | U26: =(1-AA$6)*F26 -> 84000 | V26: =$AA$7 -> 500 | W26: =$AA$8 -> 4500 | X26: =U26-T26-V26-W26 -> 1593.0319
A27: 26 | B27: BR-31-2 | C27: BR-31-2 | D27: No | E27: Yes | F27: =VLOOKUP(C27, 'Pivot Table 2'!$A$1:$B$123, 2, FALSE) -> 140000 | G27: 0 | H27: 0 | I27: 0 | J27: 0 | N27: =F27+G27*4*1000+H27*10000+1*1500*I27+1*J27*1000+1*K27*1000+1*L27*1000 -> 140000 | T27: =VLOOKUP(C27, 'Pivot Table 2'!$A$1:$C$119, 3, FALSE) -> 77406.968 | U27: =(1-AA$6)*F27 -> 84000 | V27: =$AA$7 -> 500 | W27: =$AA$8 -> 4500 | X27: =U27-T27-V27-W27 -> 1593.0319
A28: 27 | B28: BR-20-1 | C28: BR-20-1 | D28: No | E28: Yes | F28: =VLOOKUP(C28, 'Pivot Table 2'!$A$1:$B$123, 2, FALSE) -> 5000 | G28: 0 | H28: 0 | I28: 0 | J28: 0 | N28: =F28+G28*4*1000+H28*10000+1*1500*I28+1*J28*1000+1*K28*1000+1*L28*1000 -> 5000 | T28: =VLOOKUP(C28, 'Pivot Table 2'!$A$1:$C$119, 3, FALSE) -> 2736 | U28: =(1-AA$6)*F28 -> 3000 | V28: =$AA$7 -> 500 | W28: =$AA$8 -> 4500 | X28: =U28-T28-V28-W28 -> -4736
A29: 28 | B29: BR-20-2 | C29: BR-20-2 | D29: No | E29: Yes | F29: =VLOOKUP(C29, 'Pivot Table 2'!$A$1:$B$123, 2, FALSE) -> 5000 | G29: 0 | H29: 0 | I29: 0 | J29: 0 | N29: =F29+G29*4*1000+H29*10000+1*1500*I29+1*J29*1000+1*K29*1000+1*L29*1000 -> 5000 | T29: =VLOOKUP(C29, 'Pivot Table 2'!$A$1:$C$119, 3, FALSE) -> 2736 | U29: =(1-AA$6)*F29 -> 3000 | V29: =$AA$7 -> 500 | W29: =$AA$8 -> 4500 | X29: =U29-T29-V29-W29 -> -4736
A30: 29 | B30: BR-11-1 | C30: BR-11-1 | D30: No | E30: Yes | F30: =VLOOKUP(C30, 'Pivot Table 2'!$A$1:$B$123, 2, FALSE) -> 5000 | G30: 0 | H30: 0 | I30: 0 | J30: 0 | N30: =F30+G30*4*1000+H30*10000+1*1500*I30+1*J30*1000+1*K30*1000+1*L30*1000 -> 5000 | T30: =VLOOKUP(C30, 'Pivot Table 2'!$A$1:$C$119, 3, FALSE) -> 2736 | U30: =(1-AA$6)*F30 -> 3000 | V30: =$AA$7 -> 500 | W30: =$AA$8 -> 4500 | X30: =U30-T30-V30-W30 -> -4736
A31: 30 | B31: BR-11-2 | C31: BR-11-2 | D31: No | E31: Yes | F31: =VLOOKUP(C31, 'Pivot Table 2'!$A$1:$B$123, 2, FALSE) -> 5000 | G31: 0 | H31: 0 | I31: 0 | J31: 0 | N31: =F31+G31*4*1000+H31*10000+1*1500*I31+1*J31*1000+1*K31*1000+1*L31*1000 -> 5000 | T31: =VLOOKUP(C31, 'Pivot Table 2'!$A$1:$C$119, 3, FALSE) -> 2736 | U31: =(1-AA$6)*F31 -> 3000 | V31: =$AA$7 -> 500 | W31: =$AA$8 -> 4500 | X31: =U31-T31-V31-W31 -> -4736
A32: 31 | B32: BR-22-1 | C32: BR-22-1 | D32: No | E32: Yes | F32: =VLOOKUP(C32, 'Pivot Table 2'!$A$1:$B$123, 2, FALSE) -> 5000 | G32: 0 | H32: 0 | I32: 0 | J32: 0 | N32: =F32+G32*4*1000+H32*10000+1*1500*I32+1*J32*1000+1*K32*1000+1*L32*1000 -> 5000 | T32: =VLOOKUP(C32, 'Pivot Table 2'!$A$1:$C$119, 3, FALSE) -> 2736 | U32: =(1-AA$6)*F32 -> 3000 | V32: =$AA$7 -> 500 | W32: =$AA$8 -> 4500 | X32: =U32-T32-V32-W32 -> -4736
A33: 32 | B33: BR-23-1 | C33: BR-23-1 | D33: No | E33: Yes | F33: =VLOOKUP(C33, 'Pivot Table 2'!$A$1:$B$123, 2, FALSE) -> 5000 | G33: 0 | H33: 0 | I33: 0 | J33: 0 | N33: =F33+G33*4*1000+H33*10000+1*1500*I33+1*J33*1000+1*K33*1000+1*L33*1000 -> 5000 | T33: =VLOOKUP(C33, 'Pivot Table 2'!$A$1:$C$119, 3, FALSE) -> 2736 | U33: =(1-AA$6)*F33 -> 3000 | V33: =$AA$7 -> 500 | W33: =$AA$8 -> 4500 | X33: =U33-T33-V33-W33 -> -4736
A34: 33 | B34: BR-23-2 | C34: BR-23-2 | D34: No | E34: Yes | F34: =VLOOKUP(C34, 'Pivot Table 2'!$A$1:$B$123, 2, FALSE) -> 5000 | G34: 0 | H34: 0 | I34: 0 | J34: 0 | N34: =F34+G34*4*1000+H34*10000+1*1500*I34+1*J34*1000+1*K34*1000+1*L34*1000 -> 5000 | T34: =VLOOKUP(C34, 'Pivot Table 2'!$A$1:$C$119, 3, FALSE) -> 2736 | U34: =(1-AA$6)*F34 -> 3000 | V34: =$AA$7 -> 500 | W34: =$AA$8 -> 4500 | X34: =U34-T34-V34-W34 -> -4736
A35: 34 | B35: BR-14-1 | C35: BR-14-1 | D35: No | E35: Yes | F35: =VLOOKUP(C35, 'Pivot Table 2'!$A$1:$B$123, 2, FALSE) -> 5000 | G35: 0 | H35: 0 | I35: 0 | J35: 0 | N35: =F35+G35*4*1000+H35*10000+1*1500*I35+1*J35*1000+1*K35*1000+1*L35*1000 -> 5000 | T35: =VLOOKUP(C35, 'Pivot Table 2'!$A$1:$C$119, 3, FALSE) -> 2736 | U35: =(1-AA$6)*F35 -> 3000 | V35: =$AA$7 -> 500 | W35: =$AA$8 -> 4500 | X35: =U35-T35-V35-W35 -> -4736
A36: 35 | B36: BR-14-2 | C36: BR-14-2 | D36: No | E36: Yes | F36: =VLOOKUP(C36, 'Pivot Table 2'!$A$1:$B$123, 2, FALSE) -> 5000 | G36: 0 | H36: 0 | I36: 0 | J36: 0 | N36: =F36+G36*4*1000+H36*10000+1*1500*I36+1*J36*1000+1*K36*1000+1*L36*1000 -> 5000 | T36: =VLOOKUP(C36, 'Pivot Table 2'!$A$1:$C$119, 3, FALSE) -> 2736 | U36: =(1-AA$6)*F36 -> 3000 | V36: =$AA$7 -> 500 | W36: =$AA$8 -> 4500 | X36: =U36-T36-V36-W36 -> -4736
A37: 36 | B37: BR-28-1 | C37: BR-28-1 | D37: No | E37: Yes | F37: =VLOOKUP(C37, 'Pivot Table 2'!$A$1:$B$123, 2, FALSE) -> 5000 | G37: 0 | H37: 0 | I37: 0 | J37: 0 | N37: =F37+G37*4*1000+H37*10000+1*1500*I37+1*J37*1000+1*K37*1000+1*L37*1000 -> 5000 | T37: =VLOOKUP(C37, 'Pivot Table 2'!$A$1:$C$119, 3, FALSE) -> 2736 | U37: =(1-AA$6)*F37 -> 3000 | V37: =$AA$7 -> 500 | W37: =$AA$8 -> 4500 | X37: =U37-T37-V37-W37 -> -4736
... A56: 55 | B56: BR-33-1 | C56: BR-33-1 | D56: No | E56: Yes | F56: =VLOOKUP(C56, 'Pivot Table 2'!$A$1:$B$123, 2, FALSE) -> 5000 | G56: 0 | H56: 0 | I56: 0 | J56: 0 | N56: =F56+G56*4*1000+H56*10000+1*1500*I56+1*J56*1000+1*K56*1000+1*L56*1000 -> 5000 | T56: =VLOOKUP(C56, 'Pivot Table 2'!$A$1:$C$119, 3, FALSE) -> 2736 | U56: =(1-AA$6)*F56 -> 3000 | V56: =$AA$7 -> 500 | W56: =$AA$8 -> 4500 | X56: =U56-T56-V56-W56 -> -4736
A57: 56 | B57: Scandinavian Warmth (LR-09L-1) | C57: LR-09L-1 | D57: Yes | E57: Yes | F57: =VLOOKUP(C57, 'Pivot Table 2'!$A$1:$B$123, 2, FALSE) -> 40000 | G57: 0 | H57: 0 | I57: 0 | J57: 0 | K57: 2 | L57: 0 | M57: Mid | N57: =F57+G57*4*1000+H57*10000+1*1500*I57+1*J57*1000+1*K57*1000+1*L57*1000 -> 42000 | O57: WHSWBIW02S217 | P57: No | Q57: 0 | R57: WHSWSRBWBMWS182 | S57: 0 | T57: =VLOOKUP(C57, 'Pivot Table 2'!$A$1:$C$119, 3, FALSE) -> 20771.288 | U57: =(1-AA$6)*F57 -> 24000 | V57: =$AA$7 -> 500 | W57: =$AA$8 -> 4500 | X57: =U57-T57-V57-W57 -> -1771.2881 | Y57: =35% -> 0.35
A58: 57 | B58: Graphite Horizon (LR-09L-2) | C58: LR-09L-2 | D58: Yes | E58: Yes | F58: =VLOOKUP(C58, 'Pivot Table 2'!$A$1:$B$123, 2, FALSE) -> 40000 | G58: 0 | H58: 0 | I58: 0 | J58: 0 | K58: 2 | L58: 0 | M58: Solid dark | N58: =F58+G58*4*1000+H58*10000+1*1500*I58+1*J58*1000+1*K58*1000+1*L58*1000 -> 42000 | O58: WHSWBIW02S217 | P58: No | Q58: 0 | R58: WHSWSRBWBSDS179 | S58: 0 | T58: =VLOOKUP(C58, 'Pivot Table 2'!$A$1:$C$119, 3, FALSE) -> 19876.373 | U58: =(1-AA$6)*F58 -> 24000 | V58: =$AA$7 -> 500 | W58: =$AA$8 -> 4500 | X58: =U58-T58-V58-W58 -> -876.37288 | Y58: =35% -> 0.35
A59: 58 | B59: Caramel Contemporary (LR-10L-1) | C59: LR-10L-1 | D59: Yes | E59: Yes | F59: =VLOOKUP(C59, 'Pivot Table 2'!$A$1:$B$123, 2, FALSE) -> 42000 | G59: 0 | H59: 0 | I59: 0 | J59: 2 | K59: 0 | L59: 0 | M59: Light | N59: =F59+G59*4*1000+H59*10000+1*1500*I59+1*J59*1000+1*K59*1000+1*L59*1000 -> 44000 | O59: WHSWBIW01S216 | P59: No | Q59: WHSWSSBWBLWS171 | R59: 0 | S59: 0 | T59: =VLOOKUP(C59, 'Pivot Table 2'!$A$1:$C$119, 3, FALSE) -> 22210.746 | U59: =(1-AA$6)*F59 -> 25200 | V59: =$AA$7 -> 500 | W59: =$AA$8 -> 4500 | X59: =U59-T59-V59-W59 -> -2010.7458 | Y59: =35% -> 0.35
A60: 59 | B60: Monora Bloom (LR-10L-2) | C60: LR-10L-2 | D60: Yes | E60: Yes | F60: =VLOOKUP(C60, 'Pivot Table 2'!$A$1:$B$123, 2, FALSE) -> 37000 | G60: 0 | H60: 0 | I60: 0 | J60: 2 | K60: 0 | L60: 0 | M60: Solid dark | N60: =F60+G60*4*1000+H60*10000+1*1500*I60+1*J60*1000+1*K60*1000+1*L60*1000 -> 39000 | O60: WHSWBIW01S216 | P60: No | Q60: WHSWSSBWBSDS169 | R60: 0 | S60: 0 | T60: =VLOOKUP(C60, 'Pivot Table 2'!$A$1:$C$119, 3, FALSE) -> 18185.932 | U60: =(1-AA$6)*F60 -> 22200 | V60: =$AA$7 -> 500 | W60: =$AA$8 -> 4500 | X60: =U60-T60-V60-W60 -> -985.9322 | Y60: =35% -> 0.35
A61: 60 | B61: LR-11L-1 | C61: LR-11L-1 | D61: No | E61: Yes | F61: =VLOOKUP(C61, 'Pivot Table 2'!$A$1:$B$123, 2, FALSE) -> 5000 | G61: 0 | H61: 0 | I61: 0 | J61: 0 | N61: =F61+G61*4*1000+H61*10000+1*1500*I61+1*J61*1000+1*K61*1000+1*L61*1000 -> 5000 | T61: =VLOOKUP(C61, 'Pivot Table 2'!$A$1:$C$119, 3, FALSE) -> 2736 | U61: =(1-AA$6)*F61 -> 3000 | V61: =$AA$7 -> 500 | W61: =$AA$8 -> 4500 | X61: =U61-T61-V61-W61 -> -4736
A62: 61 | B62: Auric Timberline (LR-20L-1) | C62: LR-20L-1 | D62: Yes | E62: Yes | F62: =VLOOKUP(C62, 'Pivot Table 2'!$A$1:$B$123, 2, FALSE) -> 32700 | G62: 0 | H62: 0 | I62: 1 | J62: 0 | K62: 0 | L62: 0 | M62: NA | N62: =F62+G62*4*1000+H62*10000+1*1500*I62+1*J62*1000+1*K62*1000+1*L62*1000 -> 34200 | O62: WHSWBIW10S225 | P62: No | Q62: 0 | R62: 0 | S62: 0 | T62: =VLOOKUP(C62, 'Pivot Table 2'!$A$1:$C$119, 3, FALSE) -> 17431.161 | U62: =(1-AA$6)*F62 -> 19620 | V62: =$AA$7 -> 500 | W62: =$AA$8 -> 4500 | X62: =U62-T62-V62-W62 -> -2811.1614 | Y62: 0.25
A63: 62 | B63: Armon Lumera (LR-20L-2) | C63: LR-20L-2 | D63: Yes | E63: Yes | F63: =VLOOKUP(C63, 'Pivot Table 2'!$A$1:$B$123, 2, FALSE) -> 32700 | G63: 0 | H63: 0 | I63: 1 | J63: 0 | K63: 0 | L63: 0 | M63: NA | N63: =F63+G63*4*1000+H63*10000+1*1500*I63+1*J63*1000+1*K63*1000+1*L63*1000 -> 34200 | O63: WHSWBIW01S216 | P63: No | Q63: 0 | R63: 0 | S63: 0 | T63: =VLOOKUP(C63, 'Pivot Table 2'!$A$1:$C$119, 3, FALSE) -> 17431.161 | U63: =(1-AA$6)*F63 -> 19620 | V63: =$AA$7 -> 500 | W63: =$AA$8 -> 4500 | X63: =U63-T63-V63-W63 -> -2811.1614 | Y63: 0.25
A64: 63 | B64: LR-18-1 | C64: LR-18-1 | D64: No | E64: Yes | F64: =VLOOKUP(C64, 'Pivot Table 2'!$A$1:$B$123, 2, FALSE) -> 5000 | G64: 0 | H64: 0 | I64: 0 | J64: 0 | N64: =F64+G64*4*1000+H64*10000+1*1500*I64+1*J64*1000+1*K64*1000+1*L64*1000 -> 5000 | T64: =VLOOKUP(C64, 'Pivot Table 2'!$A$1:$C$119, 3, FALSE) -> 2736 | U64: =(1-AA$6)*F64 -> 3000 | V64: =$AA$7 -> 500 | W64: =$AA$8 -> 4500 | X64: =U64-T64-V64-W64 -> -4736
A65: 64 | B65: LR-18-2 | C65: LR-18-2 | D65: No | E65: Yes | F65: =VLOOKUP(C65, 'Pivot Table 2'!$A$1:$B$123, 2, FALSE) -> 5000 | G65: 0 | H65: 0 | I65: 0 | J65: 0 | N65: =F65+G65*4*1000+H65*10000+1*1500*I65+1*J65*1000+1*K65*1000+1*L65*1000 -> 5000 | T65: =VLOOKUP(C65, 'Pivot Table 2'!$A$1:$C$119, 3, FALSE) -> 2736 | U65: =(1-AA$6)*F65 -> 3000 | V65: =$AA$7 -> 500 | W65: =$AA$8 -> 4500 | X65: =U65-T65-V65-W65 -> -4736
A66: 65 | B66: Brinova Rustic (LR-21L-1) | C66: LR-21L-1 | D66: Yes | E66: Yes | F66: =VLOOKUP(C66, 'Pivot Table 2'!$A$1:$B$123, 2, FALSE) -> 49500 | G66: 0 | H66: 0 | I66: 0 | J66: 1 | K66: 1 | L66: 1 | M66: Mid | N66: =F66+G66*4*1000+H66*10000+1*1500*I66+1*J66*1000+1*K66*1000+1*L66*1000 -> 52500 | O66: WHSWBIW10S225 | P66: Yes | Q66: WHSWSSBWBMWS172 | R66: WHSWSRBWBMWS182 | S66: WHSWS300SMWS192 | T66: =VLOOKUP(C66, 'Pivot Table 2'!$A$1:$C$119, 3, FALSE) -> 23123.288 | U66: =(1-AA$6)*F66 -> 29700 | V66: =$AA$7 -> 500 | W66: =$AA$8 -> 4500 | X66: =U66-T66-V66-W66 -> 1576.7119 | Y66: =40% -> 0.4
A67: 66 | B67: Brunelle Haven (LR-21L-2) | C67: LR-21L-2 | D67: Yes | E67: Yes | F67: =VLOOKUP(C67, 'Pivot Table 2'!$A$1:$B$123, 2, FALSE) -> 9000 | G67: 0 | H67: 0 | I67: 0 | J67: 1 | K67: 1 | L67: 1 | M67: Mid | N67: =F67+G67*4*1000+H67*10000+1*1500*I67+1*J67*1000+1*K67*1000+1*L67*1000 -> 12000 | O67: WHSWBIW03S218 | P67: No | Q67: WHSWSSBWBMWS172 | R67: WHSWSRBWBMWS182 | S67: WHSWS300SMWS192 | T67: =VLOOKUP(C67, 'Pivot Table 2'!$A$1:$C$119, 3, FALSE) -> 3986 | U67: =(1-AA$6)*F67 -> 5400 | V67: =$AA$7 -> 500 | W67: =$AA$8 -> 4500 | X67: =U67-T67-V67-W67 -> -3586
A68: 67 | B68: LR-22L-1 | C68: LR-22L-1 | D68: No | E68: Yes | F68: =VLOOKUP(C68, 'Pivot Table 2'!$A$1:$B$123, 2, FALSE) -> 5000 | G68: 0 | H68: 0 | I68: 0 | J68: 0 | N68: =F68+G68*4*1000+H68*10000+1*1500*I68+1*J68*1000+1*K68*1000+1*L68*1000 -> 5000 | T68: =VLOOKUP(C68, 'Pivot Table 2'!$A$1:$C$119, 3, FALSE) -> 2736 | U68: =(1-AA$6)*F68 -> 3000 | V68: =$AA$7 -> 500 | W68: =$AA$8 -> 4500 | X68: =U68-T68-V68-W68 -> -4736
A69: 68 | B69: LR-22L-2 | C69: LR-22L-2 | D69: No | E69: Yes | F69: =VLOOKUP(C69, 'Pivot Table 2'!$A$1:$B$123, 2, FALSE) -> 5000 | G69: 0 | H69: 0 | I69: 0 | J69: 0 | N69: =F69+G69*4*1000+H69*10000+1*1500*I69+1*J69*1000+1*K69*1000+1*L69*1000 -> 5000 | T69: =VLOOKUP(C69, 'Pivot Table 2'!$A$1:$C$119, 3, FALSE) -> 2736 | U69: =(1-AA$6)*F69 -> 3000 | V69: =$AA$7 -> 500 | W69: =$AA$8 -> 4500 | X69: =U69-T69-V69-W69 -> -4736
A70: 69 | B70: LR-23L-1 | C70: LR-23L-1 | D70: No | E70: Yes | F70: =VLOOKUP(C70, 'Pivot Table 2'!$A$1:$B$123, 2, FALSE) -> 5000 | G70: 0 | H70: 0 | I70: 0 | J70: 0 | N70: =F70+G70*4*1000+H70*10000+1*1500*I70+1*J70*1000+1*K70*1000+1*L70*1000 -> 5000 | T70: =VLOOKUP(C70, 'Pivot Table 2'!$A$1:$C$119, 3, FALSE) -> 2736 | U70: =(1-AA$6)*F70 -> 3000 | V70: =$AA$7 -> 500 | W70: =$AA$8 -> 4500 | X70: =U70-T70-V70-W70 -> -4736
A71: 70 | B71: LR-23L-2 | C71: LR-23L-2 | D71: No | E71: Yes | F71: =VLOOKUP(C71, 'Pivot Table 2'!$A$1:$B$123, 2, FALSE) -> 5000 | G71: 0 | H71: 0 | I71: 0 | J71: 0 | N71: =F71+G71*4*1000+H71*10000+1*1500*I71+1*J71*1000+1*K71*1000+1*L71*1000 -> 5000 | T71: =VLOOKUP(C71, 'Pivot Table 2'!$A$1:$C$119, 3, FALSE) -> 2736 | U71: =(1-AA$6)*F71 -> 3000 | V71: =$AA$7 -> 500 | W71: =$AA$8 -> 4500 | X71: =U71-T71-V71-W71 -> -4736
A72: 71 | B72: LR-24L-1 | C72: LR-24L-1 | D72: No | E72: Yes | F72: =VLOOKUP(C72, 'Pivot Table 2'!$A$1:$B$123, 2, FALSE) -> 5000 | G72: 0 | H72: 0 | I72: 0 | J72: 0 | N72: =F72+G72*4*1000+H72*10000+1*1500*I72+1*J72*1000+1*K72*1000+1*L72*1000 -> 5000 | T72: =VLOOKUP(C72, 'Pivot Table 2'!$A$1:$C$119, 3, FALSE) -> 2736 | U72: =(1-AA$6)*F72 -> 3000 | V72: =$AA$7 -> 500 | W72: =$AA$8 -> 4500 | X72: =U72-T72-V72-W72 -> -4736
A73: 72 | B73: LR-24L-2 | C73: LR-24L-2 | D73: No | E73: Yes | F73: =VLOOKUP(C73, 'Pivot Table 2'!$A$1:$B$123, 2, FALSE) -> 5000 | G73: 0 | H73: 0 | I73: 0 | J73: 0 | N73: =F73+G73*4*1000+H73*10000+1*1500*I73+1*J73*1000+1*K73*1000+1*L73*1000 -> 5000 | T73: =VLOOKUP(C73, 'Pivot Table 2'!$A$1:$C$119, 3, FALSE) -> 2736 | U73: =(1-AA$6)*F73 -> 3000 | V73: =$AA$7 -> 500 | W73: =$AA$8 -> 4500 | X73: =U73-T73-V73-W73 -> -4736
A74: 73 | B74: LR-25L-1 | C74: LR-25L-1 | D74: No | E74: Yes | F74: =VLOOKUP(C74, 'Pivot Table 2'!$A$1:$B$123, 2, FALSE) -> 5000 | G74: 0 | H74: 0 | I74: 0 | J74: 0 | N74: =F74+G74*4*1000+H74*10000+1*1500*I74+1*J74*1000+1*K74*1000+1*L74*1000 -> 5000 | T74: =VLOOKUP(C74, 'Pivot Table 2'!$A$1:$C$119, 3, FALSE) -> 2736 | U74: =(1-AA$6)*F74 -> 3000 | V74: =$AA$7 -> 500 | W74: =$AA$8 -> 4500 | X74: =U74-T74-V74-W74 -> -4736
A75: 74 | B75: LR-25L-2 | C75: LR-25L-2 | D75: No | E75: Yes | F75: =VLOOKUP(C75, 'Pivot Table 2'!$A$1:$B$123, 2, FALSE) -> 5000 | G75: 0 | H75: 0 | I75: 0 | J75: 0 | N75: =F75+G75*4*1000+H75*10000+1*1500*I75+1*J75*1000+1*K75*1000+1*L75*1000 -> 5000 | T75: =VLOOKUP(C75, 'Pivot Table 2'!$A$1:$C$119, 3, FALSE) -> 2736 | U75: =(1-AA$6)*F75 -> 3000 | V75: =$AA$7 -> 500 | W75: =$AA$8 -> 4500 | X75: =U75-T75-V75-W75 -> -4736
A76: 75 | B76: Orlune Canvas (LR-26L-1) | C76: LR-26L-1 | D76: Yes | E76: Yes | F76: =VLOOKUP(C76, 'Pivot Table 2'!$A$1:$B$123, 2, FALSE) -> 44500 | G76: 0 | H76: 0 | I76: 0 | J76: 0 | N76: =F76+G76*4*1000+H76*10000+1*1500*I76+1*J76*1000+1*K76*1000+1*L76*1000 -> 44500 | T76: =VLOOKUP(C76, 'Pivot Table 2'!$A$1:$C$119, 3, FALSE) -> 23977.936 | U76: =(1-AA$6)*F76 -> 26700 | V76: =$AA$7 -> 500 | W76: =$AA$8 -> 4500 | X76: =U76-T76-V76-W76 -> -2277.9356 | Y76: =35% -> 0.35
A77: 76 | B77: Caldessa Line (LR-27L-1) | C77: LR-27L-1 | D77: Yes | E77: Yes | F77: =VLOOKUP(C77, 'Pivot Table 2'!$A$1:$B$123, 2, FALSE) -> 76700 | G77: 0 | H77: 0 | I77: 0 | J77: 0 | N77: =F77+G77*4*1000+H77*10000+1*1500*I77+1*J77*1000+1*K77*1000+1*L77*1000 -> 76700 | T77: =VLOOKUP(C77, 'Pivot Table 2'!$A$1:$C$119, 3, FALSE) -> 37667.766 | U77: =(1-AA$6)*F77 -> 46020 | V77: =$AA$7 -> 500 | W77: =$AA$8 -> 4500 | X77: =U77-T77-V77-W77 -> 3352.2339 | Y77: =40% -> 0.4
A78: 77 | B78: Roventa Canvas (LR-28L-1) | C78: LR-28L-1 | D78: Yes | E78: Yes | F78: =VLOOKUP(C78, 'Pivot Table 2'!$A$1:$B$123, 2, FALSE) -> 36700 | G78: 0 | H78: 0 | I78: 0 | J78: 0 | N78: =F78+G78*4*1000+H78*10000+1*1500*I78+1*J78*1000+1*K78*1000+1*L78*1000 -> 36700 | T78: =VLOOKUP(C78, 'Pivot Table 2'!$A$1:$C$119, 3, FALSE) -> 19276.382 | U78: =(1-AA$6)*F78 -> 22020 | V78: =$AA$7 -> 500 | W78: =$AA$8 -> 4500 | X78: =U78-T78-V78-W78 -> -2256.3817
A79: 78 | B79: LR-28L-2 | C79: LR-28L-2 | D79: No | E79: Yes | F79: =VLOOKUP(C79, 'Pivot Table 2'!$A$1:$B$123, 2, FALSE) -> 5000 | G79: 0 | H79: 0 | I79: 0 | J79: 0 | N79: =F79+G79*4*1000+H79*10000+1*1500*I79+1*J79*1000+1*K79*1000+1*L79*1000 -> 5000 | T79: =VLOOKUP(C79, 'Pivot Table 2'!$A$1:$C$119, 3, FALSE) -> 2736 | U79: =(1-AA$6)*F79 -> 3000 | V79: =$AA$7 -> 500 | W79: =$AA$8 -> 4500 | X79: =U79-T79-V79-W79 -> -4736
A80: 79 | B80: Rivenza Line (LR-29L-1) | C80: LR-29L-1 | D80: Yes | E80: Yes | F80: =VLOOKUP(C80, 'Pivot Table 2'!$A$1:$B$123, 2, FALSE) -> 47700 | G80: 0 | H80: 0 | I80: 0 | J80: 0 | N80: =F80+G80*4*1000+H80*10000+1*1500*I80+1*J80*1000+1*K80*1000+1*L80*1000 -> 47700 | T80: =VLOOKUP(C80, 'Pivot Table 2'!$A$1:$C$119, 3, FALSE) -> 27848.447 | U80: =(1-AA$6)*F80 -> 28620 | V80: =$AA$7 -> 500 | W80: =$AA$8 -> 4500 | X80: =U80-T80-V80-W80 -> -4228.4468
A81: 80 | B81: LR-29L-2 | C81: LR-29L-2 | D81: No | E81: Yes | F81: =VLOOKUP(C81, 'Pivot Table 2'!$A$1:$B$123, 2, FALSE) -> 5000 | G81: 0 | H81: 0 | I81: 0 | J81: 0 | N81: =F81+G81*4*1000+H81*10000+1*1500*I81+1*J81*1000+1*K81*1000+1*L81*1000 -> 5000 | T81: =VLOOKUP(C81, 'Pivot Table 2'!$A$1:$C$119, 3, FALSE) -> 2736 | U81: =(1-AA$6)*F81 -> 3000 | V81: =$AA$7 -> 500 | W81: =$AA$8 -> 4500 | X81: =U81-T81-V81-W81 -> -4736
A82: 81 | B82: LR-30L-1 | C82: LR-30L-1 | D82: No | E82: Yes | F82: =VLOOKUP(C82, 'Pivot Table 2'!$A$1:$B$123, 2, FALSE) -> 5000 | G82: 0 | H82: 0 | I82: 0 | J82: 0 | N82: =F82+G82*4*1000+H82*10000+1*1500*I82+1*J82*1000+1*K82*1000+1*L82*1000 -> 5000 | T82: =VLOOKUP(C82, 'Pivot Table 2'!$A$1:$C$119, 3, FALSE) -> 2736 | U82: =(1-AA$6)*F82 -> 3000 | V82: =$AA$7 -> 500 | W82: =$AA$8 -> 4500 | X82: =U82-T82-V82-W82 -> -4736
A83: 82 | B83: LR-30L-2 | C83: LR-30L-2 | D83: No | E83: Yes | F83: =VLOOKUP(C83, 'Pivot Table 2'!$A$1:$B$123, 2, FALSE) -> 5000 | G83: 0 | H83: 0 | I83: 0 | J83: 0 | N83: =F83+G83*4*1000+H83*10000+1*1500*I83+1*J83*1000+1*K83*1000+1*L83*1000 -> 5000 | T83: =VLOOKUP(C83, 'Pivot Table 2'!$A$1:$C$119, 3, FALSE) -> 2736 | U83: =(1-AA$6)*F83 -> 3000 | V83: =$AA$7 -> 500 | W83: =$AA$8 -> 4500 | X83: =U83-T83-V83-W83 -> -4736
A84: 83 | B84: Torenza Atelier (LR-31L-1) | C84: LR-31L-1 | D84: Yes | E84: Yes | F84: =VLOOKUP(C84, 'Pivot Table 2'!$A$1:$B$123, 2, FALSE) -> 47900 | G84: 0 | H84: 0 | I84: 0 | J84: 0 | N84: =F84+G84*4*1000+H84*10000+1*1500*I84+1*J84*1000+1*K84*1000+1*L84*1000 -> 47900 | T84: =VLOOKUP(C84, 'Pivot Table 2'!$A$1:$C$119, 3, FALSE) -> 23448.077 | U84: =(1-AA$6)*F84 -> 28740 | V84: =$AA$7 -> 500 | W84: =$AA$8 -> 4500 | X84: =U84-T84-V84-W84 -> 291.92339
A85: 84 | B85: LR-31L-2 | C85: LR-31L-2 | D85: No | E85: Yes | F85: =VLOOKUP(C85, 'Pivot Table 2'!$A$1:$B$123, 2, FALSE) -> 5000 | G85: 0 | H85: 0 | I85: 0 | J85: 0 | N85: =F85+G85*4*1000+H85*10000+1*1500*I85+1*J85*1000+1*K85*1000+1*L85*1000 -> 5000 | T85: =VLOOKUP(C85, 'Pivot Table 2'!$A$1:$C$119, 3, FALSE) -> 2736 | U85: =(1-AA$6)*F85 -> 3000 | V85: =$AA$7 -> 500 | W85: =$AA$8 -> 4500 | X85: =U85-T85-V85-W85 -> -4736
A86: 85 | B86: LR-32L-1 | C86: LR-32L-1 | D86: Yes | E86: Yes | F86: =VLOOKUP(C86, 'Pivot Table 2'!$A$1:$B$123, 2, FALSE) -> 48300 | G86: 0 | H86: 0 | I86: 0 | J86: 0 | N86: =F86+G86*4*1000+H86*10000+1*1500*I86+1*J86*1000+1*K86*1000+1*L86*1000 -> 48300 | T86: =VLOOKUP(C86, 'Pivot Table 2'!$A$1:$C$119, 3, FALSE) -> 27163.191 | U86: =(1-AA$6)*F86 -> 28980 | V86: =$AA$7 -> 500 | W86: =$AA$8 -> 4500 | X86: =U86-T86-V86-W86 -> -3183.1912
A87: 86 | B87: LR-33L-1 | C87: LR-33L-1 | D87: No | E87: Yes | F87: =VLOOKUP(C87, 'Pivot Table 2'!$A$1:$B$123, 2, FALSE) -> 5000 | G87: 0 | H87: 0 | I87: 0 | J87: 0 | N87: =F87+G87*4*1000+H87*10000+1*1500*I87+1*J87*1000+1*K87*1000+1*L87*1000 -> 5000 | T87: =VLOOKUP(C87, 'Pivot Table 2'!$A$1:$C$119, 3, FALSE) -> 2736 | U87: =(1-AA$6)*F87 -> 3000 | V87: =$AA$7 -> 500 | W87: =$AA$8 -> 4500 | X87: =U87-T87-V87-W87 -> -4736
A88: 87 | B88: Orlith Lios (LR-33L-2) | C88: LR-33L-2 | D88: Yes | E88: Yes | F88: =VLOOKUP(C88, 'Pivot Table 2'!$A$1:$B$123, 2, FALSE) -> 36700 | G88: 0 | H88: 0 | I88: 0 | J88: 0 | N88: =F88+G88*4*1000+H88*10000+1*1500*I88+1*J88*1000+1*K88*1000+1*L88*1000 -> 36700 | T88: =VLOOKUP(C88, 'Pivot Table 2'!$A$1:$C$119, 3, FALSE) -> 21303.791 | U88: =(1-AA$6)*F88 -> 22020 | V88: =$AA$7 -> 500 | W88: =$AA$8 -> 4500 | X88: =U88-T88-V88-W88 -> -4283.7905
A89: 88 | B89: LR-34L-1 | C89: LR-34L-1 | D89: No | E89: Yes | F89: =VLOOKUP(C89, 'Pivot Table 2'!$A$1:$B$123, 2, FALSE) -> 5000 | G89: 0 | H89: 0 | I89: 0 | J89: 0 | N89: =F89+G89*4*1000+H89*10000+1*1500*I89+1*J89*1000+1*K89*1000+1*L89*1000 -> 5000 | T89: =VLOOKUP(C89, 'Pivot Table 2'!$A$1:$C$119, 3, FALSE) -> 2736 | U89: =(1-AA$6)*F89 -> 3000 | V89: =$AA$7 -> 500 | W89: =$AA$8 -> 4500 | X89: =U89-T89-V89-W89 -> -4736
... A93: 92 | B93: LR-36L-1 | C93: LR-36L-1 | D93: No | E93: Yes | F93: =VLOOKUP(C93, 'Pivot Table 2'!$A$1:$B$123, 2, FALSE) -> 5000 | G93: 0 | H93: 0 | I93: 0 | J93: 0 | N93: =F93+G93*4*1000+H93*10000+1*1500*I93+1*J93*1000+1*K93*1000+1*L93*1000 -> 5000 | T93: =VLOOKUP(C93, 'Pivot Table 2'!$A$1:$C$119, 3, FALSE) -> 2736 | U93: =(1-AA$6)*F93 -> 3000 | V93: =$AA$7 -> 500 | W93: =$AA$8 -> 4500 | X93: =U93-T93-V93-W93 -> -4736
A94: 93 | B94: Aviora Form (LR-37L-1) | C94: LR-37L-1 | D94: Yes | E94: Yes | F94: =VLOOKUP(C94, 'Pivot Table 2'!$A$1:$B$123, 2, FALSE) -> 37000
A95: 94 | B95: Calyra Nest (LR-38L-1) | C95: LR-38L-1 | D95: Yes | E95: Yes | F95: =VLOOKUP(C95, 'Pivot Table 2'!$A$1:$B$123, 2, FALSE) -> 67900
A96: 95 | B96: Vireza Elris (LR-39L-1) | C96: LR-39L-1 | D96: Yes | E96: Yes | F96: =VLOOKUP(C96, 'Pivot Table 2'!$A$1:$B$123, 2, FALSE) -> 5000
A97: 96 | B97: Calveris Cove (LR-40L-1) | C97: LR-40L-1 | D97: Yes | E97: Yes | F97: =VLOOKUP(C97, 'Pivot Table 2'!$A$1:$B$123, 2, FALSE) -> 36200
A98: 97 | B98: Seren Walnut Elegance (TV-60) | C98: TV-60 | D98: Yes | E98: Yes | F98: =VLOOKUP(C98, 'Pivot Table 2'!$A$1:$B$123, 2, FALSE) -> 9000 | G98: 0 | H98: 1 | I98: 0 | J98: 0 | K98: 0 | L98: 2 | M98: Mid | N98: =F98+G98*4*1000+H98*10000+1*1500*I98+1*J98*1000+1*K98*1000+1*L98*1000 -> 21000 | O98: WHSWBIP02S210 | P98: ?? | Q98: 0 | R98: 0 | S98: WHSWS300SMWS192 | T98: =VLOOKUP(C98, 'Pivot Table 2'!$A$1:$C$119, 3, FALSE) -> 4036 | U98: =(1-AA$6)*F98 -> 5400 | V98: =$AA$7 -> 500 | W98: =$AA$8 -> 4500 | X98: =U98-T98-V98-W98 -> -3636
A99: 98 | B99: Timber Whisper (TV-61) | C99: TV-61 | D99: Yes | E99: Yes | F99: =VLOOKUP(C99, 'Pivot Table 2'!$A$1:$B$123, 2, FALSE) -> 73500 | G99: 0 | H99: 1 | I99: 0 | J99: 0 | K99: 0 | L99: 2 | M99: Dark | N99: =F99+G99*4*1000+H99*10000+1*1500*I99+1*J99*1000+1*K99*1000+1*L99*1000 -> 85500 | O99: WHSWBIW02S217 | P99: Yes | Q99: 0 | R99: 0 | S99: WHSWS300SDWS193 | T99: =VLOOKUP(C99, 'Pivot Table 2'!$A$1:$C$119, 3, FALSE) -> 40252.342 | U99: =(1-AA$6)*F99 -> 44100 | V99: =$AA$7 -> 500 | W99: =$AA$8 -> 4500 | X99: =U99-T99-V99-W99 -> -1152.3424 | Y99: =35% -> 0.35
A100: 99 | B100: TV-62 | C100: TV-62 | D100: Yes | E100: Yes | F100: =VLOOKUP(C100, 'Pivot Table 2'!$A$1:$B$123, 2, FALSE) -> 55500 | G100: 0 | H100: 0 | I100: 0 | J100: 0 | N100: =F100+G100*4*1000+H100*10000+1*1500*I100+1*J100*1000+1*K100*1000+1*L100*1000 -> 55500 | T100: =VLOOKUP(C100, 'Pivot Table 2'!$A$1:$C$119, 3, FALSE) -> 28523.147 | U100: =(1-AA$6)*F100 -> 33300 | V100: =$AA$7 -> 500 | W100: =$AA$8 -> 4500 | X100: =U100-T100-V100-W100 -> -223.14712
A101: 100 | B101: Signature Marble (TV-63) | C101: TV-63 | D101: Yes | E101: Yes | F101: =VLOOKUP(C101, 'Pivot Table 2'!$A$1:$B$123, 2, FALSE) -> 54000 | G101: 0 | H101: 1 | I101: 0 | J101: 2 | K101: 0 | L101: 1 | M101: Mid | N101: =F101+G101*4*1000+H101*10000+1*1500*I101+1*J101*1000+1*K101*1000+1*L101*1000 -> 67000 | O101: WHSWBIW10S225 | P101: ?? | Q101: WHSWSSBWBMWS172 | R101: 0 | S101: WHSWS300SMWS192 | T101: =VLOOKUP(C101, 'Pivot Table 2'!$A$1:$C$119, 3, FALSE) -> 24357.38 | U101: =(1-AA$6)*F101 -> 32400 | V101: =$AA$7 -> 500 | W101: =$AA$8 -> 4500 | X101: =U101-T101-V101-W101 -> 3042.6197 | Y101: =40% -> 0.4
A102: 101 | B102: TV-64 | C102: TV-64 | D102: Yes | E102: Yes | F102: =VLOOKUP(C102, 'Pivot Table 2'!$A$1:$B$123, 2, FALSE) -> 41700 | G102: 0 | H102: 0 | I102: 0 | J102: 0 | N102: =F102+G102*4*1000+H102*10000+1*1500*I102+1*J102*1000+1*K102*1000+1*L102*1000 -> 41700 | T102: =VLOOKUP(C102, 'Pivot Table 2'!$A$1:$C$119, 3, FALSE) -> 21557.094 | U102: =(1-AA$6)*F102 -> 25020 | V102: =$AA$7 -> 500 | W102: =$AA$8 -> 4500 | X102: =U102-T102-V102-W102 -> -1537.0936
A103: 102 | B103: Novara Veil (TV-65) | C103: TV-65 | D103: Yes | E103: Yes | F103: =VLOOKUP(C103, 'Pivot Table 2'!$A$1:$B$123, 2, FALSE) -> 13000 | G103: 0 | H103: 1 | I103: 0 | J103: 0 | K103: 0 | L103: 0 | M103: NA | N103: =F103+G103*4*1000+H103*10000+1*1500*I103+1*J103*1000+1*K103*1000+1*L103*1000 -> 23000 | O103: WHSWBIW01S216 | P103: No | Q103: 0 | R103: 0 | S103: 0 | T103: =VLOOKUP(C103, 'Pivot Table 2'!$A$1:$C$119, 3, FALSE) -> 8586 | U103: =(1-AA$6)*F103 -> 7800 | V103: =$AA$7 -> 500 | W103: =$AA$8 -> 4500 | X103: =U103-T103-V103-W103 -> -5786
A104: 103 | B104: Mirello Veil (TV-66) | C104: TV-66 | D104: Yes | E104: Yes | F104: =VLOOKUP(C104, 'Pivot Table 2'!$A$1:$B$123, 2, FALSE) -> 28500 | G104: 0 | H104: 1 | I104: 0 | J104: 0 | K104: 0 | L104: 0 | M104: NA | N104: =F104+G104*4*1000+H104*10000+1*1500*I104+1*J104*1000+1*K104*1000+1*L104*1000 -> 38500 | O104: WHSWBIW01S216 | P104: No | Q104: 0 | R104: 0 | S104: 0 | T104: =VLOOKUP(C104, 'Pivot Table 2'!$A$1:$C$119, 3, FALSE) -> 14834.557 | U104: =(1-AA$6)*F104 -> 17100 | V104: =$AA$7 -> 500 | W104: =$AA$8 -> 4500 | X104: =U104-T104-V104-W104 -> -2734.5566 | Y104: =30% -> 0.3
A105: 104 | B105: Casa Cavora (TV-67) | C105: TV-67 | D105: Yes | E105: Yes | F105: =VLOOKUP(C105, 'Pivot Table 2'!$A$1:$B$123, 2, FALSE) -> 71100 | G105: 0 | H105: 0 | I105: 0 | J105: 0 | K105: 1 | L105: 2 | M105: Light | N105: =F105+G105*4*1000+H105*10000+1*1500*I105+1*J105*1000+1*K105*1000+1*L105*1000 -> 74100 | O105: WHSWBIW10S225 | P105: ?? | Q105: 0 | R105: WHSWSRBWBLWS181 | S105: WHSWS300SLWS191 | T105: =VLOOKUP(C105, 'Pivot Table 2'!$A$1:$C$119, 3, FALSE) -> 39688.953 | U105: =(1-AA$6)*F105 -> 42660 | V105: =$AA$7 -> 500 | W105: =$AA$8 -> 4500 | X105: =U105-T105-V105-W105 -> -2028.9525 | Y105: =35% -> 0.35
A106: 105 | B106: TV-68 | C106: TV-68 | D106: Yes | E106: Yes | F106: =VLOOKUP(C106, 'Pivot Table 2'!$A$1:$B$123, 2, FALSE) -> 61500 | G106: 0 | H106: 0 | I106: 0 | J106: 0 | N106: =F106+G106*4*1000+H106*10000+1*1500*I106+1*J106*1000+1*K106*1000+1*L106*1000 -> 61500 | T106: =VLOOKUP(C106, 'Pivot Table 2'!$A$1:$C$119, 3, FALSE) -> 34774.71 | U106: =(1-AA$6)*F106 -> 36900 | V106: =$AA$7 -> 500 | W106: =$AA$8 -> 4500 | X106: =U106-T106-V106-W106 -> -2874.7098
A107: 106 | B107: TV-69 | C107: TV-69 | D107: Yes | E107: Yes | F107: =VLOOKUP(C107, 'Pivot Table 2'!$A$1:$B$123, 2, FALSE) -> 49500 | G107: 0 | H107: 0 | I107: 0 | J107: 0 | N107: =F107+G107*4*1000+H107*10000+1*1500*I107+1*J107*1000+1*K107*1000+1*L107*1000 -> 49500 | T107: =VLOOKUP(C107, 'Pivot Table 2'!$A$1:$C$119, 3, FALSE) -> 26078.147 | U107: =(1-AA$6)*F107 -> 29700 | V107: =$AA$7 -> 500 | W107: =$AA$8 -> 4500 | X107: =U107-T107-V107-W107 -> -1378.1471
A108: 107 | B108: TV-70 | C108: TV-70 | D108: Yes | E108: Yes | F108: =VLOOKUP(C108, 'Pivot Table 2'!$A$1:$B$123, 2, FALSE) -> 69000 | G108: 0 | H108: 0 | I108: 0 | J108: 0 | N108: =F108+G108*4*1000+H108*10000+1*1500*I108+1*J108*1000+1*K108*1000+1*L108*1000 -> 69000 | T108: =VLOOKUP(C108, 'Pivot Table 2'!$A$1:$C$119, 3, FALSE) -> 41057.936 | U108: =(1-AA$6)*F108 -> 41400 | V108: =$AA$7 -> 500 | W108: =$AA$8 -> 4500 | X108: =U108-T108-V108-W108 -> -4657.9356
A109: 108 | B109: TV-71 | C109: TV-71 | D109: No | E109: Yes | F109: =VLOOKUP(C109, 'Pivot Table 2'!$A$1:$B$123, 2, FALSE) -> 5000 | G109: 0 | H109: 0 | I109: 0 | J109: 0 | N109: =F109+G109*4*1000+H109*10000+1*1500*I109+1*J109*1000+1*K109*1000+1*L109*1000 -> 5000 | T109: =VLOOKUP(C109, 'Pivot Table 2'!$A$1:$C$119, 3, FALSE) -> 2736 | U109: =(1-AA$6)*F109 -> 3000 | V109: =$AA$7 -> 500 | W109: =$AA$8 -> 4500 | X109: =U109-T109-V109-W109 -> -4736
A110: 109 | B110: TV-72 | C110: TV-72 | D110: Yes | E110: Yes | F110: =VLOOKUP(C110, 'Pivot Table 2'!$A$1:$B$123, 2, FALSE) -> 38000 | G110: 0 | H110: 0 | I110: 0 | J110: 0 | N110: =F110+G110*4*1000+H110*10000+1*1500*I110+1*J110*1000+1*K110*1000+1*L110*1000 -> 38000 | T110: =VLOOKUP(C110, 'Pivot Table 2'!$A$1:$C$119, 3, FALSE) -> 22401.161 | U110: =(1-AA$6)*F110 -> 22800 | V110: =$AA$7 -> 500 | W110: =$AA$8 -> 4500 | X110: =U110-T110-V110-W110 -> -4601.1614
A111: 110 | B111: TV-73 | C111: TV-73 | D111: Yes | E111: Yes | F111: =VLOOKUP(C111, 'Pivot Table 2'!$A$1:$B$123, 2, FALSE) -> 59900 | G111: 0 | H111: 0 | I111: 0 | J111: 0 | N111: =F111+G111*4*1000+H111*10000+1*1500*I111+1*J111*1000+1*K111*1000+1*L111*1000 -> 59900 | T111: =VLOOKUP(C111, 'Pivot Table 2'!$A$1:$C$119, 3, FALSE) -> 31133.651 | U111: =(1-AA$6)*F111 -> 35940 | V111: =$AA$7 -> 500 | W111: =$AA$8 -> 4500 | X111: =U111-T111-V111-W111 -> -193.65085
A112: 111 | B112: TV-74 | C112: TV-74 | D112: Yes | E112: Yes | F112: =VLOOKUP(C112, 'Pivot Table 2'!$A$1:$B$123, 2, FALSE) -> 48400 | G112: 0 | H112: 0 | I112: 0 | J112: 0 | N112: =F112+G112*4*1000+H112*10000+1*1500*I112+1*J112*1000+1*K112*1000+1*L112*1000 -> 48400 | T112: =VLOOKUP(C112, 'Pivot Table 2'!$A$1:$C$119, 3, FALSE) -> 25887.751 | U112: =(1-AA$6)*F112 -> 29040 | V112: =$AA$7 -> 500 | W112: =$AA$8 -> 4500 | X112: =U112-T112-V112-W112 -> -1847.7505
A113: 112 | B113: TV-75 | C113: TV-75 | D113: Yes | E113: Yes | F113: =VLOOKUP(C113, 'Pivot Table 2'!$A$1:$B$123, 2, FALSE) -> 66700 | G113: 0 | H113: 0 | I113: 0 | J113: 0 | N113: =F113+G113*4*1000+H113*10000+1*1500*I113+1*J113*1000+1*K113*1000+1*L113*1000 -> 66700 | T113: =VLOOKUP(C113, 'Pivot Table 2'!$A$1:$C$119, 3, FALSE) -> 38716.323 | U113: =(1-AA$6)*F113 -> 40020 | V113: =$AA$7 -> 500 | W113: =$AA$8 -> 4500 | X113: =U113-T113-V113-W113 -> -3696.3227
A114: 113 | B114: TV-76 | C114: TV-76 | D114: No | E114: Yes | F114: =VLOOKUP(C114, 'Pivot Table 2'!$A$1:$B$123, 2, FALSE) -> 5000 | G114: 0 | H114: 0 | I114: 0 | J114: 0 | N114: =F114+G114*4*1000+H114*10000+1*1500*I114+1*J114*1000+1*K114*1000+1*L114*1000 -> 5000 | T114: =VLOOKUP(C114, 'Pivot Table 2'!$A$1:$C$119, 3, FALSE) -> #N/A | U114: =(1-AA$6)*F114 -> 3000 | V114: =$AA$7 -> 500 | W114: =$AA$8 -> 4500 | X114: =U114-T114-V114-W114 -> #N/A
A115: 114 | B115: TV-77 | C115: TV-77 | D115: Yes | E115: Yes | F115: =VLOOKUP(C115, 'Pivot Table 2'!$A$1:$B$123, 2, FALSE) -> 13500 | G115: 0 | H115: 0 | I115: 0 | J115: 0 | N115: =F115+G115*4*1000+H115*10000+1*1500*I115+1*J115*1000+1*K115*1000+1*L115*1000 -> 13500 | T115: =VLOOKUP(C115, 'Pivot Table 2'!$A$1:$C$119, 3, FALSE) -> #N/A | U115: =(1-AA$6)*F115 -> 8100 | V115: =$AA$7 -> 500 | W115: =$AA$8 -> 4500 | X115: =U115-T115-V115-W115 -> #N/A
A116: 115 | B116: TV-78 | C116: TV-78 | D116: Yes | E116: Yes | F116: =VLOOKUP(C116, 'Pivot Table 2'!$A$1:$B$123, 2, FALSE) -> 47500 | G116: 0 | H116: 0 | I116: 0 | J116: 0 | N116: =F116+G116*4*1000+H116*10000+1*1500*I116+1*J116*1000+1*K116*1000+1*L116*1000 -> 47500 | T116: =VLOOKUP(C116, 'Pivot Table 2'!$A$1:$C$119, 3, FALSE) -> #N/A | U116: =(1-AA$6)*F116 -> 28500 | V116: =$AA$7 -> 500 | W116: =$AA$8 -> 4500 | X116: =U116-T116-V116-W116 -> #N/A
A117: 116 | B117: TV-79 | C117: TV-79 | D117: Yes | E117: Yes | F117: =VLOOKUP(C117, 'Pivot Table 2'!$A$1:$B$123, 2, FALSE) -> 67200 | G117: 0 | H117: 0 | I117: 0 | J117: 0 | N117: =F117+G117*4*1000+H117*10000+1*1500*I117+1*J117*1000+1*K117*1000+1*L117*1000 -> 67200 | T117: =VLOOKUP(C117, 'Pivot Table 2'!$A$1:$C$119, 3, FALSE) -> #N/A | U117: =(1-AA$6)*F117 -> 40320 | V117: =$AA$7 -> 500 | W117: =$AA$8 -> 4500 | X117: =U117-T117-V117-W117 -> #N/A
A118: 117 | B118: Sylvena Crest (BR-34) | C118: BR-34 | D118: Yes | E118: Yes | F118: =VLOOKUP(C118, 'Pivot Table 2'!$A$1:$B$123, 2, FALSE) -> 72000 | G118: 1 | H118: 0 | I118: 0 | J118: 2 | K118: 1 | L118: 0 | M118: Light | N118: =F118+G118*4*1000+H118*10000+1*1500*I118+1*J118*1000+1*K118*1000+1*L118*1000 -> 79000 | O118: Mid | T118: =VLOOKUP(C118, 'Pivot Table 2'!$A$1:$C$119, 3, FALSE) -> 37906.58 | U118: =(1-AA$6)*F118 -> 43200 | V118: =$AA$7 -> 500 | W118: =$AA$8 -> 4500 | X118: =U118-T118-V118-W118 -> 293.42034 | Y118: =40% -> 0.4
A119: 118 | B119: Corin Nuvella (BR-35) | C119: BR-35 | D119: Yes | E119: Yes | F119: =VLOOKUP(C119, 'Pivot Table 2'!$A$1:$B$123, 2, FALSE) -> 42500 | G119: 0 | H119: 0 | I119: 0 | J119: 3 | K119: 0 | L119: 2 | M119: Light | N119: =F119+G119*4*1000+H119*10000+1*1500*I119+1*J119*1000+1*K119*1000+1*L119*1000 -> 47500 | T119: =VLOOKUP(C119, 'Pivot Table 2'!$A$1:$C$119, 3, FALSE) -> 20489.363 | U119: =(1-AA$6)*F119 -> 25500 | V119: =$AA$7 -> 500 | W119: =$AA$8 -> 4500 | X119: =U119-T119-V119-W119 -> 10.63661 | Y119: =40% -> 0.4
A120: 119 | B120: Bronze Echo (BR-37) | C120: BR-37 | D120: Yes | E120: Yes | F120: =VLOOKUP(C120, 'Pivot Table 2'!$A$1:$B$123, 2, FALSE) -> 5000 | G120: 1 | H120: 0 | I120: 0 | J120: 4 | K120: 0 | L120: 0 | M120: Light | N120: =F120+G120*4*1000+H120*10000+1*1500*I120+1*J120*1000+1*K120*1000+1*L120*1000 -> 13000 | O120: Mid | T120: =VLOOKUP(C120, 'Pivot Table 2'!$A$1:$C$119, 3, FALSE) -> 2736 | U120: =(1-AA$6)*F120 -> 3000 | V120: =$AA$7 -> 500 | W120: =$AA$8 -> 4500 | X120: =U120-T120-V120-W120 -> -4736
A121: 120 | B121: Brass Korvana (BR-38) | C121: BR-38 | D121: Yes | E121: Yes | F121: =VLOOKUP(C121, 'Pivot Table 2'!$A$1:$B$123, 2, FALSE) -> 60000 | G121: 1 | H121: 0 | I121: 0 | J121: 0 | K121: 2 | L121: 1 | M121: Light | N121: =F121+G121*4*1000+H121*10000+1*1500*I121+1*J121*1000+1*K121*1000+1*L121*1000 -> 67000 | T121: =VLOOKUP(C121, 'Pivot Table 2'!$A$1:$C$119, 3, FALSE) -> 32897.094 | U121: =(1-AA$6)*F121 -> 36000 | V121: =$AA$7 -> 500 | W121: =$AA$8 -> 4500 | X121: =U121-T121-V121-W121 -> -1897.0936 | Y121: =35% -> 0.35
...

Sheet Material
A1: sno | B1: material_name | C1: material_type | D1: material_crm_code | E1: material_sap_code | F1: Price | G1: cost
A2: 1 | B2: =VLOOKUP(E2, SAP!$G$1:$V$236, 16, FALSE) -> Charcoal (PS)-Cream-Matte-PN 06167 || 8 ft x 5 inch | C2: material | D2: {=unique(Mapping!C2:C616)} -> WHSWPLCS017 | E2: WHSWPLCS017 | F2: =vlookup(E2,SAP!G$1:S$236,13,0) -> 2500 | G2: =vlookup(E2,SAP!G$1:S$236,12,0) -> 1084.0678
A3: 2 | B3: =VLOOKUP(E3, SAP!$G$1:$V$236, 16, FALSE) -> Charcoal (PS)-Pine-Wood Grain-PN 03221 || 8 ft x 5 inch | C3: material | D3: WHSWPLCS020 | E3: WHSWPLCS020 | F3: =vlookup(E3,SAP!G$1:S$236,13,0) -> 1500 | G3: =vlookup(E3,SAP!G$1:S$236,12,0) -> 595.86441
A4: 3 | B4: =VLOOKUP(E4, SAP!$G$1:$V$236, 16, FALSE) -> Charcoal (PS)-Light-Wood Grain-PN 06277 || 8 ft x 5 inch | C4: material | D4: WHSWPLCS103 | E4: WHSWPLCS103 | F4: =vlookup(E4,SAP!G$1:S$236,13,0) -> 1500 | G4: =vlookup(E4,SAP!G$1:S$236,12,0) -> 609.49153
A5: 4 | B5: =VLOOKUP(E5, SAP!$G$1:$V$236, 16, FALSE) -> Charcoal (PS)-Brown-Wood Grain-PN 03399 || 8 ft x 5 inch | C5: material | D5: WHSWPLCS079 | E5: WHSWPLCS079 | F5: =vlookup(E5,SAP!G$1:S$236,13,0) -> 2000 | G5: =vlookup(E5,SAP!G$1:S$236,12,0) -> 894.16949
A6: 5 | B6: =VLOOKUP(E6, SAP!$G$1:$V$236, 16, FALSE) -> 240 LED strip light (5m) | C6: material | D6: WHSWLTLEDS164 | E6: WHSWLTLEDS164 | F6: =vlookup(E6,SAP!G$1:S$236,13,0) -> 1500 | G6: =vlookup(E6,SAP!G$1:S$236,12,0) -> 750
A7: 6 | B7: =VLOOKUP(E7, SAP!$G$1:$V$236, 16, FALSE) -> 16X16 Alumnium Angular Profile (3m) || 16 x 16 mm | C7: material | D7: WHSWLTLEDS165 | E7: WHSWLTLEDS165 | F7: =vlookup(E7,SAP!G$1:S$236,13,0) -> 500 | G7: =vlookup(E7,SAP!G$1:S$236,12,0) -> 270
A8: 7 | B8: =VLOOKUP(E8, SAP!$G$1:$V$236, 16, FALSE) -> 10 AMP (24V) LED Power Adapter | C8: material | D8: WHSWLTLEDS167 | E8: WHSWLTLEDS167 | F8: =vlookup(E8,SAP!G$1:S$236,13,0) -> 1500 | G8: =vlookup(E8,SAP!G$1:S$236,12,0) -> 750
A9: 8 | B9: =VLOOKUP(E9, SAP!$G$1:$V$236, 16, FALSE) -> Aluminium channels reactangular 1 mm || 12 ft x 50 mm | C9: material | D9: WHSWCHALS162 | E9: WHSWCHALS162 | F9: =vlookup(E9,SAP!G$1:S$236,13,0) -> 1000 | G9: =vlookup(E9,SAP!G$1:S$236,12,0) -> 675
A10: 9 | B10: =VLOOKUP(E10, SAP!$G$1:$V$236, 16, FALSE) -> PVC board 11 mm || 8 ft x 4 ft | C10: material | D10: WHSWBDPS161 | E10: WHSWBDPS161 | F10: =vlookup(E10,SAP!G$1:S$236,13,0) -> 2500 | G10: =vlookup(E10,SAP!G$1:S$236,12,0) -> 2050
A11: 10 | B11: =VLOOKUP(E11, SAP!$G$1:$V$236, 16, FALSE) -> Wall Bidding WPC 08 | C11: material | D11: WHSWBIW08S223 | E11: WHSWBIW08S223 | F11: =vlookup(E11,SAP!G$1:S$236,13,0) -> 500 | G11: =vlookup(E11,SAP!G$1:S$236,12,0) -> 250
A12: 11 | B12: =VLOOKUP(E12, SAP!$G$1:$V$236, 16, FALSE) -> Charcoal (PS)-Dark-Wood Grain-PN 02746 || 9.5 ft x 4.8 inch | C12: material | D12: WHSWPLCS042 | E12: WHSWPLCS042 | F12: =vlookup(E12,SAP!G$1:S$236,13,0) -> 2000 | G12: =vlookup(E12,SAP!G$1:S$236,12,0) -> 819.59322
A13: 12 | B13: =VLOOKUP(E13, SAP!$G$1:$V$236, 16, FALSE) -> Wall Bidding WPC 01 | C13: material | D13: WHSWBIW01S216 | E13: WHSWBIW01S216 | F13: =vlookup(E13,SAP!G$1:S$236,13,0) -> 500 | G13: =vlookup(E13,SAP!G$1:S$236,12,0) -> 250
A14: 13 | B14: =VLOOKUP(E14, SAP!$G$1:$V$236, 16, FALSE) -> Charcoal (PS)-Walnut-Wood Grain-PN 03223 || 8 ft x 5 inch | C14: material | D14: WHSWPLCS021 | E14: WHSWPLCS021 | F14: =vlookup(E14,SAP!G$1:S$236,13,0) -> 1500 | G14: =vlookup(E14,SAP!G$1:S$236,12,0) -> 595.86441
... A94: 93 | B94: =VLOOKUP(E94, SAP!$G$1:$V$236, 16, FALSE) -> Silicon sealant glue | C94: material | D94: WHSWGLSS168 | E94: WHSWGLSS168 | F94: =vlookup(E94,SAP!G$1:S$236,13,0) -> 500 | G94: =vlookup(E94,SAP!G$1:S$236,12,0) -> 273.6

Sheet Mapping
A1: sno | B1: design_code | C1: material_crm_code | D1: material_md_code | E1: qty | F1: Price | G1: cost_price
B2: BR-1-1 | C2: WHSWPLCS017 | D2: 6167 | E2: 0 | F2: =VLOOKUP(C2, Material!$E$2:$F$94, 2, FALSE) -> 2500 | G2: =VLOOKUP(C2, Material!$E$2:$G$94, 3, FALSE) -> 1084.0678
B3: BR-1-2 | C3: WHSWPLCS020 | D3: 3221 | E3: 0 | F3: =VLOOKUP(C3, Material!$E$2:$F$94, 2, FALSE) -> 1500 | G3: =VLOOKUP(C3, Material!$E$2:$G$94, 3, FALSE) -> 595.86441
B4: BR-2-1 | C4: WHSWPLCS103 | D4: 6277 | E4: 0 | F4: =VLOOKUP(C4, Material!$E$2:$F$94, 2, FALSE) -> 1500 | G4: =VLOOKUP(C4, Material!$E$2:$G$94, 3, FALSE) -> 609.49153
B5: BR-2-2 | C5: WHSWPLCS079 | D5: 3399 | E5: 0 | F5: =VLOOKUP(C5, Material!$E$2:$F$94, 2, FALSE) -> 2000 | G5: =VLOOKUP(C5, Material!$E$2:$G$94, 3, FALSE) -> 894.16949
B6: BR-3-1 | C6: WHSWPLCS017 | D6: 6167 | E6: 5 | F6: =VLOOKUP(C6, Material!$E$2:$F$94, 2, FALSE) -> 2500 | G6: =VLOOKUP(C6, Material!$E$2:$G$94, 3, FALSE) -> 1084.0678
B7: BR-3-1 | C7: WHSWLTLEDS164 | D7: LED-1 | E7: 1 | F7: =VLOOKUP(C7, Material!$E$2:$F$94, 2, FALSE) -> 1500 | G7: =VLOOKUP(C7, Material!$E$2:$G$94, 3, FALSE) -> 750
B8: BR-3-1 | C8: WHSWLTLEDS165 | D8: AL-1 | E8: 1 | F8: =VLOOKUP(C8, Material!$E$2:$F$94, 2, FALSE) -> 500 | G8: =VLOOKUP(C8, Material!$E$2:$G$94, 3, FALSE) -> 270
B9: BR-3-1 | C9: WHSWLTLEDS167 | D9: PA-1 | E9: 1 | F9: =VLOOKUP(C9, Material!$E$2:$F$94, 2, FALSE) -> 1500 | G9: =VLOOKUP(C9, Material!$E$2:$G$94, 3, FALSE) -> 750
B10: BR-3-1 | C10: WHSWCHALS162 | D10: ALC-1 | E10: 2 | F10: =VLOOKUP(C10, Material!$E$2:$F$94, 2, FALSE) -> 1000 | G10: =VLOOKUP(C10, Material!$E$2:$G$94, 3, FALSE) -> 675
B11: BR-3-1 | C11: WHSWBDPS161 | D11: PVCBD-1 | E11: 1 | F11: =VLOOKUP(C11, Material!$E$2:$F$94, 2, FALSE) -> 2500 | G11: =VLOOKUP(C11, Material!$E$2:$G$94, 3, FALSE) -> 2050
B12: BR-3-1 | C12: WHSWBIW08S223 | D12: BD-08 | E12: 2 | F12: =VLOOKUP(C12, Material!$E$2:$F$94, 2, FALSE) -> 500 | G12: =VLOOKUP(C12, Material!$E$2:$G$94, 3, FALSE) -> 250
B13: BR-3-2 | C13: WHSWPLCS042 | D13: 2746 | E13: 5 | F13: =VLOOKUP(C13, Material!$E$2:$F$94, 2, FALSE) -> 2000 | G13: =VLOOKUP(C13, Material!$E$2:$G$94, 3, FALSE) -> 819.59322
B14: BR-3-2 | C14: WHSWLTLEDS164 | D14: LED-1 | E14: 1 | F14: =VLOOKUP(C14, Material!$E$2:$F$94, 2, FALSE) -> 1500 | G14: =VLOOKUP(C14, Material!$E$2:$G$94, 3, FALSE) -> 750
B15: BR-3-2 | C15: WHSWLTLEDS165 | D15: AL-1 | E15: 1 | F15: =VLOOKUP(C15, Material!$E$2:$F$94, 2, FALSE) -> 500 | G15: =VLOOKUP(C15, Material!$E$2:$G$94, 3, FALSE) -> 270
B16: BR-3-2 | C16: WHSWLTLEDS167 | D16: PA-1 | E16: 1 | F16: =VLOOKUP(C16, Material!$E$2:$F$94, 2, FALSE) -> 1500 | G16: =VLOOKUP(C16, Material!$E$2:$G$94, 3, FALSE) -> 750
B17: BR-3-2 | C17: WHSWCHALS162 | D17: ALC-1 | E17: 2 | F17: =VLOOKUP(C17, Material!$E$2:$F$94, 2, FALSE) -> 1000 | G17: =VLOOKUP(C17, Material!$E$2:$G$94, 3, FALSE) -> 675
B18: BR-3-2 | C18: WHSWBDPS161 | D18: PVCBD-1 | E18: 1 | F18: =VLOOKUP(C18, Material!$E$2:$F$94, 2, FALSE) -> 2500 | G18: =VLOOKUP(C18, Material!$E$2:$G$94, 3, FALSE) -> 2050
B19: BR-3-2 | C19: WHSWBIW01S216 | D19: BD-01 | E19: 2 | F19: =VLOOKUP(C19, Material!$E$2:$F$94, 2, FALSE) -> 500 | G19: =VLOOKUP(C19, Material!$E$2:$G$94, 3, FALSE) -> 250
B20: BR-4-1 | C20: WHSWPLCS021 | D20: 3223 | E20: 10 | F20: =VLOOKUP(C20, Material!$E$2:$F$94, 2, FALSE) -> 1500 | G20: =VLOOKUP(C20, Material!$E$2:$G$94, 3, FALSE) -> 595.86441
B21: BR-4-1 | C21: WHSWLTLEDS164 | D21: LED-1 | E21: 1 | F21: =VLOOKUP(C21, Material!$E$2:$F$94, 2, FALSE) -> 1500 | G21: =VLOOKUP(C21, Material!$E$2:$G$94, 3, FALSE) -> 750
B22: BR-4-1 | C22: WHSWLTLEDS165 | D22: AL-1 | E22: 1 | F22: =VLOOKUP(C22, Material!$E$2:$F$94, 2, FALSE) -> 500 | G22: =VLOOKUP(C22, Material!$E$2:$G$94, 3, FALSE) -> 270
B23: BR-4-1 | C23: WHSWLTLEDS167 | D23: PA-1 | E23: 1 | F23: =VLOOKUP(C23, Material!$E$2:$F$94, 2, FALSE) -> 1500 | G23: =VLOOKUP(C23, Material!$E$2:$G$94, 3, FALSE) -> 750
B24: BR-4-1 | C24: WHSWCHALS162 | D24: ALC-1 | E24: 2 | F24: =VLOOKUP(C24, Material!$E$2:$F$94, 2, FALSE) -> 1000 | G24: =VLOOKUP(C24, Material!$E$2:$G$94, 3, FALSE) -> 675
B25: BR-4-1 | C25: WHSWBDPS161 | D25: PVCBD-1 | E25: 2 | F25: =VLOOKUP(C25, Material!$E$2:$F$94, 2, FALSE) -> 2500 | G25: =VLOOKUP(C25, Material!$E$2:$G$94, 3, FALSE) -> 2050
B26: BR-4-1 | C26: WHSWSSBWBLWS171 | D26: SB | E26: 2 | F26: =VLOOKUP(C26, Material!$E$2:$F$94, 2, FALSE) -> 1000 | G26: =VLOOKUP(C26, Material!$E$2:$G$94, 3, FALSE) -> 250
B27: BR-4-1 | C27: WHSWSRBWBLWS181 | D27: Shelf | E27: 1 | F27: =VLOOKUP(C27, Material!$E$2:$F$94, 2, FALSE) -> 1000 | G27: =VLOOKUP(C27, Material!$E$2:$G$94, 3, FALSE) -> 250
B28: BR-4-1 | C28: WHSWBIW01S216 | D28: BD-01 | E28: 2 | F28: =VLOOKUP(C28, Material!$E$2:$F$94, 2, FALSE) -> 500 | G28: =VLOOKUP(C28, Material!$E$2:$G$94, 3, FALSE) -> 250
B29: BR-4-2 | C29: WHSWPLCS055 | D29: 5656 | E29: 10 | F29: =VLOOKUP(C29, Material!$E$2:$F$94, 2, FALSE) -> 2000 | G29: =VLOOKUP(C29, Material!$E$2:$G$94, 3, FALSE) -> 968.74576
B30: BR-4-2 | C30: WHSWLTLEDS164 | D30: LED-1 | E30: 1 | F30: =VLOOKUP(C30, Material!$E$2:$F$94, 2, FALSE) -> 1500 | G30: =VLOOKUP(C30, Material!$E$2:$G$94, 3, FALSE) -> 750
B31: BR-4-2 | C31: WHSWLTLEDS165 | D31: AL-1 | E31: 1 | F31: =VLOOKUP(C31, Material!$E$2:$F$94, 2, FALSE) -> 500 | G31: =VLOOKUP(C31, Material!$E$2:$G$94, 3, FALSE) -> 270
B32: BR-4-2 | C32: WHSWLTLEDS167 | D32: PA-1 | E32: 1 | F32: =VLOOKUP(C32, Material!$E$2:$F$94, 2, FALSE) -> 1500 | G32: =VLOOKUP(C32, Material!$E$2:$G$94, 3, FALSE) -> 750
B33: BR-4-2 | C33: WHSWCHALS162 | D33: ALC-1 | E33: 2 | F33: =VLOOKUP(C33, Material!$E$2:$F$94, 2, FALSE) -> 1000 | G33: =VLOOKUP(C33, Material!$E$2:$G$94, 3, FALSE) -> 675
B34: BR-4-2 | C34: WHSWBDPS161 | D34: PVCBD-1 | E34: 2 | F34: =VLOOKUP(C34, Material!$E$2:$F$94, 2, FALSE) -> 2500 | G34: =VLOOKUP(C34, Material!$E$2:$G$94, 3, FALSE) -> 2050
B35: BR-4-2 | C35: WHSWSSBWBLWS171 | D35: SB | E35: 2 | F35: =VLOOKUP(C35, Material!$E$2:$F$94, 2, FALSE) -> 1000 | G35: =VLOOKUP(C35, Material!$E$2:$G$94, 3, FALSE) -> 250
B36: BR-4-2 | C36: WHSWSRBWBLWS181 | D36: Shelf | E36: 1 | F36: =VLOOKUP(C36, Material!$E$2:$F$94, 2, FALSE) -> 1000 | G36: =VLOOKUP(C36, Material!$E$2:$G$94, 3, FALSE) -> 250
B37: BR-4-2 | C37: WHSWBIW03S218 | D37: BD-03 | E37: 2 | F37: =VLOOKUP(C37, Material!$E$2:$F$94, 2, FALSE) -> 500 | G37: =VLOOKUP(C37, Material!$E$2:$G$94, 3, FALSE) -> 250
B38: BR-5-1 | C38: WHSWPLCS106 | D38: 3889 | E38: 20 | F38: =VLOOKUP(C38, Material!$E$2:$F$94, 2, FALSE) -> 1500 | G38: =VLOOKUP(C38, Material!$E$2:$G$94, 3, FALSE) -> 745.01695
B39: BR-5-2 | C39: WHSWPLCS020 | D39: 3221 | E39: 20 | F39: =VLOOKUP(C39, Material!$E$2:$F$94, 2, FALSE) -> 1500 | G39: =VLOOKUP(C39, Material!$E$2:$G$94, 3, FALSE) -> 595.86441
B40: BR-6-1 | C40: WHSWPLCS025 | D40: 545 | E40: 20 | F40: =VLOOKUP(C40, Material!$E$2:$F$94, 2, FALSE) -> 2000 | G40: =VLOOKUP(C40, Material!$E$2:$G$94, 3, FALSE) -> 819.59322
B41: BR-6-1 | C41: WHSWLTLEDS164 | D41: LED-1 | E41: 1 | F41: =VLOOKUP(C41, Material!$E$2:$F$94, 2, FALSE) -> 1500 | G41: =VLOOKUP(C41, Material!$E$2:$G$94, 3, FALSE) -> 750
B42: BR-6-1 | C42: WHSWLTLEDS165 | D42: AL-1 | E42: 1 | F42: =VLOOKUP(C42, Material!$E$2:$F$94, 2, FALSE) -> 500 | G42: =VLOOKUP(C42, Material!$E$2:$G$94, 3, FALSE) -> 270
B43: BR-6-1 | C43: WHSWLTLEDS167 | D43: PA-1 | E43: 1 | F43: =VLOOKUP(C43, Material!$E$2:$F$94, 2, FALSE) -> 1500 | G43: =VLOOKUP(C43, Material!$E$2:$G$94, 3, FALSE) -> 750
B44: BR-6-1 | C44: WHSWCHALS162 | D44: ALC-1 | E44: 2 | F44: =VLOOKUP(C44, Material!$E$2:$F$94, 2, FALSE) -> 1000 | G44: =VLOOKUP(C44, Material!$E$2:$G$94, 3, FALSE) -> 675
B45: BR-6-1 | C45: WHSWBDPS161 | D45: PVCBD-1 | E45: 3 | F45: =VLOOKUP(C45, Material!$E$2:$F$94, 2, FALSE) -> 2500 | G45: =VLOOKUP(C45, Material!$E$2:$G$94, 3, FALSE) -> 2050
B46: BR-6-1 | C46: WHSWSSBWBLWS171 | D46: SB | E46: 4 | F46: =VLOOKUP(C46, Material!$E$2:$F$94, 2, FALSE) -> 1000 | G46: =VLOOKUP(C46, Material!$E$2:$G$94, 3, FALSE) -> 250
B47: BR-6-1 | C47: WHSWBIW02S217 | D47: BD-02 | E47: 2 | F47: =VLOOKUP(C47, Material!$E$2:$F$94, 2, FALSE) -> 500 | G47: =VLOOKUP(C47, Material!$E$2:$G$94, 3, FALSE) -> 250
B48: BR-6-2 | C48: WHSWPLCS102 | D48: 5667 | E48: 20 | F48: =VLOOKUP(C48, Material!$E$2:$F$94, 2, FALSE) -> 1500 | G48: =VLOOKUP(C48, Material!$E$2:$G$94, 3, FALSE) -> 609.49153
B49: BR-6-2 | C49: WHSWLTLEDS164 | D49: LED-1 | E49: 1 | F49: =VLOOKUP(C49, Material!$E$2:$F$94, 2, FALSE) -> 1500 | G49: =VLOOKUP(C49, Material!$E$2:$G$94, 3, FALSE) -> 750
B50: BR-6-2 | C50: WHSWLTLEDS165 | D50: AL-1 | E50: 1 | F50: =VLOOKUP(C50, Material!$E$2:$F$94, 2, FALSE) -> 500 | G50: =VLOOKUP(C50, Material!$E$2:$G$94, 3, FALSE) -> 270
B51: BR-6-2 | C51: WHSWLTLEDS167 | D51: PA-1 | E51: 1 | F51: =VLOOKUP(C51, Material!$E$2:$F$94, 2, FALSE) -> 1500 | G51: =VLOOKUP(C51, Material!$E$2:$G$94, 3, FALSE) -> 750
B52: BR-6-2 | C52: WHSWCHALS162 | D52: ALC-1 | E52: 2 | F52: =VLOOKUP(C52, Material!$E$2:$F$94, 2, FALSE) -> 1000 | G52: =VLOOKUP(C52, Material!$E$2:$G$94, 3, FALSE) -> 675
B53: BR-6-2 | C53: WHSWBDPS161 | D53: PVCBD-1 | E53: 3 | F53: =VLOOKUP(C53, Material!$E$2:$F$94, 2, FALSE) -> 2500 | G53: =VLOOKUP(C53, Material!$E$2:$G$94, 3, FALSE) -> 2050
B54: BR-6-2 | C54: WHSWSSBWBLWS171 | D54: SB | E54: 4 | F54: =VLOOKUP(C54, Material!$E$2:$F$94, 2, FALSE) -> 1000 | G54: =VLOOKUP(C54, Material!$E$2:$G$94, 3, FALSE) -> 250
B55: BR-6-2 | C55: WHSWBIW01S216 | D55: BD-01 | E55: 2 | F55: =VLOOKUP(C55, Material!$E$2:$F$94, 2, FALSE) -> 500 | G55: =VLOOKUP(C55, Material!$E$2:$G$94, 3, FALSE) -> 250
B56: BR-7-1 | C56: WHSWPLCS076 | D56: 3027 | E56: 20 | F56: =VLOOKUP(C56, Material!$E$2:$F$94, 2, FALSE) -> 1500 | G56: =VLOOKUP(C56, Material!$E$2:$G$94, 3, FALSE) -> 609.49153
B57: BR-7-2 | C57: WHSWPLCS051 | D57: 149 | E57: 20 | F57: =VLOOKUP(C57, Material!$E$2:$F$94, 2, FALSE) -> 1500 | G57: =VLOOKUP(C57, Material!$E$2:$G$94, 3, FALSE) -> 670.44068
B58: BR-8-1 | C58: WHSWPLCS029 | D58: 155 | E58: 14 | F58: =VLOOKUP(C58, Material!$E$2:$F$94, 2, FALSE) -> 1500 | G58: =VLOOKUP(C58, Material!$E$2:$G$94, 3, FALSE) -> 670.44068
B59: BR-8-1 | C59: WHSWLTLEDS164 | D59: LED-1 | E59: 2 | F59: =VLOOKUP(C59, Material!$E$2:$F$94, 2, FALSE) -> 1500 | G59: =VLOOKUP(C59, Material!$E$2:$G$94, 3, FALSE) -> 750
B60: BR-8-1 | C60: WHSWLTLEDS165 | D60: AL-1 | E60: 2 | F60: =VLOOKUP(C60, Material!$E$2:$F$94, 2, FALSE) -> 500 | G60: =VLOOKUP(C60, Material!$E$2:$G$94, 3, FALSE) -> 270
B61: BR-8-1 | C61: WHSWLTLEDS167 | D61: PA-1 | E61: 2 | F61: =VLOOKUP(C61, Material!$E$2:$F$94, 2, FALSE) -> 1500 | G61: =VLOOKUP(C61, Material!$E$2:$G$94, 3, FALSE) -> 750
B62: BR-8-1 | C62: WHSWCHALS162 | D62: ALC-1 | E62: 2 | F62: =VLOOKUP(C62, Material!$E$2:$F$94, 2, FALSE) -> 1000 | G62: =VLOOKUP(C62, Material!$E$2:$G$94, 3, FALSE) -> 675
B63: BR-8-1 | C63: WHSWBDPS161 | D63: PVCBD-1 | E63: 4 | F63: =VLOOKUP(C63, Material!$E$2:$F$94, 2, FALSE) -> 2500 | G63: =VLOOKUP(C63, Material!$E$2:$G$94, 3, FALSE) -> 2050
B64: BR-8-1 | C64: WHSWSSBWBMWS172 | D64: SB | E64: 4 | F64: =VLOOKUP(C64, Material!$E$2:$F$94, 2, FALSE) -> 1000 | G64: =VLOOKUP(C64, Material!$E$2:$G$94, 3, FALSE) -> 250
B65: BR-8-1 | C65: WHSWBIW03S218 | D65: BD-03 | E65: 2 | F65: =VLOOKUP(C65, Material!$E$2:$F$94, 2, FALSE) -> 500 | G65: =VLOOKUP(C65, Material!$E$2:$G$94, 3, FALSE) -> 250
B66: BR-8-2 | C66: WHSWPLCS051 | D66: 149 | E66: 14 | F66: =VLOOKUP(C66, Material!$E$2:$F$94, 2, FALSE) -> 1500 | G66: =VLOOKUP(C66, Material!$E$2:$G$94, 3, FALSE) -> 670.44068
B67: BR-8-2 | C67: WHSWLTLEDS164 | D67: LED-1 | E67: 2 | F67: =VLOOKUP(C67, Material!$E$2:$F$94, 2, FALSE) -> 1500 | G67: =VLOOKUP(C67, Material!$E$2:$G$94, 3, FALSE) -> 750
B68: BR-8-2 | C68: WHSWLTLEDS165 | D68: AL-1 | E68: 2 | F68: =VLOOKUP(C68, Material!$E$2:$F$94, 2, FALSE) -> 500 | G68: =VLOOKUP(C68, Material!$E$2:$G$94, 3, FALSE) -> 270
B69: BR-8-2 | C69: WHSWLTLEDS167 | D69: PA-1 | E69: 2 | F69: =VLOOKUP(C69, Material!$E$2:$F$94, 2, FALSE) -> 1500 | G69: =VLOOKUP(C69, Material!$E$2:$G$94, 3, FALSE) -> 750
B70: BR-8-2 | C70: WHSWCHALS162 | D70: ALC-1 | E70: 2 | F70: =VLOOKUP(C70, Material!$E$2:$F$94, 2, FALSE) -> 1000 | G70: =VLOOKUP(C70, Material!$E$2:$G$94, 3, FALSE) -> 675
B71: BR-8-2 | C71: WHSWBDPS161 | D71: PVCBD-1 | E71: 4 | F71: =VLOOKUP(C71, Material!$E$2:$F$94, 2, FALSE) -> 2500 | G71: =VLOOKUP(C71, Material!$E$2:$G$94, 3, FALSE) -> 2050
B72: BR-8-2 | C72: WHSWSSBWBMWS172 | D72: SB | E72: 4 | F72: =VLOOKUP(C72, Material!$E$2:$F$94, 2, FALSE) -> 1000 | G72: =VLOOKUP(C72, Material!$E$2:$G$94, 3, FALSE) -> 250
B73: BR-8-2 | C73: WHSWBIW02S217 | D73: BD-02 | E73: 2 | F73: =VLOOKUP(C73, Material!$E$2:$F$94, 2, FALSE) -> 500 | G73: =VLOOKUP(C73, Material!$E$2:$G$94, 3, FALSE) -> 250
B74: BR-12-1 | C74: WHSWPLCS102 | D74: 5667 | E74: 12 | F74: =VLOOKUP(C74, Material!$E$2:$F$94, 2, FALSE) -> 1500 | G74: =VLOOKUP(C74, Material!$E$2:$G$94, 3, FALSE) -> 609.49153
B75: BR-12-1 | C75: WHSWLTLEDS164 | D75: LED-1 | E75: 2 | F75: =VLOOKUP(C75, Material!$E$2:$F$94, 2, FALSE) -> 1500 | G75: =VLOOKUP(C75, Material!$E$2:$G$94, 3, FALSE) -> 750
B76: BR-12-1 | C76: WHSWLTLEDS165 | D76: AL-1 | E76: 2 | F76: =VLOOKUP(C76, Material!$E$2:$F$94, 2, FALSE) -> 500 | G76: =VLOOKUP(C76, Material!$E$2:$G$94, 3, FALSE) -> 270
B77: BR-12-1 | C77: WHSWLTLEDS167 | D77: PA-1 | E77: 2 | F77: =VLOOKUP(C77, Material!$E$2:$F$94, 2, FALSE) -> 1500 | G77: =VLOOKUP(C77, Material!$E$2:$G$94, 3, FALSE) -> 750
B78: BR-12-1 | C78: WHSWCHALS162 | D78: ALC-1 | E78: 2 | F78: =VLOOKUP(C78, Material!$E$2:$F$94, 2, FALSE) -> 1000 | G78: =VLOOKUP(C78, Material!$E$2:$G$94, 3, FALSE) -> 675
B79: BR-12-1 | C79: WHSWBDPS161 | D79: PVCBD-1 | E79: 2 | F79: =VLOOKUP(C79, Material!$E$2:$F$94, 2, FALSE) -> 2500 | G79: =VLOOKUP(C79, Material!$E$2:$G$94, 3, FALSE) -> 2050
B80: BR-12-1 | C80: WHSWSRBWBLWS181 | D80: RB | E80: 2 | F80: =VLOOKUP(C80, Material!$E$2:$F$94, 2, FALSE) -> 1000 | G80: =VLOOKUP(C80, Material!$E$2:$G$94, 3, FALSE) -> 250
B81: BR-12-1 | C81: WHSWS300SLWS191 | D81: Shelf | E81: 1 | F81: =VLOOKUP(C81, Material!$E$2:$F$94, 2, FALSE) -> 1000 | G81: =VLOOKUP(C81, Material!$E$2:$G$94, 3, FALSE) -> 250
B82: BR-12-1 | C82: WHSWBIW02S217 | D82: BD-02 | E82: 2 | F82: =VLOOKUP(C82, Material!$E$2:$F$94, 2, FALSE) -> 500 | G82: =VLOOKUP(C82, Material!$E$2:$G$94, 3, FALSE) -> 250
B83: BR-13-1 | C83: WHSWPLCS036 | D83: 2347 | E83: 15 | F83: =VLOOKUP(C83, Material!$E$2:$F$94, 2, FALSE) -> 2500 | G83: =VLOOKUP(C83, Material!$E$2:$G$94, 3, FALSE) -> 1117.8983
B84: BR-15-1 | C84: WHSWPLCPCS118 | D84: 2308 | E84: 3 | F84: =VLOOKUP(C84, Material!$E$2:$F$94, 2, FALSE) -> 7500 | G84: =VLOOKUP(C84, Material!$E$2:$G$94, 3, FALSE) -> 4148.3871
B85: BR-15-1 | C85: WHSWLTLEDS164 | D85: LED-1 | E85: 1 | F85: =VLOOKUP(C85, Material!$E$2:$F$94, 2, FALSE) -> 1500 | G85: =VLOOKUP(C85, Material!$E$2:$G$94, 3, FALSE) -> 750
B86: BR-15-1 | C86: WHSWLTLEDS165 | D86: AL-1 | E86: 1 | F86: =VLOOKUP(C86, Material!$E$2:$F$94, 2, FALSE) -> 500 | G86: =VLOOKUP(C86, Material!$E$2:$G$94, 3, FALSE) -> 270
B87: BR-15-1 | C87: WHSWLTLEDS167 | D87: PA-1 | E87: 1 | F87: =VLOOKUP(C87, Material!$E$2:$F$94, 2, FALSE) -> 1500 | G87: =VLOOKUP(C87, Material!$E$2:$G$94, 3, FALSE) -> 750
B88: BR-15-1 | C88: WHSWCHALS162 | D88: ALC-1 | E88: 2 | F88: =VLOOKUP(C88, Material!$E$2:$F$94, 2, FALSE) -> 1000 | G88: =VLOOKUP(C88, Material!$E$2:$G$94, 3, FALSE) -> 675
B89: BR-15-1 | C89: WHSWBDPS161 | D89: PVCBD-1 | E89: 2 | F89: =VLOOKUP(C89, Material!$E$2:$F$94, 2, FALSE) -> 2500 | G89: =VLOOKUP(C89, Material!$E$2:$G$94, 3, FALSE) -> 2050
B90: BR-15-1 | C90: WHSWSSBWBMWS172 | D90: SB | E90: 3 | F90: =VLOOKUP(C90, Material!$E$2:$F$94, 2, FALSE) -> 1000 | G90: =VLOOKUP(C90, Material!$E$2:$G$94, 3, FALSE) -> 250
B91: BR-15-1 | C91: WHSWS300SLWS191 | D91: Shelf | E91: 2 | F91: =VLOOKUP(C91, Material!$E$2:$F$94, 2, FALSE) -> 1000 | G91: =VLOOKUP(C91, Material!$E$2:$G$94, 3, FALSE) -> 250
B92: BR-15-1 | C92: WHSWTSSBG6TS233 | D92: T-01 | E92: 3 | F92: =VLOOKUP(C92, Material!$E$2:$F$94, 2, FALSE) -> 600 | G92: =VLOOKUP(C92, Material!$E$2:$G$94, 3, FALSE) -> 500
B93: BR-15-1 | C93: WHSWBIW02S217 | D93: BD-02 | E93: 2 | F93: =VLOOKUP(C93, Material!$E$2:$F$94, 2, FALSE) -> 500 | G93: =VLOOKUP(C93, Material!$E$2:$G$94, 3, FALSE) -> 250
B94: BR-15-2 | C94: WHSWPLCPCS150 | D94: 2327 | E94: 3 | F94: =VLOOKUP(C94, Material!$E$2:$F$94, 2, FALSE) -> 7500 | G94: =VLOOKUP(C94, Material!$E$2:$G$94, 3, FALSE) -> 4148.3871
B95: BR-15-2 | C95: WHSWLTLEDS164 | D95: LED-1 | E95: 1 | F95: =VLOOKUP(C95, Material!$E$2:$F$94, 2, FALSE) -> 1500 | G95: =VLOOKUP(C95, Material!$E$2:$G$94, 3, FALSE) -> 750
B96: BR-15-2 | C96: WHSWLTLEDS165 | D96: AL-1 | E96: 1 | F96: =VLOOKUP(C96, Material!$E$2:$F$94, 2, FALSE) -> 500 | G96: =VLOOKUP(C96, Material!$E$2:$G$94, 3, FALSE) -> 270
B97: BR-15-2 | C97: WHSWLTLEDS167 | D97: PA-1 | E97: 1 | F97: =VLOOKUP(C97, Material!$E$2:$F$94, 2, FALSE) -> 1500 | G97: =VLOOKUP(C97, Material!$E$2:$G$94, 3, FALSE) -> 750
B98: BR-15-2 | C98: WHSWCHALS162 | D98: ALC-1 | E98: 1 | F98: =VLOOKUP(C98, Material!$E$2:$F$94, 2, FALSE) -> 1000 | G98: =VLOOKUP(C98, Material!$E$2:$G$94, 3, FALSE) -> 675
B99: BR-15-2 | C99: WHSWBDPS161 | D99: PVCBD-1 | E99: 2 | F99: =VLOOKUP(C99, Material!$E$2:$F$94, 2, FALSE) -> 2500 | G99: =VLOOKUP(C99, Material!$E$2:$G$94, 3, FALSE) -> 2050
B100: BR-15-2 | C100: WHSWSSBWBMWS172 | D100: SB | E100: 3 | F100: =VLOOKUP(C100, Material!$E$2:$F$94, 2, FALSE) -> 1000 | G100: =VLOOKUP(C100, Material!$E$2:$G$94, 3, FALSE) -> 250
...

Sheet Pivot Table 1
H1: Product name
H2: =VLOOKUP(B2,SAP!G$1:H$236,2,FALSE()) -> Silicon sealant glue nail free
H3: =VLOOKUP(B3,SAP!G$1:H$236,2,FALSE()) -> Silicon sealant glue nail free
H4: =VLOOKUP(B4,SAP!G$1:H$236,2,FALSE()) -> Silicon sealant glue nail free
H5: =VLOOKUP(B5,SAP!G$1:H$236,2,FALSE()) -> PVC board 11 mm (8 X 4) | I5: Basic | J5: 30000
H6: =VLOOKUP(B6,SAP!G$1:H$236,2,FALSE()) -> Wall Bidding WPC 02 | I6: Light | J6: 11500
H7: =VLOOKUP(B7,SAP!G$1:H$236,2,FALSE()) -> Aluminium channels reactangular 1 mm
H8: =VLOOKUP(B8,SAP!G$1:H$236,2,FALSE()) -> Silicon sealant glue nail free
H9: =VLOOKUP(B9,SAP!G$1:H$236,2,FALSE()) -> 240 LED strip light 5m
H10: =VLOOKUP(B10,SAP!G$1:H$236,2,FALSE()) -> 10 AMP 24V LED Power Adapter
H11: =VLOOKUP(B11,SAP!G$1:H$236,2,FALSE()) -> Brown Wooden Louver PN 02307 CPC Panel
H12: =VLOOKUP(B12,SAP!G$1:H$236,2,FALSE()) -> Silicon sealant glue nail free
H13: =VLOOKUP(B13,SAP!G$1:H$236,2,FALSE()) -> Silicon sealant glue nail free
H14: =VLOOKUP(B14,SAP!G$1:H$236,2,FALSE()) -> PVC board 11 mm (8 X 4) | I14: Basic | J14: 18000
H15: =VLOOKUP(B15,SAP!G$1:H$236,2,FALSE()) -> Wall Bidding WPC 02 | I15: Light | J15: 14000
H16: =VLOOKUP(B16,SAP!G$1:H$236,2,FALSE()) -> Aluminium channels reactangular 1 mm | I16: Storage | J16: 3000
H17: =VLOOKUP(B17,SAP!G$1:H$236,2,FALSE()) -> Silicon sealant glue nail free
H18: =VLOOKUP(B18,SAP!G$1:H$236,2,FALSE()) -> 240 LED strip light 5m
H19: =VLOOKUP(B19,SAP!G$1:H$236,2,FALSE()) -> 16X16 Alumnium Angular Profile 3m
H20: =VLOOKUP(B20,SAP!G$1:H$236,2,FALSE()) -> 10 AMP 24V LED Power Adapter
H21: =VLOOKUP(B21,SAP!G$1:H$236,2,FALSE()) -> Charcoal PS-Cream-Matte-PN 05667
H22: =VLOOKUP(B22,SAP!G$1:H$236,2,FALSE()) -> Wall storage 300mm shelf light woodgrain
H23: =VLOOKUP(B23,SAP!G$1:H$236,2,FALSE()) -> Rangular box wo backpanel lightwoodgrain
H24: =VLOOKUP(B24,SAP!G$1:H$236,2,FALSE()) -> Silicon sealant glue nail free
H25: =VLOOKUP(B25,SAP!G$1:H$236,2,FALSE()) -> Charcoal PS-Walnut-Wood Grain-PN 02347
H26: =VLOOKUP(B26,SAP!G$1:H$236,2,FALSE()) -> Silicon sealant glue nail free
H27: =VLOOKUP(B27,SAP!G$1:H$236,2,FALSE()) -> Silicon sealant glue nail free
H28: =VLOOKUP(B28,SAP!G$1:H$236,2,FALSE()) -> PVC board 11 mm (8 X 4) | I28: Basic | J28: 22500
H29: =VLOOKUP(B29,SAP!G$1:H$236,2,FALSE()) -> Wall Bidding WPC 02 | I29: Storage | J29: 5000
H30: =VLOOKUP(B30,SAP!G$1:H$236,2,FALSE()) -> Aluminium channels reactangular 1 mm | I30: Light | J30: 10500
H31: =VLOOKUP(B31,SAP!G$1:H$236,2,FALSE()) -> Silicon sealant glue nail free
H32: =VLOOKUP(B32,SAP!G$1:H$236,2,FALSE()) -> 240 LED strip light 5m
H33: =VLOOKUP(B33,SAP!G$1:H$236,2,FALSE()) -> 16X16 Alumnium Angular Profile 3m
H34: =VLOOKUP(B34,SAP!G$1:H$236,2,FALSE()) -> 10 AMP 24V LED Power Adapter
H35: =VLOOKUP(B35,SAP!G$1:H$236,2,FALSE()) -> Brown Wooden Louver PN 02308 - CPC Panel
H36: =VLOOKUP(B36,SAP!G$1:H$236,2,FALSE()) -> Wall storage 300mm shelf light woodgrain
H37: =VLOOKUP(B37,SAP!G$1:H$236,2,FALSE()) -> Square box wo backpanel mid wood grain
H38: =VLOOKUP(B38,SAP!G$1:H$236,2,FALSE()) -> Wall Trim 6 mm SS: Black Glossy
H39: =VLOOKUP(B39,SAP!G$1:H$236,2,FALSE()) -> PVC board 11 mm (8 X 4) | I39: Basic | J39: 22500
H40: =VLOOKUP(B40,SAP!G$1:H$236,2,FALSE()) -> Wall Bidding WPC 02 | I40: Storage | J40: 5000
H41: =VLOOKUP(B41,SAP!G$1:H$236,2,FALSE()) -> Aluminium channels reactangular 1 mm | I41: Light | J41: 9500
H42: =VLOOKUP(B42,SAP!G$1:H$236,2,FALSE()) -> Silicon sealant glue nail free
H43: =VLOOKUP(B43,SAP!G$1:H$236,2,FALSE()) -> 240 LED strip light 5m
H44: =VLOOKUP(B44,SAP!G$1:H$236,2,FALSE()) -> 16X16 Alumnium Angular Profile 3m
H45: =VLOOKUP(B45,SAP!G$1:H$236,2,FALSE()) -> 10 AMP 24V LED Power Adapter
H46: =VLOOKUP(B46,SAP!G$1:H$236,2,FALSE()) -> Beige Fabric Louver PN 02327 CPC Panel
H47: =VLOOKUP(B47,SAP!G$1:H$236,2,FALSE()) -> Wall storage 300mm shelf light woodgrain
H48: =VLOOKUP(B48,SAP!G$1:H$236,2,FALSE()) -> Square box wo backpanel mid wood grain
H49: =VLOOKUP(B49,SAP!G$1:H$236,2,FALSE()) -> Wall Trim 6 mm SS: Black Glossy
H50: =VLOOKUP(B50,SAP!G$1:H$236,2,FALSE()) -> Silicon sealant glue nail free
H51: =VLOOKUP(B51,SAP!G$1:H$236,2,FALSE()) -> Silicon sealant glue nail free
H52: =VLOOKUP(B52,SAP!G$1:H$236,2,FALSE()) -> Silicon sealant glue nail free
H53: =VLOOKUP(B53,SAP!G$1:H$236,2,FALSE()) -> Silicon sealant glue nail free
... H74: =VLOOKUP(B74,SAP!G$1:H$236,2,FALSE()) -> Silicon sealant glue nail free
H75: =VLOOKUP(B75,SAP!G$1:H$236,2,FALSE()) -> PVC board 11 mm (8 X 4) | I75: BR-3-1
H76: =VLOOKUP(B76,SAP!G$1:H$236,2,FALSE()) -> Wall Bidding WPC 08 | I76: Basic | J76: 12500
H77: =VLOOKUP(B77,SAP!G$1:H$236,2,FALSE()) -> Aluminium channels reactangular 1 mm | I77: Light | J77: 8000
H78: =VLOOKUP(B78,SAP!G$1:H$236,2,FALSE()) -> Silicon sealant glue nail free
H79: =VLOOKUP(B79,SAP!G$1:H$236,2,FALSE()) -> 240 LED strip light 5m
H80: =VLOOKUP(B80,SAP!G$1:H$236,2,FALSE()) -> 16X16 Alumnium Angular Profile 3m
H81: =VLOOKUP(B81,SAP!G$1:H$236,2,FALSE()) -> 10 AMP 24V LED Power Adapter
H82: =VLOOKUP(B82,SAP!G$1:H$236,2,FALSE()) -> Charcoal PS-Cream-Matte-PN 06167
H83: =VLOOKUP(B83,SAP!G$1:H$236,2,FALSE()) -> PVC board 11 mm (8 X 4) | I83: BR-3-2
H84: =VLOOKUP(B84,SAP!G$1:H$236,2,FALSE()) -> Wall Bidding WPC 01 | I84: Basic | J84: 10000
H85: =VLOOKUP(B85,SAP!G$1:H$236,2,FALSE()) -> Aluminium channels reactangular 1 mm | I85: Light | J85: 8000
H86: =VLOOKUP(B86,SAP!G$1:H$236,2,FALSE()) -> Silicon sealant glue nail free
H87: =VLOOKUP(B87,SAP!G$1:H$236,2,FALSE()) -> 240 LED strip light 5m
H88: =VLOOKUP(B88,SAP!G$1:H$236,2,FALSE()) -> 16X16 Alumnium Angular Profile 3m
H89: =VLOOKUP(B89,SAP!G$1:H$236,2,FALSE()) -> 10 AMP 24V LED Power Adapter
H90: =VLOOKUP(B90,SAP!G$1:H$236,2,FALSE()) -> Charcoal PS-Dark-Wood Grain-PN 02746
H91: =VLOOKUP(B91,SAP!G$1:H$236,2,FALSE()) -> Silicon sealant glue nail free
H92: =VLOOKUP(B92,SAP!G$1:H$236,2,FALSE()) -> Silicon sealant glue nail free
H93: =VLOOKUP(B93,SAP!G$1:H$236,2,FALSE()) -> Brown Wooden Louver PN 02307 CPC Panel
H94: =VLOOKUP(B94,SAP!G$1:H$236,2,FALSE()) -> Silicon sealant glue nail free
H95: =VLOOKUP(B95,SAP!G$1:H$236,2,FALSE()) -> Brown Wooden Louver PN 02313 CPC Panel
H96: =VLOOKUP(B96,SAP!G$1:H$236,2,FALSE()) -> Silicon sealant glue nail free
H97: =VLOOKUP(B97,SAP!G$1:H$236,2,FALSE()) -> Silicon sealant glue nail free
H98: =VLOOKUP(B98,SAP!G$1:H$236,2,FALSE()) -> PVC board 11 mm (8 X 4) | I98: BR-4-1
H99: =VLOOKUP(B99,SAP!G$1:H$236,2,FALSE()) -> Wall Bidding WPC 09 | I99: Basic | J99: 15000
H100: =VLOOKUP(B100,SAP!G$1:H$236,2,FALSE()) -> Aluminium channels reactangular 1 mm | I100: Storage | J100: 3000
H101: =VLOOKUP(B101,SAP!G$1:H$236,2,FALSE()) -> Silicon sealant glue nail free | I101: Light | J101: 10500
H102: =VLOOKUP(B102,SAP!G$1:H$236,2,FALSE()) -> 240 LED strip light 5m
H103: =VLOOKUP(B103,SAP!G$1:H$236,2,FALSE()) -> 16X16 Alumnium Angular Profile 3m
H104: =VLOOKUP(B104,SAP!G$1:H$236,2,FALSE()) -> 10 AMP 24V LED Power Adapter
H105: =VLOOKUP(B105,SAP!G$1:H$236,2,FALSE()) -> Beige Fabric Decor PN 02326 CPC Panel
H106: =VLOOKUP(B106,SAP!G$1:H$236,2,FALSE()) -> Charcoal PS-Walnut-Wood Grain-PN 03223
H107: =VLOOKUP(B107,SAP!G$1:H$236,2,FALSE()) -> Rangular box wo backpanel lightwoodgrain
H108: =VLOOKUP(B108,SAP!G$1:H$236,2,FALSE()) -> Square box wo backpanel light wood grain | I108: BR-4-2
H109: =VLOOKUP(B109,SAP!G$1:H$236,2,FALSE()) -> Silicon sealant glue nail free | I109: Basic | J109: 20000
H110: =VLOOKUP(B110,SAP!G$1:H$236,2,FALSE()) -> Brown Wooden Louver PN 02308 - CPC Panel | I110: Light | J110: 10500
H111: =VLOOKUP(B111,SAP!G$1:H$236,2,FALSE()) -> Brown Wooden Louver PN 02313 B CPC Panel | I111: Storage | J111: 3000
H112: =VLOOKUP(B112,SAP!G$1:H$236,2,FALSE()) -> Wall storage 450mm shelf light woodgrain
H113: =VLOOKUP(B113,SAP!G$1:H$236,2,FALSE()) -> Square box wo backpanel light wood grain
H114: =VLOOKUP(B114,SAP!G$1:H$236,2,FALSE()) -> Wall Bidding PVC 05
H115: =VLOOKUP(B115,SAP!G$1:H$236,2,FALSE()) -> Silicon sealant glue nail free
H116: =VLOOKUP(B116,SAP!G$1:H$236,2,FALSE()) -> Grey Marble Louver PN 02325 - CPC Panel
H117: =VLOOKUP(B117,SAP!G$1:H$236,2,FALSE()) -> Charcoal PS-Dark-Wood Grain-PN 02746
H118: =VLOOKUP(B118,SAP!G$1:H$236,2,FALSE()) -> Silicon sealant glue nail free
H119: =VLOOKUP(B119,SAP!G$1:H$236,2,FALSE()) -> PVC board 11 mm (8 X 4)
H120: =VLOOKUP(B120,SAP!G$1:H$236,2,FALSE()) -> Aluminium channels reactangular 1 mm
...

Sheet Pivot Table 2

Sheet SAP
A1: Revenue Segment | B1: Product Type/ Generic Name | C1: Country of Origin | D1: Parent SKU Code | E1: Parent Product Name | F1: Characters Length (40 Characters) | G1: Child SKU Code | H1: Child Product Name | I1: Characters Length (40 Characters) | J1: UOM | K1: Packing Dimensions (MM) (LXWXH) | L1: Product Dimensions (MM) (LXWXH) | M1: Gross Weight (KG) | N1: Net Weight (KG) | O1: HSN Code | P1: Conversion Factor | Q1: Plant | R1: MAP (Child) | S1: MRP | T1: SAP Code Parent | U1: SAP Code child | V1: Product Name with size
A2: HIF | B2: Wall Panel | C2: India | G2: WHSWPLPS001 | H2: PVC-Wooden/Multi-clr-Wood Grain-PN 06186 | I2: =len(H2) -> 40 | J2: N | K2: 3048 x 254 x 6 | L2: =K2 -> 3048 x 254 x 6 | M2: 2.5 | N2: 2.5 | O2: 39259090 | P2: 1 | Q2: KA04,MTN9 | R2: 1043.322 | S2: =2500 -> 2500 | V2: PVC-Wooden/Multi-clr-Wood Grain-PN 06186 || 10 ft x 10 inch
A3: HIF | B3: Wall Panel | C3: India | G3: WHSWPLPS002 | H3: PVC-Walnut/Dark Wood-Wood Grain-PN 00402 | I3: =len(H3) -> 40 | J3: N | K3: 3048 x 254 x 6 | L3: =K3 -> 3048 x 254 x 6 | M3: 2.5 | N3: 2.5 | O3: 39259090 | P3: 1 | Q3: KA04,MTN9 | R3: 335.60169 | S3: =700 -> 700 | V3: PVC-Walnut/Dark Wood-Wood Grain-PN 00402 || 10 ft x 10 inch
A4: HIF | B4: Wall Panel | C4: India | G4: WHSWPLWS003 | H4: WPC-Natural Wood-Wood Grain-PN 00273 | I4: =len(H4) -> 36 | J4: N | K4: 2895.6 x 127 x 12 | L4: =K4 -> 2895.6 x 127 x 12 | M4: 4 | N4: 4 | O4: 39259090 | P4: 1 | Q4: KA04,MTN9 | R4: 648.80508 | S4: =1500 -> 1500 | V4: WPC-Natural Wood-Wood Grain-PN 00273 || 9.5 ft x 5 inch
A5: HIF | B5: Wall Panel | C5: India | G5: WHSWPLWS004 | H5: WPC-Charcoal Grey-Matte-PN 02898 | I5: =len(H5) -> 32 | J5: N | K5: 2895.6 x 127 x 12 | L5: =K5 -> 2895.6 x 127 x 12 | M5: 4 | N5: 4 | O5: 39259090 | P5: 1 | Q5: KA04,MTN9 | R5: 648.80508 | S5: =1500 -> 1500 | V5: WPC-Charcoal Grey-Matte-PN 02898 || 9.5 ft x 5 inch
A6: HIF | B6: Wall Panel | C6: India | G6: WHSWPLWS005 | H6: WPC-Black-Matte-PN 02912 | I6: =len(H6) -> 24 | J6: N | K6: 2895.6 x 127 x 12 | L6: =K6 -> 2895.6 x 127 x 12 | M6: 4 | N6: 4 | O6: 39259090 | P6: 1 | Q6: KA04,MTN9 | R6: 648.80508 | S6: =1500 -> 1500 | V6: WPC-Black-Matte-PN 02912 || 9.5 ft x 5 inch
A7: HIF | B7: Wall Panel | C7: India | G7: WHSWPLCS006 | H7: Charcoal PS-Beige-Matte-PN 03851 | I7: =len(H7) -> 32 | J7: N | K7: 2895.6 x 152.4 x 10 | L7: =K7 -> 2895.6 x 152.4 x 10 | M7: 1.5 | N7: 1.5 | O7: 39269099 | P7: 1 | Q7: KA04,MTN9 | R7: 648.80508 | S7: 1500 | V7: Charcoal (PS)-Beige-Matte-PN 03851 || 9.5 ft x 6 inch
A8: HIF | B8: Wall Panel | C8: India | G8: WHSWPLCS007 | H8: Charcoal PS-Grey-Matte-PN 03856 | I8: =len(H8) -> 31 | J8: N | K8: 2895.6 x 152.4 x 10 | L8: =K8 -> 2895.6 x 152.4 x 10 | M8: 1.5 | N8: 1.5 | O8: 39269099 | P8: 1 | Q8: KA04,MTN9 | R8: 745.01695 | S8: =1500 -> 1500 | V8: Charcoal (PS)-Grey-Matte-PN 03856 || 9.5 ft x 6 inch
A9: HIF | B9: Wall Panel | C9: India | G9: WHSWPLCS008 | H9: Charcoal PS-Walnut-Wood Grain-PN 03864 | I9: =len(H9) -> 38 | J9: N | K9: 2895.6 x 152.4 x 10 | L9: =K9 -> 2895.6 x 152.4 x 10 | M9: 1.5 | N9: 1.5 | O9: 39269099 | P9: 1 | Q9: KA04,MTN9 | R9: 819.59322 | S9: =2000 -> 2000 | V9: Charcoal (PS)-Walnut-Wood Grain-PN 03864 || 9.5 ft x 6 inch
A10: HIF | B10: Wall Panel | C10: India | G10: WHSWPLCS009 | H10: Charcoal PS-Pine-Wood Grain-PN 03865 | I10: =len(H10) -> 36 | J10: N | K10: 2895.6 x 152.4 x 10 | L10: =K10 -> 2895.6 x 152.4 x 10 | M10: 1.5 | N10: 1.5 | O10: 39269099 | P10: 1 | Q10: KA04,MTN9 | R10: 819.59322 | S10: =2000 -> 2000 | V10: Charcoal (PS)-Pine-Wood Grain-PN 03865 || 9.5 ft x 6 inch
A11: HIF | B11: Wall Panel | C11: India | G11: WHSWPLCS010 | H11: Charcoal PS-Teak-Wood Grain-PN 03044 | I11: =len(H11) -> 36 | J11: N | K11: 2438.4 x 127 x 12 | L11: =K11 -> 2438.4 x 127 x 12 | M11: 1.5 | N11: 1.5 | O11: 39269099 | P11: 1 | Q11: KA04,MTN9 | R11: 670.44068 | S11: 1500 | V11: Charcoal (PS)-Teak-Wood Grain-PN 03044 || 8 ft x 5 inch
A12: HIF | B12: Wall Panel | C12: India | G12: WHSWPLCS011 | H12: Charcoal PS-Grey-Matte-PN 00901 | I12: =len(H12) -> 31 | J12: N | K12: 2438.4 x 127 x 12 | L12: =K12 -> 2438.4 x 127 x 12 | M12: 1.5 | N12: 1.5 | O12: 392690 | P12: 1 | Q12: KA04,MTN9 | R12: 819.59322 | S12: =2000 -> 2000 | V12: Charcoal (PS)-Grey-Matte-PN 00901 || 8 ft x 5 inch
A13: HIF | B13: Wall Panel | C13: India | G13: WHSWPLCS012 | H13: Charcoal PS-Walnut-Wood Grain-PN 03043 | I13: =len(H13) -> 38 | J13: N | K13: 2438.4 x 127 x 12 | L13: =K13 -> 2438.4 x 127 x 12 | M13: 1.5 | N13: 1.5 | O13: 39269099 | P13: 1 | Q13: KA04,MTN9 | R13: 670.44068 | S13: 1500 | V13: Charcoal (PS)-Walnut-Wood Grain-PN 03043 || 8 ft x 5 inch
A14: HIF | B14: Wall Panel | C14: India | G14: WHSWPLCS013 | H14: Charcoal PS-Brown-Wood Grain-PN 05777 | I14: =len(H14) -> 37 | J14: N | K14: 2438.4 x 127 x 11 | L14: =K14 -> 2438.4 x 127 x 11 | M14: 1.5 | N14: 1.5 | O14: 39269099 | P14: 1 | Q14: KA04,MTN9 | R14: 1192.4746 | S14: =2500 -> 2500 | V14: Charcoal (PS)-Brown-Wood Grain-PN 05777 || 8 ft x 5 inch
A15: HIF | B15: Wall Panel | C15: India | G15: WHSWPLCS014 | H15: Charcoal PS-Teak-Wood Grain-PN 06161 | I15: =len(H15) -> 36 | J15: N | K15: 2438.4 x 127 x 11 | L15: =K15 -> 2438.4 x 127 x 11 | M15: 1.5 | N15: 1.5 | O15: 39269099 | P15: 1 | Q15: KA04,MTN9 | R15: 1084.0678 | S15: 2500 | V15: Charcoal (PS)-Teak-Wood Grain-PN 06161 || 8 ft x 5 inch
A16: HIF | B16: Wall Panel | C16: India | G16: WHSWPLCS015 | H16: Charcoal PS-Pine-Wood Grain-PN 06158 | I16: =len(H16) -> 36 | J16: N | K16: 2438.4 x 127 x 11 | L16: =K16 -> 2438.4 x 127 x 11 | M16: 1.5 | N16: 1.5 | O16: 39269099 | P16: 1 | Q16: KA04,MTN9 | R16: 1192.4746 | S16: =2500 -> 2500 | V16: Charcoal (PS)-Pine-Wood Grain-PN 06158 || 8 ft x 5 inch
A17: HIF | B17: Wall Panel | C17: India | G17: WHSWPLCS016 | H17: Charcoal PS-Black-Matte-PN 06159 | I17: =len(H17) -> 32 | J17: N | K17: 2438.4 x 127 x 11 | L17: =K17 -> 2438.4 x 127 x 11 | M17: 1.5 | N17: 1.5 | O17: 39269099 | P17: 1 | Q17: KA04,MTN9 | R17: 1084.0678 | S17: 2500 | V17: Charcoal (PS)-Black-Matte-PN 06159 || 8 ft x 5 inch
A18: HIF | B18: Wall Panel | C18: India | G18: WHSWPLCS017 | H18: Charcoal PS-Cream-Matte-PN 06167 | I18: =len(H18) -> 32 | J18: N | K18: 2438.4 x 127 x 11 | L18: =K18 -> 2438.4 x 127 x 11 | M18: 1.5 | N18: 1.5 | O18: 39269099 | P18: 1 | Q18: KA04,MTN9 | R18: 1084.0678 | S18: 2500 | V18: Charcoal (PS)-Cream-Matte-PN 06167 || 8 ft x 5 inch
A19: HIF | B19: Wall Panel | C19: India | G19: WHSWPLCS018 | H19: Charcoal PS-Ivory-Matte-PN 06156 | I19: =len(H19) -> 32 | J19: N | K19: 2438.4 x 127 x 11 | L19: =K19 -> 2438.4 x 127 x 11 | M19: 1.5 | N19: 1.5 | O19: 39269099 | P19: 1 | Q19: KA04,MTN9 | R19: 1084.0678 | S19: 2500 | V19: Charcoal (PS)-Ivory-Matte-PN 06156 || 8 ft x 5 inch
A20: HIF | B20: Wall Panel | C20: India | G20: WHSWPLCS019 | H20: Charcoal PS-Dark-Wood Grain-PN 03208 | I20: =len(H20) -> 36 | J20: N | K20: 2438.4 x 127 x 11 | L20: =K20 -> 2438.4 x 127 x 11 | M20: 1.5 | N20: 1.5 | O20: 39269099 | P20: 1 | Q20: KA04,MTN9 | R20: 595.86441 | S20: 1500 | V20: Charcoal (PS)-Dark-Wood Grain-PN 03208 || 8 ft x 5 inch
A21: HIF | B21: Wall Panel | C21: India | G21: WHSWPLCS020 | H21: Charcoal PS-Pine-Wood Grain-PN 03221 | I21: =len(H21) -> 36 | J21: N | K21: 2438.4 x 127 x 11 | L21: =K21 -> 2438.4 x 127 x 11 | M21: 1.5 | N21: 1.5 | O21: 39269099 | P21: 1 | Q21: KA04,MTN9 | R21: 595.86441 | S21: 1500 | V21: Charcoal (PS)-Pine-Wood Grain-PN 03221 || 8 ft x 5 inch
A22: HIF | B22: Wall Panel | C22: India | G22: WHSWPLCS021 | H22: Charcoal PS-Walnut-Wood Grain-PN 03223 | I22: =len(H22) -> 38 | J22: N | K22: 2438.4 x 127 x 11 | L22: =K22 -> 2438.4 x 127 x 11 | M22: 1.5 | N22: 1.5 | O22: 39269099 | P22: 1 | Q22: KA04,MTN9 | R22: 595.86441 | S22: 1500 | V22: Charcoal (PS)-Walnut-Wood Grain-PN 03223 || 8 ft x 5 inch
A23: HIF | B23: Wall Panel | C23: India | G23: WHSWPLCS022 | H23: Charcoal PS-Teak-Wood Grain-PN 03222 | I23: =len(H23) -> 36 | J23: N | K23: 2438.4 x 127 x 11 | L23: =K23 -> 2438.4 x 127 x 11 | M23: 1.5 | N23: 1.5 | O23: 39269099 | P23: 1 | Q23: KA04,MTN9 | R23: 595.86441 | S23: 1500 | V23: Charcoal (PS)-Teak-Wood Grain-PN 03222 || 8 ft x 5 inch
A24: HIF | B24: Wall Panel | C24: India | G24: WHSWPLCS023 | H24: Charcoal PS-Grey-Matte-PN 03210 | I24: =len(H24) -> 31 | J24: N | K24: 2438.4 x 127 x 11 | L24: =K24 -> 2438.4 x 127 x 11 | M24: 1.5 | N24: 1.5 | O24: 39269099 | P24: 1 | Q24: KA04,MTN9 | R24: 595.86441 | S24: 1500 | V24: Charcoal (PS)-Grey-Matte-PN 03210 || 8 ft x 5 inch
A25: HIF | B25: Wall Panel | C25: India | G25: WHSWPLCS024 | H25: Charcoal PS-Oak-Wood Grain-PN 05610 | I25: =len(H25) -> 35 | J25: N | K25: 2438.4 x 127 x 11 | L25: =K25 -> 2438.4 x 127 x 11 | M25: 1.5 | N25: 1.5 | O25: 39269099 | P25: 1 | Q25: KA04,MTN9 | R25: 670.44068 | S25: 1500 | V25: Charcoal (PS)-Oak-Wood Grain-PN 05610 || 8 ft x 5 inch
A26: HIF | B26: Wall Panel | C26: India | G26: WHSWPLCS025 | H26: Charcoal PS-Dark Grey-Matte-PN 00545 | I26: =len(H26) -> 36 | J26: N | K26: 2438.4 x 127 x 11 | L26: =K26 -> 2438.4 x 127 x 11 | M26: 1.5 | N26: 1.5 | O26: 392690 | P26: 1 | Q26: KA04,MTN9 | R26: 819.59322 | S26: =2000 -> 2000 | V26: Charcoal (PS)-Dark Grey-Matte-PN 00545 || 8 ft x 5 inch
A27: HIF | B27: Wall Panel | C27: India | G27: WHSWPLCS026 | H27: Charcoal PS-Pine-Wood Grain-PN 05291 | I27: =len(H27) -> 36 | J27: N | K27: 2438.4 x 127 x 11 | L27: =K27 -> 2438.4 x 127 x 11 | M27: 1.5 | N27: 1.5 | O27: 39269099 | P27: 1 | Q27: KA04,MTN9 | R27: 595.86441 | S27: 1500 | V27: Charcoal (PS)-Pine-Wood Grain-PN 05291 || 8 ft x 5 inch
A28: HIF | B28: Wall Panel | C28: India | G28: WHSWPLCS027 | H28: Charcoal PS-Walnut-Wood Grain-PN 05289 | I28: =len(H28) -> 38 | J28: N | K28: 2438.4 x 127 x 11 | L28: =K28 -> 2438.4 x 127 x 11 | M28: 1.5 | N28: 1.5 | O28: 39269099 | P28: 1 | Q28: KA04,MTN9 | R28: 595.86441 | S28: 1500 | V28: Charcoal (PS)-Walnut-Wood Grain-PN 05289 || 8 ft x 5 inch
A29: HIF | B29: Wall Panel | C29: India | G29: WHSWPLCS028 | H29: Charcoal PS-Multi-Wood Grain-PN 06288 | I29: =len(H29) -> 37 | J29: N | K29: 2438.4 x 127 x 11 | L29: =K29 -> 2438.4 x 127 x 11 | M29: 1.5 | N29: 1.5 | O29: 39269099 | P29: 1 | Q29: KA04,MTN9 | R29: 745.01695 | S29: =1500 -> 1500 | V29: Charcoal (PS)-Multi-Wood Grain-PN 06288 || 8 ft x 5 inch
A30: HIF | B30: Wall Panel | C30: India | G30: WHSWPLCS029 | H30: Charcoal PS-White-Matte-PN 00155 | I30: =len(H30) -> 32 | J30: N | K30: 2438.4 x 127 x 11 | L30: =K30 -> 2438.4 x 127 x 11 | M30: 1.5 | N30: 1.5 | O30: 39269099 | P30: 1 | Q30: KA04,MTN9 | R30: 670.44068 | S30: 1500 | V30: Charcoal (PS)-White-Matte-PN 00155 || 8 ft x 5 inch
A31: HIF | B31: Wall Panel | C31: India | G31: WHSWPLCS030 | H31: Charcoal PS-Medium-Wood Grain-PN 05514 | I31: =len(H31) -> 38 | J31: N | K31: 2438.4 x 127 x 11 | L31: =K31 -> 2438.4 x 127 x 11 | M31: 1.5 | N31: 1.5 | O31: 39269099 | P31: 1 | Q31: KA04,MTN9 | R31: 595.86441 | S31: 1500 | V31: Charcoal (PS)-Medium-Wood Grain-PN 05514 || 8 ft x 5 inch
A32: HIF | B32: Wall Panel | C32: India | G32: WHSWPLCS031 | H32: Charcoal PS-Teak-Wood Grain-PN 00140 | I32: =len(H32) -> 36 | J32: N | K32: 2438.4 x 127 x 11 | L32: =K32 -> 2438.4 x 127 x 11 | M32: 1.5 | N32: 1.5 | O32: 39269099 | P32: 1 | Q32: KA04,MTN9 | R32: 677.28814 | S32: =1500 -> 1500 | V32: Charcoal (PS)-Teak-Wood Grain-PN 00140 || 8 ft x 5 inch
A33: HIF | B33: Wall Panel | C33: India | G33: WHSWPLCS032 | H33: Charcoal PS-Dark-Wood Grain-PN 05484 | I33: =len(H33) -> 36 | J33: N | K33: 2438.4 x 127 x 11 | L33: =K33 -> 2438.4 x 127 x 11 | M33: 1.5 | N33: 1.5 | O33: 39269099 | P33: 1 | Q33: KA04,MTN9 | R33: 595.86441 | S33: 1500 | V33: Charcoal (PS)-Dark-Wood Grain-PN 05484 || 8 ft x 5 inch
A34: HIF | B34: Wall Panel | C34: India | G34: WHSWPLCS033 | H34: Charcoal PS-Pine-Wood Grain-PN 00147 | I34: =len(H34) -> 36 | J34: N | K34: 2438.4 x 127 x 11 | L34: =K34 -> 2438.4 x 127 x 11 | M34: 1.5 | N34: 1.5 | O34: 39269099 | P34: 1 | Q34: KA04,MTN9 | R34: 670.44068 | S34: 1500 | V34: Charcoal (PS)-Pine-Wood Grain-PN 00147 || 8 ft x 5 inch
A35: HIF | B35: Wall Panel | C35: India | G35: WHSWPLCS034 | H35: Charcoal PS-Oak-Wood Grain-PN 05606 | I35: =len(H35) -> 35 | J35: N | K35: 2438.4 x 127 x 11 | L35: =K35 -> 2438.4 x 127 x 11 | M35: 1.5 | N35: 1.5 | O35: 39269099 | P35: 1 | Q35: KA04,MTN9 | R35: 670.44068 | S35: 1500 | V35: Charcoal (PS)-Oak-Wood Grain-PN 05606 || 8 ft x 5 inch
A36: HIF | B36: Wall Panel | C36: India | G36: WHSWPLCS035 | H36: Charcoal PS-Teak-Wood Grain-PN 02343 | I36: =len(H36) -> 36 | J36: N | K36: 2438.4 x 609.6 x 10 | L36: =K36 -> 2438.4 x 609.6 x 10 | M36: 10 | N36: 10 | O36: 39269099 | P36: 1 | Q36: KA04,MTN9 | R36: 1117.8983 | S36: 2500 | V36: Charcoal (PS)-Teak-Wood Grain-PN 02343 || 8 ft x 2 ft
A37: HIF | B37: Wall Panel | C37: India | G37: WHSWPLCS036 | H37: Charcoal PS-Walnut-Wood Grain-PN 02347 | I37: =len(H37) -> 38 | J37: N | K37: 2438.4 x 609.6 x 10 | L37: =K37 -> 2438.4 x 609.6 x 10 | M37: 10 | N37: 10 | O37: 39269099 | P37: 1 | Q37: KA04,MTN9 | R37: 1117.8983 | S37: 2500 | V37: Charcoal (PS)-Walnut-Wood Grain-PN 02347 || 8 ft x 2 ft
A38: HIF | B38: Wall Panel | C38: India | G38: WHSWPLCS037 | H38: Charcoal PS-Grey-Matte-PN 02341 | I38: =len(H38) -> 31 | J38: N | K38: 2438.4 x 609.6 x 10 | L38: =K38 -> 2438.4 x 609.6 x 10 | M38: 10 | N38: 10 | O38: 39269099 | P38: 1 | Q38: KA04,MTN9 | R38: 1016.2712 | S38: 2500 | V38: Charcoal (PS)-Grey-Matte-PN 02341 || 8 ft x 2 ft
A39: HIF | B39: Wall Panel | C39: India | G39: WHSWPLCS038 | H39: Charcoal PS-Beige-Matte-PN 02345 B | I39: =len(H39) -> 34 | J39: N | K39: 2438.4 x 609.6 x 10 | L39: =K39 -> 2438.4 x 609.6 x 10 | M39: 10 | N39: 10 | O39: 39269099 | P39: 1 | Q39: KA04,MTN9 | R39: 670.44068 | S39: 1500 | V39: Charcoal (PS)-Beige-Matte-PN 02345 B || 8 ft x 2 ft
A40: HIF | B40: Wall Panel | C40: India | G40: WHSWPLCS039 | H40: Charcoal PS-Black-Matte-PN 02346 | I40: =len(H40) -> 32 | J40: N | K40: 2438.4 x 609.6 x 10 | L40: =K40 -> 2438.4 x 609.6 x 10 | M40: 10 | N40: 10 | O40: 39269099 | P40: 1 | Q40: KA04,MTN9 | R40: 670.44068 | S40: 1500 | V40: Charcoal (PS)-Black-Matte-PN 02346 || 8 ft x 2 ft
A41: HIF | B41: Wall Panel | C41: India | G41: WHSWPLCS040 | H41: Charcoal PS-Brown-Wood Grain-PN 05926 | I41: =len(H41) -> 37 | J41: N | K41: 2895.6 x 121.92 x 12 | L41: =K41 -> 2895.6 x 121.92 x 12 | M41: 1.5 | N41: 1.5 | O41: 39269099 | P41: 1 | Q41: KA04,MTN9 | R41: 670.44068 | S41: 1500 | V41: Charcoal (PS)-Brown-Wood Grain-PN 05926 || 9.5 ft x 4.8 inch
A42: HIF | B42: Wall Panel | C42: India | G42: WHSWPLCS041 | H42: Charcoal PS-Walnut-Wood Grain-PN 05925 | I42: =len(H42) -> 38 | J42: N | K42: 2895.6 x 121.92 x 12 | L42: =K42 -> 2895.6 x 121.92 x 12 | M42: 1.5 | N42: 1.5 | O42: 39269099 | P42: 1 | Q42: KA04,MTN9 | R42: 670.44068 | S42: 1500 | V42: Charcoal (PS)-Walnut-Wood Grain-PN 05925 || 9.5 ft x 4.8 inch
A43: HIF | B43: Wall Panel | C43: India | G43: WHSWPLCS042 | H43: Charcoal PS-Dark-Wood Grain-PN 02746 | I43: =len(H43) -> 36 | J43: N | K43: 2895.6 x 121.92 x 12 | L43: =K43 -> 2895.6 x 121.92 x 12 | M43: 1.5 | N43: 1.5 | O43: 39259090 | P43: 1 | Q43: KA04,MTN9 | R43: 819.59322 | S43: =2000 -> 2000 | V43: Charcoal (PS)-Dark-Wood Grain-PN 02746 || 9.5 ft x 4.8 inch
A44: HIF | B44: Wall Panel | C44: India | G44: WHSWPLCS043 | H44: Charcoal PS-Ivory-Matte-PN 02750 | I44: =len(H44) -> 32 | J44: N | K44: 2895.6 x 121.92 x 12 | L44: =K44 -> 2895.6 x 121.92 x 12 | M44: 1.5 | N44: 1.5 | O44: 39259090 | P44: 1 | Q44: KA04,MTN9 | R44: 745.08475 | S44: =1500 -> 1500 | V44: Charcoal (PS)-Ivory-Matte-PN 02750 || 9.5 ft x 4.8 inch
A45: HIF | B45: Wall Panel | C45: India | G45: WHSWPLCS044 | H45: Charcoal PS-Cream-Plain-clr-PN 00521 | I45: =len(H45) -> 36 | J45: N | K45: 2895.6 x 121.92 x 12 | L45: =K45 -> 2895.6 x 121.92 x 12 | M45: 1.5 | N45: 1.5 | O45: 392111 | P45: 1 | Q45: KA04,MTN9 | R45: 968.74576 | S45: =2000 -> 2000 | V45: Charcoal (PS)-Cream-Plain-clr-PN 00521 || 9.5 ft x 4.8 inch
A46: HIF | B46: Wall Panel | C46: India | G46: WHSWPLCS045 | H46: Charcoal PS-Grey-Matte-PN 05494 | I46: =len(H46) -> 31 | J46: N | K46: 2895.6 x 121.92 x 12 | L46: =K46 -> 2895.6 x 121.92 x 12 | M46: 1.5 | N46: 1.5 | O46: 39269099 | P46: 1 | Q46: KA04,MTN9 | R46: 595.86441 | S46: 1500 | V46: Charcoal (PS)-Grey-Matte-PN 05494 || 9.5 ft x 4.8 inch
A47: HIF | B47: Wall Panel | C47: India | G47: WHSWPLCS046 | H47: Charcoal PS-Pine-Wood Grain-PN 00486 | I47: =len(H47) -> 36 | J47: N | K47: 2895.6 x 121.92 x 12 | L47: =K47 -> 2895.6 x 121.92 x 12 | M47: 1.5 | N47: 1.5 | O47: 39269099 | P47: 1 | Q47: KA04,MTN9 | R47: 1043.322 | S47: 2500 | V47: Charcoal (PS)-Pine-Wood Grain-PN 00486 || 9.5 ft x 4.8 inch
A48: HIF | B48: Wall Panel | C48: India | G48: WHSWPLCS047 | H48: Charcoal PS-Walnut-Wood Grain-PN 04567 | I48: =len(H48) -> 38 | J48: N | K48: 2438.4 x 127 x 12 | L48: =K48 -> 2438.4 x 127 x 12 | M48: 1.5 | N48: 1.5 | O48: 39269099 | P48: 1 | Q48: KA04,MTN9 | R48: 1043.322 | S48: 2500 | V48: Charcoal (PS)-Walnut-Wood Grain-PN 04567 || 8 ft x 5 inch
A49: HIF | B49: Wall Panel | C49: India | G49: WHSWPLCS048 | H49: Charcoal PS-Grey-Matte-PN 05599 | I49: =len(H49) -> 31 | J49: N | K49: 2438.4 x 127 x 12 | L49: =K49 -> 2438.4 x 127 x 12 | M49: 1.5 | N49: 1.5 | O49: 39269099 | P49: 1 | Q49: KA04,MTN9 | R49: 677.28814 | S49: =1500 -> 1500 | V49: Charcoal (PS)-Grey-Matte-PN 05599 || 8 ft x 5 inch
A50: HIF | B50: Wall Panel | C50: India | G50: WHSWPLCS049 | H50: Charcoal PS-Brown-Wood Grain-PN 05698 | I50: =len(H50) -> 37 | J50: N | K50: 2438.4 x 127 x 12 | L50: =K50 -> 2438.4 x 127 x 12 | M50: 1.5 | N50: 1.5 | O50: 39269099 | P50: 1 | Q50: KA04,MTN9 | R50: 595.86441 | S50: 1500 | V50: Charcoal (PS)-Brown-Wood Grain-PN 05698 || 8 ft x 5 inch
A51: HIF | B51: Wall Panel | C51: India | G51: WHSWPLCS050 | H51: Charcoal PS-Teak-Wood Grain-PN 04616 | I51: =len(H51) -> 36 | J51: N | K51: 2438.4 x 127 x 11 | L51: =K51 -> 2438.4 x 127 x 11 | M51: 1.5 | N51: 1.5 | O51: 39269099 | P51: 1 | Q51: KA04,MTN9 | R51: 595.86441 | S51: 1500 | V51: Charcoal (PS)-Teak-Wood Grain-PN 04616 || 8 ft x 5 inch
A52: HIF | B52: Wall Panel | C52: India | G52: WHSWPLCS051 | H52: Charcoal PS-Walnut-Wood Grain-PN 00149 | I52: =len(H52) -> 38 | J52: N | K52: 2438.4 x 127 x 11 | L52: =K52 -> 2438.4 x 127 x 11 | M52: 1.5 | N52: 1.5 | O52: 39269099 | P52: 1 | Q52: KA04,MTN9 | R52: 670.44068 | S52: 1500 | V52: Charcoal (PS)-Walnut-Wood Grain-PN 00149 || 8 ft x 5 inch
A53: HIF | B53: Wall Panel | C53: India | G53: WHSWPLCS052 | H53: Charcoal PS-Cream-Matte-PN 00137 | I53: =len(H53) -> 32 | J53: N | K53: 2438.4 x 127 x 11 | L53: =K53 -> 2438.4 x 127 x 11 | M53: 1.5 | N53: 1.5 | O53: 39269099 | P53: 1 | Q53: KA04,MTN9 | R53: 670.44068 | S53: 1500 | V53: Charcoal (PS)-Cream-Matte-PN 00137 || 8 ft x 5 inch
A54: HIF | B54: Wall Panel | C54: India | G54: WHSWPLCS053 | H54: Charcoal PS-Brown-Wood Grain-PN 04590 | I54: =len(H54) -> 37 | J54: N | K54: 2438.4 x 127 x 11 | L54: =K54 -> 2438.4 x 127 x 11 | M54: 1.5 | N54: 1.5 | O54: 39269099 | P54: 1 | Q54: KA04,MTN9 | R54: 948.47458 | S54: =2000 -> 2000 | V54: Charcoal (PS)-Brown-Wood Grain-PN 04590 || 8 ft x 5 inch
A55: HIF | B55: Wall Panel | C55: India | G55: WHSWPLCS054 | H55: Charcoal PS-Oak-Wood Grain-PN 04574 | I55: =len(H55) -> 35 | J55: N | K55: 2438.4 x 127 x 11 | L55: =K55 -> 2438.4 x 127 x 11 | M55: 1.5 | N55: 1.5 | O55: 39269099 | P55: 1 | Q55: KA04,MTN9 | R55: 1043.322 | S55: 2500 | V55: Charcoal (PS)-Oak-Wood Grain-PN 04574 || 8 ft x 5 inch
A56: HIF | B56: Wall Panel | C56: India | G56: WHSWPLCS055 | H56: Charcoal PS-Medium-Wood Grain-PN 05656 | I56: =len(H56) -> 38 | J56: N | K56: 2438.4 x 127 x 11 | L56: =K56 -> 2438.4 x 127 x 11 | M56: 1.5 | N56: 1.5 | O56: 392111 | P56: 1 | Q56: KA04,MTN9 | R56: 968.74576 | S56: =2000 -> 2000 | V56: Charcoal (PS)-Medium-Wood Grain-PN 05656 || 8 ft x 5 inch
A57: HIF | B57: Wall Panel | C57: India | G57: WHSWPLCS056 | H57: Charcoal PS-Walnut-Wood Grain-PN 05852 | I57: =len(H57) -> 38 | J57: N | K57: 2438.4 x 127 x 11 | L57: =K57 -> 2438.4 x 127 x 11 | M57: 1.5 | N57: 1.5 | O57: 392111 | P57: 1 | Q57: KA04,MTN9 | R57: 968.74576 | S57: =2000 -> 2000 | V57: Charcoal (PS)-Walnut-Wood Grain-PN 05852 || 8 ft x 5 inch
A58: HIF | B58: Wall Panel | C58: India | G58: WHSWPLCS057 | H58: Charcoal PS-Brown-Wood Grain-PN 03556 | I58: =len(H58) -> 37 | J58: N | K58: 2438.4 x 127 x 11 | L58: =K58 -> 2438.4 x 127 x 11 | M58: 1.5 | N58: 1.5 | O58: 392111 | P58: 1 | Q58: KA04,MTN9 | R58: 968.74576 | S58: =2000 -> 2000 | V58: Charcoal (PS)-Brown-Wood Grain-PN 03556 || 8 ft x 5 inch
A59: HIF | B59: Wall Panel | C59: India | G59: WHSWPLCS058 | H59: Charcoal PS-Oak-Wood Grain-PN 05855 | I59: =len(H59) -> 35 | J59: N | K59: 2438.4 x 127 x 11 | L59: =K59 -> 2438.4 x 127 x 11 | M59: 1.5 | N59: 1.5 | O59: 392111 | P59: 1 | Q59: KA04,MTN9 | R59: 670.44068 | S59: 1500 | V59: Charcoal (PS)-Oak-Wood Grain-PN 05855 || 8 ft x 5 inch
A60: HIF | B60: Wall Panel | C60: India | G60: WHSWPLCS059 | H60: Charcoal PS-Teak-Wood Grain-PN 04075 | I60: =len(H60) -> 36 | J60: N | K60: 2438.4 x 203.2 x 14 | L60: =K60 -> 2438.4 x 203.2 x 14 | M60: 1.5 | N60: 1.5 | O60: 39269099 | P60: 1 | Q60: KA04,MTN9 | R60: 595.86441 | S60: 1500 | V60: Charcoal (PS)-Teak-Wood Grain-PN 04075 || 8 ft x 8 inch
A61: HIF | B61: Wall Panel | C61: India | G61: WHSWPLCS060 | H61: Charcoal PS-Pine-Wood Grain-PN 04073 | I61: =len(H61) -> 36 | J61: N | K61: 2438.4 x 203.2 x 14 | L61: =K61 -> 2438.4 x 203.2 x 14 | M61: 1.5 | N61: 1.5 | O61: 39269099 | P61: 1 | Q61: KA04,MTN9 | R61: 677.28814 | S61: =1500 -> 1500 | V61: Charcoal (PS)-Pine-Wood Grain-PN 04073 || 8 ft x 8 inch
A62: HIF | B62: Wall Panel | C62: India | G62: WHSWPLCS061 | H62: Charcoal PS-Light-Wood Grain-PN 04072 | I62: =len(H62) -> 37 | J62: N | K62: 2438.4 x 203.2 x 14 | L62: =K62 -> 2438.4 x 203.2 x 14 | M62: 1.5 | N62: 1.5 | O62: 39269099 | P62: 1 | Q62: KA04,MTN9 | R62: 677.28814 | S62: =1500 -> 1500 | V62: Charcoal (PS)-Light-Wood Grain-PN 04072 || 8 ft x 8 inch
A63: HIF | B63: Wall Panel | C63: India | G63: WHSWPLCS062 | H63: Charcoal PS-Teak-Wood Grain-PN 02339 | I63: =len(H63) -> 36 | J63: N | K63: 2438.4 x 149.86 x 8 | L63: =K63 -> 2438.4 x 149.86 x 8 | M63: 1.5 | N63: 1.5 | O63: 39269099 | P63: 1 | Q63: KA04,MTN9 | R63: 1161.1017 | S63: =2500 -> 2500 | V63: Charcoal (PS)-Teak-Wood Grain-PN 02339 || 8 ft x 5.9 inch
A64: HIF | B64: Wall Panel | C64: India | G64: WHSWPLCS063 | H64: Charcoal PS-Medium-Wood Grain-PN 03214 | I64: =len(H64) -> 38 | J64: N | K64: 2438.4 x 203.2 x 14 | L64: =K64 -> 2438.4 x 203.2 x 14 | M64: 1.5 | N64: 1.5 | O64: 39269099 | P64: 1 | Q64: KA04,MTN9 | R64: 595.86441 | S64: 1500 | V64: Charcoal (PS)-Medium-Wood Grain-PN 03214 || 8 ft x 8 inch
A65: HIF | B65: Wall Panel | C65: India | G65: WHSWPLCS064 | H65: Charcoal PS-Beige-Matte-PN 05296 | I65: =len(H65) -> 32 | J65: N | K65: 2438.4 x 203.2 x 14 | L65: =K65 -> 2438.4 x 203.2 x 14 | M65: 1.5 | N65: 1.5 | O65: 39269099 | P65: 1 | Q65: KA04,MTN9 | R65: 609.49153 | S65: 1500 | V65: Charcoal (PS)-Beige-Matte-PN 05296 || 8 ft x 8 inch
A66: HIF | B66: Wall Panel | C66: India | G66: WHSWPLCS065 | H66: Charcoal PS-Grey-Matte-PN 05375 | I66: =len(H66) -> 31 | J66: N | K66: 2438.4 x 203.2 x 14 | L66: =K66 -> 2438.4 x 203.2 x 14 | M66: 1.5 | N66: 1.5 | O66: 39269099 | P66: 1 | Q66: KA04,MTN9 | R66: 595.86441 | S66: 1500 | V66: Charcoal (PS)-Grey-Matte-PN 05375 || 8 ft x 8 inch
A67: HIF | B67: Wall Panel | C67: India | G67: WHSWPLCS066 | H67: Charcoal PS-Pine-Wood Grain-PN 03022 | I67: =len(H67) -> 36 | J67: N | K67: 2895.6 x 203.2 x 14 | L67: =K67 -> 2895.6 x 203.2 x 14 | M67: 1.5 | N67: 1.5 | O67: 39269099 | P67: 1 | Q67: KA04,MTN9 | R67: 609.49153 | S67: 1500 | V67: Charcoal (PS)-Pine-Wood Grain-PN 03022 || 9.5 ft x 8 inch
A68: HIF | B68: Wall Panel | C68: India | G68: WHSWPLCS067 | H68: Charcoal PS-White-Matte-PN 05383 | I68: =len(H68) -> 32 | J68: N | K68: 2895.6 x 203.2 x 14 | L68: =K68 -> 2895.6 x 203.2 x 14 | M68: 1.5 | N68: 1.5 | O68: 39269099 | P68: 1 | Q68: KA04,MTN9 | R68: 595.86441 | S68: 1500 | V68: Charcoal (PS)-White-Matte-PN 05383 || 9.5 ft x 8 inch
A69: HIF | B69: Wall Panel | C69: India | G69: WHSWPLCS068 | H69: Charcoal PS-Pine-Wood Grain-PN 05350 | I69: =len(H69) -> 36 | J69: N | K69: 2895.6 x 203.2 x 14 | L69: =K69 -> 2895.6 x 203.2 x 14 | M69: 1.5 | N69: 1.5 | O69: 39269099 | P69: 1 | Q69: KA04,MTN9 | R69: 595.86441 | S69: 1500 | V69: Charcoal (PS)-Pine-Wood Grain-PN 05350 || 9.5 ft x 8 inch
A70: HIF | B70: Wall Panel | C70: India | G70: WHSWPLCS069 | H70: Charcoal PS-Brown-Wood Grain-PN 05334 | I70: =len(H70) -> 37 | J70: N | K70: 2895.6 x 203.2 x 14 | L70: =K70 -> 2895.6 x 203.2 x 14 | M70: 1.5 | N70: 1.5 | O70: 39269099 | P70: 1 | Q70: KA04,MTN9 | R70: 595.86441 | S70: 1500 | V70: Charcoal (PS)-Brown-Wood Grain-PN 05334 || 9.5 ft x 8 inch
A71: HIF | B71: Wall Panel | C71: India | G71: WHSWPLCS070 | H71: Charcoal PS-Pine-Wood Grain-PN 05328 | I71: =len(H71) -> 36 | J71: N | K71: 2895.6 x 203.2 x 14 | L71: =K71 -> 2895.6 x 203.2 x 14 | M71: 1.5 | N71: 1.5 | O71: 39269099 | P71: 1 | Q71: KA04,MTN9 | R71: 1117.8983 | S71: 2500 | V71: Charcoal (PS)-Pine-Wood Grain-PN 05328 || 9.5 ft x 8 inch
A72: HIF | B72: Wall Panel | C72: India | G72: WHSWPLCS071 | H72: Charcoal PS-Beige-Matte-PN 02796 | I72: =len(H72) -> 32 | J72: N | K72: 2895.6 x 203.2 x 14 | L72: =K72 -> 2895.6 x 203.2 x 14 | M72: 1.5 | N72: 1.5 | O72: 39259090 | P72: 1 | Q72: KA04,MTN9 | R72: 1117.8983 | S72: 2500 | V72: Charcoal (PS)-Beige-Matte-PN 02796 || 9.5 ft x 8 inch
A73: HIF | B73: Wall Panel | C73: India | G73: WHSWPLCS072 | H73: Charcoal PS-Cream-Matte-PN 05380 | I73: =len(H73) -> 32 | J73: N | K73: 2895.6 x 203.2 x 14 | L73: =K73 -> 2895.6 x 203.2 x 14 | M73: 1.5 | N73: 1.5 | O73: 39269099 | P73: 1 | Q73: KA04,MTN9 | R73: 595.86441 | S73: 1500 | V73: Charcoal (PS)-Cream-Matte-PN 05380 || 9.5 ft x 8 inch
A74: HIF | B74: Wall Panel | C74: India | G74: WHSWPLCS073 | H74: Charcoal PS-Brown-Wood Grain-PN 02754 | I74: =len(H74) -> 37 | J74: N | K74: 2438.4 x 127 x 12 | L74: =K74 -> 2438.4 x 127 x 12 | M74: 1.5 | N74: 1.5 | O74: 39259090 | P74: 1 | Q74: KA04,MTN9 | R74: 745.08475 | S74: =1500 -> 1500 | V74: Charcoal (PS)-Brown-Wood Grain-PN 02754 || 8 ft x 5 inch
A75: HIF | B75: Wall Panel | C75: India | G75: WHSWPLCS074 | H75: Charcoal PS-Grey-Matte-PN 02759 | I75: =len(H75) -> 31 | J75: N | K75: 2438.4 x 127 x 12 | L75: =K75 -> 2438.4 x 127 x 12 | M75: 1.5 | N75: 1.5 | O75: 39259090 | P75: 1 | Q75: KA04,MTN9 | R75: 745.08475 | S75: =1500 -> 1500 | V75: Charcoal (PS)-Grey-Matte-PN 02759 || 8 ft x 5 inch
A76: HIF | B76: Wall Panel | C76: India | G76: WHSWPLCS075 | H76: Charcoal PS-Walnut-Wood Grain-PN 03026 | I76: =len(H76) -> 38 | J76: N | K76: 2438.4 x 127 x 12 | L76: =K76 -> 2438.4 x 127 x 12 | M76: 1.5 | N76: 1.5 | O76: 39269099 | P76: 1 | Q76: KA04,MTN9 | R76: 609.49153 | S76: 1500 | V76: Charcoal (PS)-Walnut-Wood Grain-PN 03026 || 8 ft x 5 inch
A77: HIF | B77: Wall Panel | C77: India | G77: WHSWPLCS076 | H77: Charcoal PS-Dark-Wood Grain-PN 03027 | I77: =len(H77) -> 36 | J77: N | K77: 2438.4 x 127 x 12 | L77: =K77 -> 2438.4 x 127 x 12 | M77: 1.5 | N77: 1.5 | O77: 39269099 | P77: 1 | Q77: KA04,MTN9 | R77: 609.49153 | S77: 1500 | V77: Charcoal (PS)-Dark-Wood Grain-PN 03027 || 8 ft x 5 inch
A78: HIF | B78: Wall Panel | C78: India | G78: WHSWPLCS077 | H78: Charcoal PS-Beige-Matte-PN 00138 | I78: =len(H78) -> 32 | J78: N | K78: 2438.4 x 127 x 12 | L78: =K78 -> 2438.4 x 127 x 12 | M78: 1.5 | N78: 1.5 | O78: 39269099 | P78: 1 | Q78: KA04,MTN9 | R78: 677.28814 | S78: =1500 -> 1500 | V78: Charcoal (PS)-Beige-Matte-PN 00138 || 8 ft x 5 inch
A79: HIF | B79: Wall Panel | C79: India | G79: WHSWPLCS078 | H79: Charcoal PS-Brown-Wood Grain-PN 05755 | I79: =len(H79) -> 37 | J79: N | K79: 2438.4 x 127 x 12 | L79: =K79 -> 2438.4 x 127 x 12 | M79: 1.5 | N79: 1.5 | O79: 39269099 | P79: 1 | Q79: KA04,MTN9 | R79: 1016.2712 | S79: 2500 | V79: Charcoal (PS)-Brown-Wood Grain-PN 05755 || 8 ft x 5 inch
A80: HIF | B80: Wall Panel | C80: India | G80: WHSWPLCS079 | H80: Charcoal PS-Brown-Wood Grain-PN 03399 | I80: =len(H80) -> 37 | J80: N | K80: 2438.4 x 127 x 10 | L80: =K80 -> 2438.4 x 127 x 10 | M80: 1.5 | N80: 1.5 | O80: 392111 | P80: 1 | Q80: KA04,MTN9 | R80: 894.16949 | S80: =2000 -> 2000 | V80: Charcoal (PS)-Brown-Wood Grain-PN 03399 || 8 ft x 5 inch
A81: HIF | B81: Wall Panel | C81: India | G81: WHSWPLCS080 | H81: Charcoal PS-Grey-Matte-PN 05472 | I81: =len(H81) -> 31 | J81: N | K81: 2438.4 x 127 x 10 | L81: =K81 -> 2438.4 x 127 x 10 | M81: 1.5 | N81: 1.5 | O81: 39269099 | P81: 1 | Q81: KA04,MTN9 | R81: 595.86441 | S81: 1500 | V81: Charcoal (PS)-Grey-Matte-PN 05472 || 8 ft x 5 inch
A82: HIF | B82: Wall Panel | C82: India | G82: WHSWPLCS081 | H82: Charcoal PS-Beige-Matte-PN 06446 | I82: =len(H82) -> 32 | J82: N | K82: 2438.4 x 127 x 10 | L82: =K82 -> 2438.4 x 127 x 10 | M82: 1.5 | N82: 1.5 | O82: 39269099 | P82: 1 | Q82: KA04,MTN9 | R82: 745.01695 | S82: =1500 -> 1500 | V82: Charcoal (PS)-Beige-Matte-PN 06446 || 8 ft x 5 inch
A83: HIF | B83: Wall Panel | C83: India | G83: WHSWPLCS082 | H83: Charcoal PS-Dark-Wood Grain-PN 02743 | I83: =len(H83) -> 36 | J83: N | K83: 2438.4 x 127 x 10 | L83: =K83 -> 2438.4 x 127 x 10 | M83: 1.5 | N83: 1.5 | O83: 39259090 | P83: 1 | Q83: KA04,MTN9 | R83: 745.08475 | S83: =1500 -> 1500 | V83: Charcoal (PS)-Dark-Wood Grain-PN 02743 || 8 ft x 5 inch
A84: HIF | B84: Wall Panel | C84: India | G84: WHSWPLCS083 | H84: Charcoal PS-Pine-Wood Grain-PN 06812 | I84: =len(H84) -> 36 | J84: N | K84: 2438.4 x 127 x 10 | L84: =K84 -> 2438.4 x 127 x 10 | M84: 1.5 | N84: 1.5 | O84: 39259090 | P84: 1 | Q84: KA04,MTN9 | R84: 894.16949 | S84: =2000 -> 2000 | V84: Charcoal (PS)-Pine-Wood Grain-PN 06812 || 8 ft x 5 inch
A85: HIF | B85: Wall Panel | C85: India | G85: WHSWPLCS084 | H85: Charcoal PS-Cream-Matte-PN 00808 | I85: =len(H85) -> 32 | J85: N | K85: 2438.4 x 127 x 10 | L85: =K85 -> 2438.4 x 127 x 10 | M85: 1.5 | N85: 1.5 | O85: 39269099 | P85: 1 | Q85: KA04,MTN9 | R85: 745.01695 | S85: =1500 -> 1500 | V85: Charcoal (PS)-Cream-Matte-PN 00808 || 8 ft x 5 inch
A86: HIF | B86: Wall Panel | C86: India | G86: WHSWPLCS085 | H86: Charcoal PS-Black-Matte-PN 04886 | I86: =len(H86) -> 32 | J86: N | K86: 2438.4 x 127 x 10 | L86: =K86 -> 2438.4 x 127 x 10 | M86: 1.5 | N86: 1.5 | O86: 39269099 | P86: 1 | Q86: KA04,MTN9 | R86: 745.01695 | S86: =1500 -> 1500 | V86: Charcoal (PS)-Black-Matte-PN 04886 || 8 ft x 5 inch
A87: HIF | B87: Wall Panel | C87: India | G87: WHSWPLCS086 | H87: Charcoal PS-Brown-Wood Grain-PN 04881 | I87: =len(H87) -> 37 | J87: N | K87: 2438.4 x 127 x 10 | L87: =K87 -> 2438.4 x 127 x 10 | M87: 1.5 | N87: 1.5 | O87: 39269099 | P87: 1 | Q87: KA04,MTN9 | R87: 745.01695 | S87: =1500 -> 1500 | V87: Charcoal (PS)-Brown-Wood Grain-PN 04881 || 8 ft x 5 inch
A88: HIF | B88: Wall Panel | C88: India | G88: WHSWPLCS087 | H88: Charcoal PS-Teak-Wood Grain-PN 04882 | I88: =len(H88) -> 36 | J88: N | K88: 2438.4 x 127 x 10 | L88: =K88 -> 2438.4 x 127 x 10 | M88: 1.5 | N88: 1.5 | O88: 39269099 | P88: 1 | Q88: KA04,MTN9 | R88: 609.49153 | S88: 1500 | V88: Charcoal (PS)-Teak-Wood Grain-PN 04882 || 8 ft x 5 inch
A89: HIF | B89: Wall Panel | C89: India | G89: WHSWPLCS088 | H89: Charcoal PS-Walnut-Wood Grain-PN 04598 | I89: =len(H89) -> 38 | J89: N | K89: 2438.4 x 127 x 10 | L89: =K89 -> 2438.4 x 127 x 10 | M89: 1.5 | N89: 1.5 | O89: 39269099 | P89: 1 | Q89: KA04,MTN9 | R89: 948.47458 | S89: =2000 -> 2000 | V89: Charcoal (PS)-Walnut-Wood Grain-PN 04598 || 8 ft x 5 inch
A90: HIF | B90: Wall Panel | C90: India | G90: WHSWPLCS089 | H90: Charcoal PS-Oak-Wood Grain-PN 04561 | I90: =len(H90) -> 35 | J90: N | K90: 2438.4 x 127 x 10 | L90: =K90 -> 2438.4 x 127 x 10 | M90: 1.5 | N90: 1.5 | O90: 39269099 | P90: 1 | Q90: KA04,MTN9 | R90: 948.47458 | S90: =2000 -> 2000 | V90: Charcoal (PS)-Oak-Wood Grain-PN 04561 || 8 ft x 5 inch
A91: HIF | B91: Wall Panel | C91: India | G91: WHSWPLCS090 | H91: Charcoal PS-Medium-Wood Grain-PN 03914 | I91: =len(H91) -> 38 | J91: N | K91: 2438.4 x 127 x 10 | L91: =K91 -> 2438.4 x 127 x 10 | M91: 1.5 | N91: 1.5 | O91: 39269099 | P91: 1 | Q91: KA04,MTN9 | R91: 711.18644 | S91: =1500 -> 1500 | V91: Charcoal (PS)-Medium-Wood Grain-PN 03914 || 8 ft x 5 inch
A92: HIF | B92: Wall Panel | C92: India | G92: WHSWPLCS091 | H92: Charcoal PS-Walnut-Wood Grain-PN 03908 | I92: =len(H92) -> 38 | J92: N | K92: 2438.4 x 127 x 10 | L92: =K92 -> 2438.4 x 127 x 10 | M92: 1.5 | N92: 1.5 | O92: 39269099 | P92: 1 | Q92: KA04,MTN9 | R92: 711.18644 | S92: =1500 -> 1500 | V92: Charcoal (PS)-Walnut-Wood Grain-PN 03908 || 8 ft x 5 inch
A93: HIF | B93: Wall Panel | C93: India | G93: WHSWPLCS092 | H93: Charcoal PS-Beige-Matte-PN 03911 | I93: =len(H93) -> 32 | J93: N | K93: 2438.4 x 127 x 10 | L93: =K93 -> 2438.4 x 127 x 10 | M93: 1.5 | N93: 1.5 | O93: 39269099 | P93: 1 | Q93: KA04,MTN9 | R93: 711.18644 | S93: =1500 -> 1500 | V93: Charcoal (PS)-Beige-Matte-PN 03911 || 8 ft x 5 inch
A94: HIF | B94: Wall Panel | C94: India | G94: WHSWPLCS093 | H94: Charcoal PS-Oak-Wood Grain-PN 03917 | I94: =len(H94) -> 35 | J94: N | K94: 2438.4 x 127 x 10 | L94: =K94 -> 2438.4 x 127 x 10 | M94: 1.5 | N94: 1.5 | O94: 39269099 | P94: 1 | Q94: KA04,MTN9 | R94: 711.18644 | S94: =1500 -> 1500 | V94: Charcoal (PS)-Oak-Wood Grain-PN 03917 || 8 ft x 5 inch
A95: HIF | B95: Wall Panel | C95: India | G95: WHSWPLCS094 | H95: Charcoal PS-Ivory-Matte-PN 03912 | I95: =len(H95) -> 32 | J95: N | K95: 2438.4 x 127 x 10 | L95: =K95 -> 2438.4 x 127 x 10 | M95: 1.5 | N95: 1.5 | O95: 39269099 | P95: 1 | Q95: KA04,MTN9 | R95: 711.18644 | S95: =1500 -> 1500 | V95: Charcoal (PS)-Ivory-Matte-PN 03912 || 8 ft x 5 inch
A96: HIF | B96: Wall Panel | C96: India | G96: WHSWPLCS095 | H96: Charcoal PS-White-Matte-PN 03918 | I96: =len(H96) -> 32 | J96: N | K96: 2438.4 x 127 x 10 | L96: =K96 -> 2438.4 x 127 x 10 | M96: 1.5 | N96: 1.5 | O96: 39269099 | P96: 1 | Q96: KA04,MTN9 | R96: 711.18644 | S96: =1500 -> 1500 | V96: Charcoal (PS)-White-Matte-PN 03918 || 8 ft x 5 inch
A97: HIF | B97: Wall Panel | C97: India | G97: WHSWPLCS096 | H97: Charcoal PS-Brown-Wood Grain-PN 05509 | I97: =len(H97) -> 37 | J97: N | K97: 2438.4 x 127 x 10 | L97: =K97 -> 2438.4 x 127 x 10 | M97: 1.5 | N97: 1.5 | O97: 392590 | P97: 1 | Q97: KA04,MTN9 | R97: 595.86441 | S97: 1500 | V97: Charcoal (PS)-Brown-Wood Grain-PN 05509 || 8 ft x 5 inch
A98: HIF | B98: Wall Panel | C98: India | G98: WHSWPLCS097 | H98: Charcoal PS-Dark-Wood Grain-PN 03173 | I98: =len(H98) -> 36 | J98: N | K98: 2438.4 x 127 x 10 | L98: =K98 -> 2438.4 x 127 x 10 | M98: 1.5 | N98: 1.5 | O98: 392111 | P98: 1 | Q98: KA04,MTN9 | R98: 894.16949 | S98: =2000 -> 2000 | V98: Charcoal (PS)-Dark-Wood Grain-PN 03173 || 8 ft x 5 inch
A99: HIF | B99: Wall Panel | C99: India | G99: WHSWPLCS098 | H99: Charcoal PS-Walnut-Wood Grain-PN 00554 | I99: =len(H99) -> 38 | J99: N | K99: 2438.4 x 127 x 10 | L99: =K99 -> 2438.4 x 127 x 10 | M99: 1.5 | N99: 1.5 | O99: 392690 | P99: 1 | Q99: KA04,MTN9 | R99: 745.08475 | S99: =1500 -> 1500 | V99: Charcoal (PS)-Walnut-Wood Grain-PN 00554 || 8 ft x 5 inch
A100: HIF | B100: Wall Panel | C100: India | G100: WHSWPLCS099 | H100: Charcoal PS-Grey-Matte-PN 00909 | I100: =len(H100) -> 31 | J100: N | K100: 2438.4 x 127 x 10 | L100: =K100 -> 2438.4 x 127 x 10 | M100: 1.5 | N100: 1.5 | O100: 392690 | P100: 1 | Q100: KA04,MTN9 | R100: 745.08475 | S100: =1500 -> 1500 | V100: Charcoal (PS)-Grey-Matte-PN 00909 || 8 ft x 5 inch
...

Sheet Copy of Designs
A1: Sno | B1: design_name | C1: design_code | D1: published | E1: active
A2: 1 | B2: BR-1-1 | C2: BR-1-1 | D2: No | E2: Yes
A3: 2 | B3: BR-1-2 | C3: BR-1-2 | D3: No | E3: Yes
A4: 3 | B4: BR-2-1 | C4: BR-2-1 | D4: No | E4: Yes
A5: 4 | B5: BR-2-2 | C5: BR-2-2 | D5: No | E5: Yes
A6: 5 | B6: Noctis Haven (BR-3-1) | C6: BR-3-1 | D6: Yes | E6: Yes
A7: 6 | B7: Caelum Nest (BR-3-2) | C7: BR-3-2 | D7: Yes | E7: Yes
A8: 7 | B8: Amber Silence (BR-4-1) | C8: BR-4-1 | D8: Yes | E8: Yes
A9: 8 | B9: Elaris Woodline (BR-4-2) | C9: BR-4-2 | D9: Yes | E9: Yes
A10: 9 | B10: BR-5-1 | C10: BR-5-1 | D10: No | E10: Yes
A11: 10 | B11: BR-5-2 | C11: BR-5-2 | D11: No | E11: Yes
A12: 11 | B12: Solstice Haven (BR-6-1) | C12: BR-6-1 | D12: Yes | E12: Yes
A13: 12 | B13: Morvane Essence (BR-6-2) | C13: BR-6-2 | D13: Yes | E13: Yes
... A122: 121 | B122: Velorian Nest (BR-39) | C122: BR-39 | D122: Yes | E122: Yes

Sheet Copy of Material
A1: sno | B1: material_name | C1: material_type | D1: material_crm_code | E1: material_sap_code | F1: Price
A2: 1 | B2: Charcoal (PS)-Cream-Matte-PN 06167 || 8 ft x 5 inch | C2: material | D2: WHSWPLCS017 | E2: WHSWPLCS017 | F2: 2500
A3: 2 | B3: Charcoal (PS)-Pine-Wood Grain-PN 03221 || 8 ft x 5 inch | C3: material | D3: WHSWPLCS020 | E3: WHSWPLCS020 | F3: 1500
A4: 3 | B4: Charcoal (PS)-Light-Wood Grain-PN 06277 || 8 ft x 5 inch | C4: material | D4: WHSWPLCS103 | E4: WHSWPLCS103 | F4: 1500
A5: 4 | B5: Charcoal (PS)-Brown-Wood Grain-PN 03399 || 8 ft x 5 inch | C5: material | D5: WHSWPLCS079 | E5: WHSWPLCS079 | F5: 2000
A6: 5 | B6: 240 LED strip light (5m) | C6: material | D6: WHSWLTLEDS164 | E6: WHSWLTLEDS164 | F6: 1500
A7: 6 | B7: 16X16 Alumnium Angular Profile (3m) || 16 x 16 mm | C7: material | D7: WHSWLTLEDS165 | E7: WHSWLTLEDS165 | F7: 500
A8: 7 | B8: 10 AMP (24V) LED Power Adapter | C8: material | D8: WHSWLTLEDS167 | E8: WHSWLTLEDS167 | F8: 1500
A9: 8 | B9: Aluminium channels reactangular 1 mm || 12 ft x 50 mm | C9: material | D9: WHSWCHALS162 | E9: WHSWCHALS162 | F9: 1000
A10: 9 | B10: PVC board 11 mm || 8 ft x 4 ft | C10: material | D10: WHSWBDPS161 | E10: WHSWBDPS161 | F10: 2500
A11: 10 | B11: Wall Bidding WPC 08 | C11: material | D11: WHSWBIW08S223 | E11: WHSWBIW08S223 | F11: 500
A12: 11 | B12: Charcoal (PS)-Dark-Wood Grain-PN 02746 || 9.5 ft x 4.8 inch | C12: material | D12: WHSWPLCS042 | E12: WHSWPLCS042 | F12: 2000
A13: 12 | B13: Wall Bidding WPC 01 | C13: material | D13: WHSWBIW01S216 | E13: WHSWBIW01S216 | F13: 500
... A94: 93 | B94: Silicon sealant glue | C94: material | D94: WHSWGLSS168 | E94: WHSWGLSS168 | F94: 500

Sheet Copy of Mapping
A1: sno | B1: design_code | C1: material_crm_code | D1: material_md_code | E1: qty | F1: Price
B2: BR-1-1 | C2: WHSWPLCS017 | D2: 6167 | E2: 0 | F2: 2500
B3: BR-1-2 | C3: WHSWPLCS020 | D3: 3221 | E3: 0 | F3: 1500
B4: BR-2-1 | C4: WHSWPLCS103 | D4: 6277 | E4: 0 | F4: 1500
B5: BR-2-2 | C5: WHSWPLCS079 | D5: 3399 | E5: 0 | F5: 2000
B6: BR-3-1 | C6: WHSWPLCS017 | D6: 6167 | E6: 5 | F6: 2500
B7: BR-3-1 | C7: WHSWLTLEDS164 | D7: LED-1 | E7: 1 | F7: 1500
B8: BR-3-1 | C8: WHSWLTLEDS165 | D8: AL-1 | E8: 1 | F8: 500
B9: BR-3-1 | C9: WHSWLTLEDS167 | D9: PA-1 | E9: 1 | F9: 1500
B10: BR-3-1 | C10: WHSWCHALS162 | D10: ALC-1 | E10: 2 | F10: 1000
B11: BR-3-1 | C11: WHSWBDPS161 | D11: PVCBD-1 | E11: 1 | F11: 2500
B12: BR-3-1 | C12: WHSWBIW08S223 | D12: BD-08 | E12: 2 | F12: 500
B13: BR-3-2 | C13: WHSWPLCS042 | D13: 2746 | E13: 5 | F13: 2000
B14: BR-3-2 | C14: WHSWLTLEDS164 | D14: LED-1 | E14: 1 | F14: 1500
B15: BR-3-2 | C15: WHSWLTLEDS165 | D15: AL-1 | E15: 1 | F15: 500
B16: BR-3-2 | C16: WHSWLTLEDS167 | D16: PA-1 | E16: 1 | F16: 1500
B17: BR-3-2 | C17: WHSWCHALS162 | D17: ALC-1 | E17: 2 | F17: 1000
B18: BR-3-2 | C18: WHSWBDPS161 | D18: PVCBD-1 | E18: 1 | F18: 2500
B19: BR-3-2 | C19: WHSWBIW01S216 | D19: BD-01 | E19: 2 | F19: 500
B20: BR-4-1 | C20: WHSWPLCS021 | D20: 3223 | E20: 10 | F20: 1500
B21: BR-4-1 | C21: WHSWLTLEDS164 | D21: LED-1 | E21: 1 | F21: 1500
B22: BR-4-1 | C22: WHSWLTLEDS165 | D22: AL-1 | E22: 1 | F22: 500
B23: BR-4-1 | C23: WHSWLTLEDS167 | D23: PA-1 | E23: 1 | F23: 1500
B24: BR-4-1 | C24: WHSWCHALS162 | D24: ALC-1 | E24: 2 | F24: 1000
B25: BR-4-1 | C25: WHSWBDPS161 | D25: PVCBD-1 | E25: 2 | F25: 2500
B26: BR-4-1 | C26: WHSWSSBWBLWS171 | D26: SB | E26: 2 | F26: 1000
B27: BR-4-1 | C27: WHSWSRBWBLWS181 | D27: Shelf | E27: 1 | F27: 1000
B28: BR-4-1 | C28: WHSWBIW01S216 | D28: BD-01 | E28: 2 | F28: 500
B29: BR-4-2 | C29: WHSWPLCS055 | D29: 5656 | E29: 10 | F29: 2000
B30: BR-4-2 | C30: WHSWLTLEDS164 | D30: LED-1 | E30: 1 | F30: 1500
B31: BR-4-2 | C31: WHSWLTLEDS165 | D31: AL-1 | E31: 1 | F31: 500
B32: BR-4-2 | C32: WHSWLTLEDS167 | D32: PA-1 | E32: 1 | F32: 1500
B33: BR-4-2 | C33: WHSWCHALS162 | D33: ALC-1 | E33: 2 | F33: 1000
B34: BR-4-2 | C34: WHSWBDPS161 | D34: PVCBD-1 | E34: 2 | F34: 2500
B35: BR-4-2 | C35: WHSWSSBWBLWS171 | D35: SB | E35: 2 | F35: 1000
B36: BR-4-2 | C36: WHSWSRBWBLWS181 | D36: Shelf | E36: 1 | F36: 1000
B37: BR-4-2 | C37: WHSWBIW03S218 | D37: BD-03 | E37: 2 | F37: 500
B38: BR-5-1 | C38: WHSWPLCS106 | D38: 3889 | E38: 20 | F38: 1500
B39: BR-5-2 | C39: WHSWPLCS020 | D39: 3221 | E39: 20 | F39: 1500
B40: BR-6-1 | C40: WHSWPLCS025 | D40: 545 | E40: 20 | F40: 2000
B41: BR-6-1 | C41: WHSWLTLEDS164 | D41: LED-1 | E41: 1 | F41: 1500
B42: BR-6-1 | C42: WHSWLTLEDS165 | D42: AL-1 | E42: 1 | F42: 500
B43: BR-6-1 | C43: WHSWLTLEDS167 | D43: PA-1 | E43: 1 | F43: 1500
B44: BR-6-1 | C44: WHSWCHALS162 | D44: ALC-1 | E44: 2 | F44: 1000
B45: BR-6-1 | C45: WHSWBDPS161 | D45: PVCBD-1 | E45: 3 | F45: 2500
B46: BR-6-1 | C46: WHSWSSBWBLWS171 | D46: SB | E46: 4 | F46: 1000
B47: BR-6-1 | C47: WHSWBIW02S217 | D47: BD-02 | E47: 2 | F47: 500
B48: BR-6-2 | C48: WHSWPLCS102 | D48: 5667 | E48: 20 | F48: 1500
B49: BR-6-2 | C49: WHSWLTLEDS164 | D49: LED-1 | E49: 1 | F49: 1500
B50: BR-6-2 | C50: WHSWLTLEDS165 | D50: AL-1 | E50: 1 | F50: 500
B51: BR-6-2 | C51: WHSWLTLEDS167 | D51: PA-1 | E51: 1 | F51: 1500
B52: BR-6-2 | C52: WHSWCHALS162 | D52: ALC-1 | E52: 2 | F52: 1000
B53: BR-6-2 | C53: WHSWBDPS161 | D53: PVCBD-1 | E53: 3 | F53: 2500
B54: BR-6-2 | C54: WHSWSSBWBLWS171 | D54: SB | E54: 4 | F54: 1000
B55: BR-6-2 | C55: WHSWBIW01S216 | D55: BD-01 | E55: 2 | F55: 500
B56: BR-7-1 | C56: WHSWPLCS076 | D56: 3027 | E56: 20 | F56: 1500
B57: BR-7-2 | C57: WHSWPLCS051 | D57: 149 | E57: 20 | F57: 1500
B58: BR-8-1 | C58: WHSWPLCS029 | D58: 155 | E58: 14 | F58: 1500
B59: BR-8-1 | C59: WHSWLTLEDS164 | D59: LED-1 | E59: 2 | F59: 1500
B60: BR-8-1 | C60: WHSWLTLEDS165 | D60: AL-1 | E60: 2 | F60: 500
B61: BR-8-1 | C61: WHSWLTLEDS167 | D61: PA-1 | E61: 2 | F61: 1500
B62: BR-8-1 | C62: WHSWCHALS162 | D62: ALC-1 | E62: 2 | F62: 1000
B63: BR-8-1 | C63: WHSWBDPS161 | D63: PVCBD-1 | E63: 4 | F63: 2500
B64: BR-8-1 | C64: WHSWSSBWBMWS172 | D64: SB | E64: 4 | F64: 1000
B65: BR-8-1 | C65: WHSWBIW03S218 | D65: BD-03 | E65: 2 | F65: 500
B66: BR-8-2 | C66: WHSWPLCS051 | D66: 149 | E66: 14 | F66: 1500
B67: BR-8-2 | C67: WHSWLTLEDS164 | D67: LED-1 | E67: 2 | F67: 1500
B68: BR-8-2 | C68: WHSWLTLEDS165 | D68: AL-1 | E68: 2 | F68: 500
B69: BR-8-2 | C69: WHSWLTLEDS167 | D69: PA-1 | E69: 2 | F69: 1500
B70: BR-8-2 | C70: WHSWCHALS162 | D70: ALC-1 | E70: 2 | F70: 1000
B71: BR-8-2 | C71: WHSWBDPS161 | D71: PVCBD-1 | E71: 4 | F71: 2500
B72: BR-8-2 | C72: WHSWSSBWBMWS172 | D72: SB | E72: 4 | F72: 1000
B73: BR-8-2 | C73: WHSWBIW02S217 | D73: BD-02 | E73: 2 | F73: 500
B74: BR-12-1 | C74: WHSWPLCS102 | D74: 5667 | E74: 12 | F74: 1500
B75: BR-12-1 | C75: WHSWLTLEDS164 | D75: LED-1 | E75: 2 | F75: 1500
B76: BR-12-1 | C76: WHSWLTLEDS165 | D76: AL-1 | E76: 2 | F76: 500
B77: BR-12-1 | C77: WHSWLTLEDS167 | D77: PA-1 | E77: 2 | F77: 1500
B78: BR-12-1 | C78: WHSWCHALS162 | D78: ALC-1 | E78: 2 | F78: 1000
B79: BR-12-1 | C79: WHSWBDPS161 | D79: PVCBD-1 | E79: 2 | F79: 2500
B80: BR-12-1 | C80: WHSWSRBWBLWS181 | D80: RB | E80: 2 | F80: 1000
B81: BR-12-1 | C81: WHSWS300SLWS191 | D81: Shelf | E81: 1 | F81: 1000
B82: BR-12-1 | C82: WHSWBIW02S217 | D82: BD-02 | E82: 2 | F82: 500
B83: BR-13-1 | C83: WHSWPLCS036 | D83: 2347 | E83: 15 | F83: 2500
B84: BR-15-1 | C84: WHSWPLCPCS118 | D84: 2308 | E84: 3 | F84: 7500
B85: BR-15-1 | C85: WHSWLTLEDS164 | D85: LED-1 | E85: 1 | F85: 1500
B86: BR-15-1 | C86: WHSWLTLEDS165 | D86: AL-1 | E86: 1 | F86: 500
B87: BR-15-1 | C87: WHSWLTLEDS167 | D87: PA-1 | E87: 1 | F87: 1500
B88: BR-15-1 | C88: WHSWCHALS162 | D88: ALC-1 | E88: 2 | F88: 1000
B89: BR-15-1 | C89: WHSWBDPS161 | D89: PVCBD-1 | E89: 2 | F89: 2500
B90: BR-15-1 | C90: WHSWSSBWBMWS172 | D90: SB | E90: 3 | F90: 1000
B91: BR-15-1 | C91: WHSWS300SLWS191 | D91: Shelf | E91: 2 | F91: 1000
B92: BR-15-1 | C92: WHSWTSSBG6TS233 | D92: T-01 | E92: 3 | F92: 600
B93: BR-15-1 | C93: WHSWBIW02S217 | D93: BD-02 | E93: 2 | F93: 500
B94: BR-15-2 | C94: WHSWPLCPCS150 | D94: 2327 | E94: 3 | F94: 7500
B95: BR-15-2 | C95: WHSWLTLEDS164 | D95: LED-1 | E95: 1 | F95: 1500
B96: BR-15-2 | C96: WHSWLTLEDS165 | D96: AL-1 | E96: 1 | F96: 500
B97: BR-15-2 | C97: WHSWLTLEDS167 | D97: PA-1 | E97: 1 | F97: 1500
B98: BR-15-2 | C98: WHSWCHALS162 | D98: ALC-1 | E98: 1 | F98: 1000
B99: BR-15-2 | C99: WHSWBDPS161 | D99: PVCBD-1 | E99: 2 | F99: 2500
B100: BR-15-2 | C100: WHSWSSBWBMWS172 | D100: SB | E100: 3 | F100: 1000
...
